Workbook
Name TiposDeFuncao: Deflatores!$L$37:$L$64
Name TiposDeManutencao: Deflatores!$G$4:$G$38

Sheet Contagem
A1: Identificação da Contagem
A4: Empresa | F4: Secretaria de Estado de Planejamento e Gestão de Mato Grosso | O4: PF IFPUG | Q4: =Funções!L4 -> 5222
A5: Aplicação | O5: PF Local do EM | Q5: =Funções!L5 -> 5198
A6: Tipo de Contagem | F6: Projeto de Desenvolvimento | O6: PF Local da FS | Q6: =Funções!L6 -> 5088.8
A7: Nível de Detalhe | F7: Detalhada (IFPUG) | O7: Tecnologia | R7: Java
A8: Projeto | F8: SIABI - Sistema de Avaliação de Imóveis | O8: Versão do Guia | R8: 4.3.1
A9: Responsável | F9: Luana Alves de Araujo Passos Aguiar | O9: Criação | R9: 44844
A10: Revisor | O10: Revisão
A11: Propósito da Contagem
A12: Contagem de Pontos de Função para subsidiar o planejamento, execução e monitoramento do projeto <descrever o nome do projeto aqui> e atender os requisitos do CONTRATO Nº 014/2022/SEPLAG e seus anexos. Com destaque: - Dar suporte à análise de qualidade e produtividade; - Estimar o custo e recursos requeridos para o desenvolvimento, melhoria e manutenção do software; - Fornecer um fator de normalização para a comparação de software; - Determinar o tamanho de um pacote de aplicação adquirido, por meio do dimensionamento funcional de todas as funções incluídas no mesmo; - Ajudar os usuários a determinar o benefício provido por um pacote de aplicação para a sua organização, por meio do dimensionamento funcional das funções que correspondam especificamente aos seus requisitos.
A16: Escopo da Contagem
A17: Essa contagem contempla a primeira entrega das histórias de usuários especificadas do projeto SIABI - Sistema de Identificação de Imóveis, conforme listadas a seguir:
A21: Documentação Utilizada na Análise
A22: Para realizar a conagem de pontos de função em questão, foram utilizadas as histórias e usuários listadas a seguir:

Sheet Funções
A1: Planilha de contagem de ponto de função - Versão 2.4
A4: =Contagem!A5&" : "&Contagem!F5 -> Aplicação : | B4: =Contagem!A8&" : "&Contagem!F8 -> Projeto : SIABI - Sistema de Avaliação de Imóveis | K4: PF IFPUG | L4: =SUM(H9:J2458) -> 5222
A5: =Contagem!A9&" : "&Contagem!F9 -> Responsável : Luana Alves de Araujo Passos Aguiar | B5: =Contagem!A10&" : "&Contagem!F10 -> Revisor : | K5: PF Local do EM | L5: =SUM(K9:K2458) -> 5198
A6: =Contagem!A4&" : "&Contagem!F4 -> Empresa : Secretaria de Estado de Planejamento e Gestão de Mato Grosso | B6: ="Tipo da Contagem : "&Contagem!F6 -> Tipo da Contagem : Projeto de Desenvolvimento | K6: PF Local da FS | L6: =SUM(L9:L2082) -> 5088.8
A7: Nome da Função | B7: Tipo | C7: Manutenção | D7: TD | E7: AR/TR | F7: Complex. | G7: ctl | H7: PF IFPUG | I7: C | J7: ctl2 | K7: PF Local do EM | L7: PF Local da FS | M7: Pacote | N7: Referência | O7: Observações
A8: SIABI
A9: US 1 - Dados do Imóvel - Dados do imóvel | F9: =IF(ISBLANK(B9),"",IF(I9="L","Baixa",IF(I9="A","Média",IF(I9="","","Alta")))) | H9: =IF(ISBLANK(B9),"",IF(B9="ALI",IF(I9="L",7,IF(I9="A",10,15)),IF(B9="AIE",IF(I9="L",5,IF(I9="A",7,10)),IF(B9="SE",IF(I9="L",4,IF(I9="A",5,7)),IF(OR(B9="EE",B9="CE"),IF(I9="L",3,IF(I9="A",4,6)),0))))) | I9: =IF(OR(ISBLANK(D9),ISBLANK(E9)),IF(OR(B9="ALI",B9="AIE"),"L",IF(OR(B9="EE",B9="SE",B9="CE"),"A","")),IF(B9="EE",IF(E9>=3,IF(D9>=5,"H","A"),IF(E9>=2,IF(D9>=16,"H",IF(D9<=4,"L","A")),IF(D9<=15,"L","A"))),IF(OR(B9="SE",B9="CE"),IF(E9>=4,IF(D9>=6,"H","A"),IF(E9>=2,IF(D9>=20,"H",IF(D9<=5,"L","A")),IF(D9<=19,"L","A"))),IF(OR(B9="ALI",B9="AIE"),IF(E9>=6,IF(D9>=20,"H","A"),IF(E9>=2,IF(D9>=51,"H",IF(D9<=19,"L","A")),IF(D9<=50,"L","A"))),"")))) | J9: =CONCATENATE(B9,C9) | K9: =IF(OR(H9="",H9=0),L9,H9) | L9: =IF(NOT(ISERROR(VLOOKUP(B9,Deflatores!G$42:H$64,2,FALSE))),VLOOKUP(B9,Deflatores!G$42:H$64,2,FALSE),IF(OR(ISBLANK(C9),ISBLANK(B9)),"",VLOOKUP(C9,Deflatores!G$4:H$38,2,FALSE)*H9+VLOOKUP(C9,Deflatores!G$4:I$38,3,FALSE)))
A10: Imóvel | B10: ALI | C10: I | D10: 147 | E10: 15 | F10: =IF(ISBLANK(B10),"",IF(I10="L","Baixa",IF(I10="A","Média",IF(I10="","","Alta")))) -> Alta | G10: =CONCATENATE(B10,I10) -> ALIH | H10: =IF(ISBLANK(B10),"",IF(B10="ALI",IF(I10="L",7,IF(I10="A",10,15)),IF(B10="AIE",IF(I10="L",5,IF(I10="A",7,10)),IF(B10="SE",IF(I10="L",4,IF(I10="A",5,7)),IF(OR(B10="EE",B10="CE"),IF(I10="L",3,IF(I10="A",4,6)),0))))) -> 15 | I10: =IF(OR(ISBLANK(D10),ISBLANK(E10)),IF(OR(B10="ALI",B10="AIE"),"L",IF(OR(B10="EE",B10="SE",B10="CE"),"A","")),IF(B10="EE",IF(E10>=3,IF(D10>=5,"H","A"),IF(E10>=2,IF(D10>=16,"H",IF(D10<=4,"L","A")),IF(D10<=15,"L","A"))),IF(OR(B10="SE",B10="CE"),IF(E10>=4,IF(D10>=6,"H","A"),IF(E10>=2,IF(D10>=20,"H",IF(D10<=5,"L","A")),IF(D10<=19,"L","A"))),IF(OR(B10="ALI",B10="AIE"),IF(E10>=6,IF(D10>=20,"H","A"),IF(E10>=2,IF(D10>=51,"H",IF(D10<=19,"L","A")),IF(D10<=50,"L","A"))),"")))) -> H | J10: =CONCATENATE(B10,C10) -> ALII | K10: =IF(OR(H10="",H10=0),L10,H10) -> 15 | L10: =IF(NOT(ISERROR(VLOOKUP(B10,Deflatores!G$42:H$64,2,FALSE))),VLOOKUP(B10,Deflatores!G$42:H$64,2,FALSE),IF(OR(ISBLANK(C10),ISBLANK(B10)),"",VLOOKUP(C10,Deflatores!G$4:H$38,2,FALSE)*H10+VLOOKUP(C10,Deflatores!G$4:I$38,3,FALSE))) -> 15 | O10: Excluído os campos da Localização: área total construída / área total do terreno / unidade de medida
A11: Cadastrar Imóvel | B11: EE | C11: I | D11: 33 | E11: 1 | F11: =IF(ISBLANK(B11),"",IF(I11="L","Baixa",IF(I11="A","Média",IF(I11="","","Alta")))) -> Média | G11: =CONCATENATE(B11,I11) -> EEA | H11: =IF(ISBLANK(B11),"",IF(B11="ALI",IF(I11="L",7,IF(I11="A",10,15)),IF(B11="AIE",IF(I11="L",5,IF(I11="A",7,10)),IF(B11="SE",IF(I11="L",4,IF(I11="A",5,7)),IF(OR(B11="EE",B11="CE"),IF(I11="L",3,IF(I11="A",4,6)),0))))) -> 4 | I11: =IF(OR(ISBLANK(D11),ISBLANK(E11)),IF(OR(B11="ALI",B11="AIE"),"L",IF(OR(B11="EE",B11="SE",B11="CE"),"A","")),IF(B11="EE",IF(E11>=3,IF(D11>=5,"H","A"),IF(E11>=2,IF(D11>=16,"H",IF(D11<=4,"L","A")),IF(D11<=15,"L","A"))),IF(OR(B11="SE",B11="CE"),IF(E11>=4,IF(D11>=6,"H","A"),IF(E11>=2,IF(D11>=20,"H",IF(D11<=5,"L","A")),IF(D11<=19,"L","A"))),IF(OR(B11="ALI",B11="AIE"),IF(E11>=6,IF(D11>=20,"H","A"),IF(E11>=2,IF(D11>=51,"H",IF(D11<=19,"L","A")),IF(D11<=50,"L","A"))),"")))) -> A | J11: =CONCATENATE(B11,C11) -> EEI | K11: =IF(OR(H11="",H11=0),L11,H11) -> 4 | L11: =IF(NOT(ISERROR(VLOOKUP(B11,Deflatores!G$42:H$64,2,FALSE))),VLOOKUP(B11,Deflatores!G$42:H$64,2,FALSE),IF(OR(ISBLANK(C11),ISBLANK(B11)),"",VLOOKUP(C11,Deflatores!G$4:H$38,2,FALSE)*H11+VLOOKUP(C11,Deflatores!G$4:I$38,3,FALSE))) -> 4
A12: Combobox listar estado de conservação | B12: CE | C12: I | D12: 2 | E12: 1 | F12: =IF(ISBLANK(B12),"",IF(I12="L","Baixa",IF(I12="A","Média",IF(I12="","","Alta")))) -> Baixa | G12: =CONCATENATE(B12,I12) -> CEL | H12: =IF(ISBLANK(B12),"",IF(B12="ALI",IF(I12="L",7,IF(I12="A",10,15)),IF(B12="AIE",IF(I12="L",5,IF(I12="A",7,10)),IF(B12="SE",IF(I12="L",4,IF(I12="A",5,7)),IF(OR(B12="EE",B12="CE"),IF(I12="L",3,IF(I12="A",4,6)),0))))) -> 3 | I12: =IF(OR(ISBLANK(D12),ISBLANK(E12)),IF(OR(B12="ALI",B12="AIE"),"L",IF(OR(B12="EE",B12="SE",B12="CE"),"A","")),IF(B12="EE",IF(E12>=3,IF(D12>=5,"H","A"),IF(E12>=2,IF(D12>=16,"H",IF(D12<=4,"L","A")),IF(D12<=15,"L","A"))),IF(OR(B12="SE",B12="CE"),IF(E12>=4,IF(D12>=6,"H","A"),IF(E12>=2,IF(D12>=20,"H",IF(D12<=5,"L","A")),IF(D12<=19,"L","A"))),IF(OR(B12="ALI",B12="AIE"),IF(E12>=6,IF(D12>=20,"H","A"),IF(E12>=2,IF(D12>=51,"H",IF(D12<=19,"L","A")),IF(D12<=50,"L","A"))),"")))) -> L | J12: =CONCATENATE(B12,C12) -> CEI | K12: =IF(OR(H12="",H12=0),L12,H12) -> 3 | L12: =IF(NOT(ISERROR(VLOOKUP(B12,Deflatores!G$42:H$64,2,FALSE))),VLOOKUP(B12,Deflatores!G$42:H$64,2,FALSE),IF(OR(ISBLANK(C12),ISBLANK(B12)),"",VLOOKUP(C12,Deflatores!G$4:H$38,2,FALSE)*H12+VLOOKUP(C12,Deflatores!G$4:I$38,3,FALSE))) -> 3
A13: Combobox listar situações | B13: CE | C13: I | D13: 2 | E13: 1 | F13: =IF(ISBLANK(B13),"",IF(I13="L","Baixa",IF(I13="A","Média",IF(I13="","","Alta")))) -> Baixa | G13: =CONCATENATE(B13,I13) -> CEL | H13: =IF(ISBLANK(B13),"",IF(B13="ALI",IF(I13="L",7,IF(I13="A",10,15)),IF(B13="AIE",IF(I13="L",5,IF(I13="A",7,10)),IF(B13="SE",IF(I13="L",4,IF(I13="A",5,7)),IF(OR(B13="EE",B13="CE"),IF(I13="L",3,IF(I13="A",4,6)),0))))) -> 3 | I13: =IF(OR(ISBLANK(D13),ISBLANK(E13)),IF(OR(B13="ALI",B13="AIE"),"L",IF(OR(B13="EE",B13="SE",B13="CE"),"A","")),IF(B13="EE",IF(E13>=3,IF(D13>=5,"H","A"),IF(E13>=2,IF(D13>=16,"H",IF(D13<=4,"L","A")),IF(D13<=15,"L","A"))),IF(OR(B13="SE",B13="CE"),IF(E13>=4,IF(D13>=6,"H","A"),IF(E13>=2,IF(D13>=20,"H",IF(D13<=5,"L","A")),IF(D13<=19,"L","A"))),IF(OR(B13="ALI",B13="AIE"),IF(E13>=6,IF(D13>=20,"H","A"),IF(E13>=2,IF(D13>=51,"H",IF(D13<=19,"L","A")),IF(D13<=50,"L","A"))),"")))) -> L | J13: =CONCATENATE(B13,C13) -> CEI | K13: =IF(OR(H13="",H13=0),L13,H13) -> 3 | L13: =IF(NOT(ISERROR(VLOOKUP(B13,Deflatores!G$42:H$64,2,FALSE))),VLOOKUP(B13,Deflatores!G$42:H$64,2,FALSE),IF(OR(ISBLANK(C13),ISBLANK(B13)),"",VLOOKUP(C13,Deflatores!G$4:H$38,2,FALSE)*H13+VLOOKUP(C13,Deflatores!G$4:I$38,3,FALSE))) -> 3
A14: Combobox listar tipo de imóvel | B14: CE | C14: I | D14: 2 | E14: 1 | F14: =IF(ISBLANK(B14),"",IF(I14="L","Baixa",IF(I14="A","Média",IF(I14="","","Alta")))) -> Baixa | G14: =CONCATENATE(B14,I14) -> CEL | H14: =IF(ISBLANK(B14),"",IF(B14="ALI",IF(I14="L",7,IF(I14="A",10,15)),IF(B14="AIE",IF(I14="L",5,IF(I14="A",7,10)),IF(B14="SE",IF(I14="L",4,IF(I14="A",5,7)),IF(OR(B14="EE",B14="CE"),IF(I14="L",3,IF(I14="A",4,6)),0))))) -> 3 | I14: =IF(OR(ISBLANK(D14),ISBLANK(E14)),IF(OR(B14="ALI",B14="AIE"),"L",IF(OR(B14="EE",B14="SE",B14="CE"),"A","")),IF(B14="EE",IF(E14>=3,IF(D14>=5,"H","A"),IF(E14>=2,IF(D14>=16,"H",IF(D14<=4,"L","A")),IF(D14<=15,"L","A"))),IF(OR(B14="SE",B14="CE"),IF(E14>=4,IF(D14>=6,"H","A"),IF(E14>=2,IF(D14>=20,"H",IF(D14<=5,"L","A")),IF(D14<=19,"L","A"))),IF(OR(B14="ALI",B14="AIE"),IF(E14>=6,IF(D14>=20,"H","A"),IF(E14>=2,IF(D14>=51,"H",IF(D14<=19,"L","A")),IF(D14<=50,"L","A"))),"")))) -> L | J14: =CONCATENATE(B14,C14) -> CEI | K14: =IF(OR(H14="",H14=0),L14,H14) -> 3 | L14: =IF(NOT(ISERROR(VLOOKUP(B14,Deflatores!G$42:H$64,2,FALSE))),VLOOKUP(B14,Deflatores!G$42:H$64,2,FALSE),IF(OR(ISBLANK(C14),ISBLANK(B14)),"",VLOOKUP(C14,Deflatores!G$4:H$38,2,FALSE)*H14+VLOOKUP(C14,Deflatores!G$4:I$38,3,FALSE))) -> 3
A15: Serviços Urbanos - Listar Características | B15: CE | C15: I | D15: 2 | E15: 1 | F15: =IF(ISBLANK(B15),"",IF(I15="L","Baixa",IF(I15="A","Média",IF(I15="","","Alta")))) -> Baixa | G15: =CONCATENATE(B15,I15) -> CEL | H15: =IF(ISBLANK(B15),"",IF(B15="ALI",IF(I15="L",7,IF(I15="A",10,15)),IF(B15="AIE",IF(I15="L",5,IF(I15="A",7,10)),IF(B15="SE",IF(I15="L",4,IF(I15="A",5,7)),IF(OR(B15="EE",B15="CE"),IF(I15="L",3,IF(I15="A",4,6)),0))))) -> 3 | I15: =IF(OR(ISBLANK(D15),ISBLANK(E15)),IF(OR(B15="ALI",B15="AIE"),"L",IF(OR(B15="EE",B15="SE",B15="CE"),"A","")),IF(B15="EE",IF(E15>=3,IF(D15>=5,"H","A"),IF(E15>=2,IF(D15>=16,"H",IF(D15<=4,"L","A")),IF(D15<=15,"L","A"))),IF(OR(B15="SE",B15="CE"),IF(E15>=4,IF(D15>=6,"H","A"),IF(E15>=2,IF(D15>=20,"H",IF(D15<=5,"L","A")),IF(D15<=19,"L","A"))),IF(OR(B15="ALI",B15="AIE"),IF(E15>=6,IF(D15>=20,"H","A"),IF(E15>=2,IF(D15>=51,"H",IF(D15<=19,"L","A")),IF(D15<=50,"L","A"))),"")))) -> L | J15: =CONCATENATE(B15,C15) -> CEI | K15: =IF(OR(H15="",H15=0),L15,H15) -> 3 | L15: =IF(NOT(ISERROR(VLOOKUP(B15,Deflatores!G$42:H$64,2,FALSE))),VLOOKUP(B15,Deflatores!G$42:H$64,2,FALSE),IF(OR(ISBLANK(C15),ISBLANK(B15)),"",VLOOKUP(C15,Deflatores!G$4:H$38,2,FALSE)*H15+VLOOKUP(C15,Deflatores!G$4:I$38,3,FALSE))) -> 3
A16: Acessibilidade - Listar Características | B16: CE | C16: I | D16: 2 | E16: 1 | F16: =IF(ISBLANK(B16),"",IF(I16="L","Baixa",IF(I16="A","Média",IF(I16="","","Alta")))) -> Baixa | G16: =CONCATENATE(B16,I16) -> CEL | H16: =IF(ISBLANK(B16),"",IF(B16="ALI",IF(I16="L",7,IF(I16="A",10,15)),IF(B16="AIE",IF(I16="L",5,IF(I16="A",7,10)),IF(B16="SE",IF(I16="L",4,IF(I16="A",5,7)),IF(OR(B16="EE",B16="CE"),IF(I16="L",3,IF(I16="A",4,6)),0))))) -> 3 | I16: =IF(OR(ISBLANK(D16),ISBLANK(E16)),IF(OR(B16="ALI",B16="AIE"),"L",IF(OR(B16="EE",B16="SE",B16="CE"),"A","")),IF(B16="EE",IF(E16>=3,IF(D16>=5,"H","A"),IF(E16>=2,IF(D16>=16,"H",IF(D16<=4,"L","A")),IF(D16<=15,"L","A"))),IF(OR(B16="SE",B16="CE"),IF(E16>=4,IF(D16>=6,"H","A"),IF(E16>=2,IF(D16>=20,"H",IF(D16<=5,"L","A")),IF(D16<=19,"L","A"))),IF(OR(B16="ALI",B16="AIE"),IF(E16>=6,IF(D16>=20,"H","A"),IF(E16>=2,IF(D16>=51,"H",IF(D16<=19,"L","A")),IF(D16<=50,"L","A"))),"")))) -> L | J16: =CONCATENATE(B16,C16) -> CEI | K16: =IF(OR(H16="",H16=0),L16,H16) -> 3 | L16: =IF(NOT(ISERROR(VLOOKUP(B16,Deflatores!G$42:H$64,2,FALSE))),VLOOKUP(B16,Deflatores!G$42:H$64,2,FALSE),IF(OR(ISBLANK(C16),ISBLANK(B16)),"",VLOOKUP(C16,Deflatores!G$4:H$38,2,FALSE)*H16+VLOOKUP(C16,Deflatores!G$4:I$38,3,FALSE))) -> 3
A17: Combobox Destinação | B17: CE | C17: I | D17: 3 | E17: 1 | F17: =IF(ISBLANK(B17),"",IF(I17="L","Baixa",IF(I17="A","Média",IF(I17="","","Alta")))) -> Baixa | G17: =CONCATENATE(B17,I17) -> CEL | H17: =IF(ISBLANK(B17),"",IF(B17="ALI",IF(I17="L",7,IF(I17="A",10,15)),IF(B17="AIE",IF(I17="L",5,IF(I17="A",7,10)),IF(B17="SE",IF(I17="L",4,IF(I17="A",5,7)),IF(OR(B17="EE",B17="CE"),IF(I17="L",3,IF(I17="A",4,6)),0))))) -> 3 | I17: =IF(OR(ISBLANK(D17),ISBLANK(E17)),IF(OR(B17="ALI",B17="AIE"),"L",IF(OR(B17="EE",B17="SE",B17="CE"),"A","")),IF(B17="EE",IF(E17>=3,IF(D17>=5,"H","A"),IF(E17>=2,IF(D17>=16,"H",IF(D17<=4,"L","A")),IF(D17<=15,"L","A"))),IF(OR(B17="SE",B17="CE"),IF(E17>=4,IF(D17>=6,"H","A"),IF(E17>=2,IF(D17>=20,"H",IF(D17<=5,"L","A")),IF(D17<=19,"L","A"))),IF(OR(B17="ALI",B17="AIE"),IF(E17>=6,IF(D17>=20,"H","A"),IF(E17>=2,IF(D17>=51,"H",IF(D17<=19,"L","A")),IF(D17<=50,"L","A"))),"")))) -> L | J17: =CONCATENATE(B17,C17) -> CEI | K17: =IF(OR(H17="",H17=0),L17,H17) -> 3 | L17: =IF(NOT(ISERROR(VLOOKUP(B17,Deflatores!G$42:H$64,2,FALSE))),VLOOKUP(B17,Deflatores!G$42:H$64,2,FALSE),IF(OR(ISBLANK(C17),ISBLANK(B17)),"",VLOOKUP(C17,Deflatores!G$4:H$38,2,FALSE)*H17+VLOOKUP(C17,Deflatores!G$4:I$38,3,FALSE))) -> 3
A18: Combobox Forma Aquisição | B18: CE | C18: I | D18: 3 | E18: 1 | F18: =IF(ISBLANK(B18),"",IF(I18="L","Baixa",IF(I18="A","Média",IF(I18="","","Alta")))) -> Baixa | G18: =CONCATENATE(B18,I18) -> CEL | H18: =IF(ISBLANK(B18),"",IF(B18="ALI",IF(I18="L",7,IF(I18="A",10,15)),IF(B18="AIE",IF(I18="L",5,IF(I18="A",7,10)),IF(B18="SE",IF(I18="L",4,IF(I18="A",5,7)),IF(OR(B18="EE",B18="CE"),IF(I18="L",3,IF(I18="A",4,6)),0))))) -> 3 | I18: =IF(OR(ISBLANK(D18),ISBLANK(E18)),IF(OR(B18="ALI",B18="AIE"),"L",IF(OR(B18="EE",B18="SE",B18="CE"),"A","")),IF(B18="EE",IF(E18>=3,IF(D18>=5,"H","A"),IF(E18>=2,IF(D18>=16,"H",IF(D18<=4,"L","A")),IF(D18<=15,"L","A"))),IF(OR(B18="SE",B18="CE"),IF(E18>=4,IF(D18>=6,"H","A"),IF(E18>=2,IF(D18>=20,"H",IF(D18<=5,"L","A")),IF(D18<=19,"L","A"))),IF(OR(B18="ALI",B18="AIE"),IF(E18>=6,IF(D18>=20,"H","A"),IF(E18>=2,IF(D18>=51,"H",IF(D18<=19,"L","A")),IF(D18<=50,"L","A"))),"")))) -> L | J18: =CONCATENATE(B18,C18) -> CEI | K18: =IF(OR(H18="",H18=0),L18,H18) -> 3 | L18: =IF(NOT(ISERROR(VLOOKUP(B18,Deflatores!G$42:H$64,2,FALSE))),VLOOKUP(B18,Deflatores!G$42:H$64,2,FALSE),IF(OR(ISBLANK(C18),ISBLANK(B18)),"",VLOOKUP(C18,Deflatores!G$4:H$38,2,FALSE)*H18+VLOOKUP(C18,Deflatores!G$4:I$38,3,FALSE))) -> 3
A19: Editar Imóvel Hyperlink | B19: EE | C19: I | D19: 33 | E19: 1 | F19: =IF(ISBLANK(B19),"",IF(I19="L","Baixa",IF(I19="A","Média",IF(I19="","","Alta")))) -> Média | G19: =CONCATENATE(B19,I19) -> EEA | H19: =IF(ISBLANK(B19),"",IF(B19="ALI",IF(I19="L",7,IF(I19="A",10,15)),IF(B19="AIE",IF(I19="L",5,IF(I19="A",7,10)),IF(B19="SE",IF(I19="L",4,IF(I19="A",5,7)),IF(OR(B19="EE",B19="CE"),IF(I19="L",3,IF(I19="A",4,6)),0))))) -> 4 | I19: =IF(OR(ISBLANK(D19),ISBLANK(E19)),IF(OR(B19="ALI",B19="AIE"),"L",IF(OR(B19="EE",B19="SE",B19="CE"),"A","")),IF(B19="EE",IF(E19>=3,IF(D19>=5,"H","A"),IF(E19>=2,IF(D19>=16,"H",IF(D19<=4,"L","A")),IF(D19<=15,"L","A"))),IF(OR(B19="SE",B19="CE"),IF(E19>=4,IF(D19>=6,"H","A"),IF(E19>=2,IF(D19>=20,"H",IF(D19<=5,"L","A")),IF(D19<=19,"L","A"))),IF(OR(B19="ALI",B19="AIE"),IF(E19>=6,IF(D19>=20,"H","A"),IF(E19>=2,IF(D19>=51,"H",IF(D19<=19,"L","A")),IF(D19<=50,"L","A"))),"")))) -> A | J19: =CONCATENATE(B19,C19) -> EEI | K19: =IF(OR(H19="",H19=0),L19,H19) -> 4 | L19: =IF(NOT(ISERROR(VLOOKUP(B19,Deflatores!G$42:H$64,2,FALSE))),VLOOKUP(B19,Deflatores!G$42:H$64,2,FALSE),IF(OR(ISBLANK(C19),ISBLANK(B19)),"",VLOOKUP(C19,Deflatores!G$4:H$38,2,FALSE)*H19+VLOOKUP(C19,Deflatores!G$4:I$38,3,FALSE))) -> 4
A20: Consulta Implícia | B20: CE | C20: I | D20: 30 | E20: 2 | F20: =IF(ISBLANK(B20),"",IF(I20="L","Baixa",IF(I20="A","Média",IF(I20="","","Alta")))) -> Alta | G20: =CONCATENATE(B20,I20) -> CEH | H20: =IF(ISBLANK(B20),"",IF(B20="ALI",IF(I20="L",7,IF(I20="A",10,15)),IF(B20="AIE",IF(I20="L",5,IF(I20="A",7,10)),IF(B20="SE",IF(I20="L",4,IF(I20="A",5,7)),IF(OR(B20="EE",B20="CE"),IF(I20="L",3,IF(I20="A",4,6)),0))))) -> 6 | I20: =IF(OR(ISBLANK(D20),ISBLANK(E20)),IF(OR(B20="ALI",B20="AIE"),"L",IF(OR(B20="EE",B20="SE",B20="CE"),"A","")),IF(B20="EE",IF(E20>=3,IF(D20>=5,"H","A"),IF(E20>=2,IF(D20>=16,"H",IF(D20<=4,"L","A")),IF(D20<=15,"L","A"))),IF(OR(B20="SE",B20="CE"),IF(E20>=4,IF(D20>=6,"H","A"),IF(E20>=2,IF(D20>=20,"H",IF(D20<=5,"L","A")),IF(D20<=19,"L","A"))),IF(OR(B20="ALI",B20="AIE"),IF(E20>=6,IF(D20>=20,"H","A"),IF(E20>=2,IF(D20>=51,"H",IF(D20<=19,"L","A")),IF(D20<=50,"L","A"))),"")))) -> H | J20: =CONCATENATE(B20,C20) -> CEI | K20: =IF(OR(H20="",H20=0),L20,H20) -> 6 | L20: =IF(NOT(ISERROR(VLOOKUP(B20,Deflatores!G$42:H$64,2,FALSE))),VLOOKUP(B20,Deflatores!G$42:H$64,2,FALSE),IF(OR(ISBLANK(C20),ISBLANK(B20)),"",VLOOKUP(C20,Deflatores!G$4:H$38,2,FALSE)*H20+VLOOKUP(C20,Deflatores!G$4:I$38,3,FALSE))) -> 6
A21: Listagem de Imóvel | B21: CE | C21: I | D21: 22 | E21: 7 | F21: =IF(ISBLANK(B21),"",IF(I21="L","Baixa",IF(I21="A","Média",IF(I21="","","Alta")))) -> Alta | G21: =CONCATENATE(B21,I21) -> CEH | H21: =IF(ISBLANK(B21),"",IF(B21="ALI",IF(I21="L",7,IF(I21="A",10,15)),IF(B21="AIE",IF(I21="L",5,IF(I21="A",7,10)),IF(B21="SE",IF(I21="L",4,IF(I21="A",5,7)),IF(OR(B21="EE",B21="CE"),IF(I21="L",3,IF(I21="A",4,6)),0))))) -> 6 | I21: =IF(OR(ISBLANK(D21),ISBLANK(E21)),IF(OR(B21="ALI",B21="AIE"),"L",IF(OR(B21="EE",B21="SE",B21="CE"),"A","")),IF(B21="EE",IF(E21>=3,IF(D21>=5,"H","A"),IF(E21>=2,IF(D21>=16,"H",IF(D21<=4,"L","A")),IF(D21<=15,"L","A"))),IF(OR(B21="SE",B21="CE"),IF(E21>=4,IF(D21>=6,"H","A"),IF(E21>=2,IF(D21>=20,"H",IF(D21<=5,"L","A")),IF(D21<=19,"L","A"))),IF(OR(B21="ALI",B21="AIE"),IF(E21>=6,IF(D21>=20,"H","A"),IF(E21>=2,IF(D21>=51,"H",IF(D21<=19,"L","A")),IF(D21<=50,"L","A"))),"")))) -> H | J21: =CONCATENATE(B21,C21) -> CEI | K21: =IF(OR(H21="",H21=0),L21,H21) -> 6 | L21: =IF(NOT(ISERROR(VLOOKUP(B21,Deflatores!G$42:H$64,2,FALSE))),VLOOKUP(B21,Deflatores!G$42:H$64,2,FALSE),IF(OR(ISBLANK(C21),ISBLANK(B21)),"",VLOOKUP(C21,Deflatores!G$4:H$38,2,FALSE)*H21+VLOOKUP(C21,Deflatores!G$4:I$38,3,FALSE))) -> 6
A22: Listagem de Imóvel - Todos os Imóveis | B22: CE | C22: I | D22: 22 | E22: 7 | F22: =IF(ISBLANK(B22),"",IF(I22="L","Baixa",IF(I22="A","Média",IF(I22="","","Alta")))) -> Alta | G22: =CONCATENATE(B22,I22) -> CEH | H22: =IF(ISBLANK(B22),"",IF(B22="ALI",IF(I22="L",7,IF(I22="A",10,15)),IF(B22="AIE",IF(I22="L",5,IF(I22="A",7,10)),IF(B22="SE",IF(I22="L",4,IF(I22="A",5,7)),IF(OR(B22="EE",B22="CE"),IF(I22="L",3,IF(I22="A",4,6)),0))))) -> 6 | I22: =IF(OR(ISBLANK(D22),ISBLANK(E22)),IF(OR(B22="ALI",B22="AIE"),"L",IF(OR(B22="EE",B22="SE",B22="CE"),"A","")),IF(B22="EE",IF(E22>=3,IF(D22>=5,"H","A"),IF(E22>=2,IF(D22>=16,"H",IF(D22<=4,"L","A")),IF(D22<=15,"L","A"))),IF(OR(B22="SE",B22="CE"),IF(E22>=4,IF(D22>=6,"H","A"),IF(E22>=2,IF(D22>=20,"H",IF(D22<=5,"L","A")),IF(D22<=19,"L","A"))),IF(OR(B22="ALI",B22="AIE"),IF(E22>=6,IF(D22>=20,"H","A"),IF(E22>=2,IF(D22>=51,"H",IF(D22<=19,"L","A")),IF(D22<=50,"L","A"))),"")))) -> H | J22: =CONCATENATE(B22,C22) -> CEI | K22: =IF(OR(H22="",H22=0),L22,H22) -> 6 | L22: =IF(NOT(ISERROR(VLOOKUP(B22,Deflatores!G$42:H$64,2,FALSE))),VLOOKUP(B22,Deflatores!G$42:H$64,2,FALSE),IF(OR(ISBLANK(C22),ISBLANK(B22)),"",VLOOKUP(C22,Deflatores!G$4:H$38,2,FALSE)*H22+VLOOKUP(C22,Deflatores!G$4:I$38,3,FALSE))) -> 6
... A25: Excluir Imóvel | B25: EE | C25: I | D25: 4 | E25: 1 | F25: =IF(ISBLANK(B25),"",IF(I25="L","Baixa",IF(I25="A","Média",IF(I25="","","Alta")))) -> Baixa | G25: =CONCATENATE(B25,I25) -> EEL | H25: =IF(ISBLANK(B25),"",IF(B25="ALI",IF(I25="L",7,IF(I25="A",10,15)),IF(B25="AIE",IF(I25="L",5,IF(I25="A",7,10)),IF(B25="SE",IF(I25="L",4,IF(I25="A",5,7)),IF(OR(B25="EE",B25="CE"),IF(I25="L",3,IF(I25="A",4,6)),0))))) -> 3 | I25: =IF(OR(ISBLANK(D25),ISBLANK(E25)),IF(OR(B25="ALI",B25="AIE"),"L",IF(OR(B25="EE",B25="SE",B25="CE"),"A","")),IF(B25="EE",IF(E25>=3,IF(D25>=5,"H","A"),IF(E25>=2,IF(D25>=16,"H",IF(D25<=4,"L","A")),IF(D25<=15,"L","A"))),IF(OR(B25="SE",B25="CE"),IF(E25>=4,IF(D25>=6,"H","A"),IF(E25>=2,IF(D25>=20,"H",IF(D25<=5,"L","A")),IF(D25<=19,"L","A"))),IF(OR(B25="ALI",B25="AIE"),IF(E25>=6,IF(D25>=20,"H","A"),IF(E25>=2,IF(D25>=51,"H",IF(D25<=19,"L","A")),IF(D25<=50,"L","A"))),"")))) -> L | J25: =CONCATENATE(B25,C25) -> EEI | K25: =IF(OR(H25="",H25=0),L25,H25) -> 3 | L25: =IF(NOT(ISERROR(VLOOKUP(B25,Deflatores!G$42:H$64,2,FALSE))),VLOOKUP(B25,Deflatores!G$42:H$64,2,FALSE),IF(OR(ISBLANK(C25),ISBLANK(B25)),"",VLOOKUP(C25,Deflatores!G$4:H$38,2,FALSE)*H25+VLOOKUP(C25,Deflatores!G$4:I$38,3,FALSE))) -> 3
H26: =IF(ISBLANK(B26),"",IF(B26="ALI",IF(I26="L",7,IF(I26="A",10,15)),IF(B26="AIE",IF(I26="L",5,IF(I26="A",7,10)),IF(B26="SE",IF(I26="L",4,IF(I26="A",5,7)),IF(OR(B26="EE",B26="CE"),IF(I26="L",3,IF(I26="A",4,6)),0))))) | I26: =IF(OR(ISBLANK(D26),ISBLANK(E26)),IF(OR(B26="ALI",B26="AIE"),"L",IF(OR(B26="EE",B26="SE",B26="CE"),"A","")),IF(B26="EE",IF(E26>=3,IF(D26>=5,"H","A"),IF(E26>=2,IF(D26>=16,"H",IF(D26<=4,"L","A")),IF(D26<=15,"L","A"))),IF(OR(B26="SE",B26="CE"),IF(E26>=4,IF(D26>=6,"H","A"),IF(E26>=2,IF(D26>=20,"H",IF(D26<=5,"L","A")),IF(D26<=19,"L","A"))),IF(OR(B26="ALI",B26="AIE"),IF(E26>=6,IF(D26>=20,"H","A"),IF(E26>=2,IF(D26>=51,"H",IF(D26<=19,"L","A")),IF(D26<=50,"L","A"))),"")))) | J26: =CONCATENATE(B26,C26) | K26: =IF(OR(H26="",H26=0),L26,H26) | L26: =IF(NOT(ISERROR(VLOOKUP(B26,Deflatores!G$42:H$64,2,FALSE))),VLOOKUP(B26,Deflatores!G$42:H$64,2,FALSE),IF(OR(ISBLANK(C26),ISBLANK(B26)),"",VLOOKUP(C26,Deflatores!G$4:H$38,2,FALSE)*H26+VLOOKUP(C26,Deflatores!G$4:I$38,3,FALSE)))
A27: [US_02] Identificação (Proprietário/Responsável/Ocupante) | F27: =IF(ISBLANK(B27),"",IF(I27="L","Baixa",IF(I27="A","Média",IF(I27="","","Alta")))) | G27: =CONCATENATE(B27,I27) | H27: =IF(ISBLANK(B27),"",IF(B27="ALI",IF(I27="L",7,IF(I27="A",10,15)),IF(B27="AIE",IF(I27="L",5,IF(I27="A",7,10)),IF(B27="SE",IF(I27="L",4,IF(I27="A",5,7)),IF(OR(B27="EE",B27="CE"),IF(I27="L",3,IF(I27="A",4,6)),0))))) | I27: =IF(OR(ISBLANK(D27),ISBLANK(E27)),IF(OR(B27="ALI",B27="AIE"),"L",IF(OR(B27="EE",B27="SE",B27="CE"),"A","")),IF(B27="EE",IF(E27>=3,IF(D27>=5,"H","A"),IF(E27>=2,IF(D27>=16,"H",IF(D27<=4,"L","A")),IF(D27<=15,"L","A"))),IF(OR(B27="SE",B27="CE"),IF(E27>=4,IF(D27>=6,"H","A"),IF(E27>=2,IF(D27>=20,"H",IF(D27<=5,"L","A")),IF(D27<=19,"L","A"))),IF(OR(B27="ALI",B27="AIE"),IF(E27>=6,IF(D27>=20,"H","A"),IF(E27>=2,IF(D27>=51,"H",IF(D27<=19,"L","A")),IF(D27<=50,"L","A"))),"")))) | J27: =CONCATENATE(B27,C27) | K27: =IF(OR(H27="",H27=0),L27,H27) | L27: =IF(NOT(ISERROR(VLOOKUP(B27,Deflatores!G$42:H$64,2,FALSE))),VLOOKUP(B27,Deflatores!G$42:H$64,2,FALSE),IF(OR(ISBLANK(C27),ISBLANK(B27)),"",VLOOKUP(C27,Deflatores!G$4:H$38,2,FALSE)*H27+VLOOKUP(C27,Deflatores!G$4:I$38,3,FALSE))) | O27: Alteração do nome de Identificação
A28: Órgão | B28: AIE | C28: I | D28: 4 | E28: 1 | F28: =IF(ISBLANK(B28),"",IF(I28="L","Baixa",IF(I28="A","Média",IF(I28="","","Alta")))) -> Baixa | G28: =CONCATENATE(B28,I28) -> AIEL | H28: =IF(ISBLANK(B28),"",IF(B28="ALI",IF(I28="L",7,IF(I28="A",10,15)),IF(B28="AIE",IF(I28="L",5,IF(I28="A",7,10)),IF(B28="SE",IF(I28="L",4,IF(I28="A",5,7)),IF(OR(B28="EE",B28="CE"),IF(I28="L",3,IF(I28="A",4,6)),0))))) -> 5 | I28: =IF(OR(ISBLANK(D28),ISBLANK(E28)),IF(OR(B28="ALI",B28="AIE"),"L",IF(OR(B28="EE",B28="SE",B28="CE"),"A","")),IF(B28="EE",IF(E28>=3,IF(D28>=5,"H","A"),IF(E28>=2,IF(D28>=16,"H",IF(D28<=4,"L","A")),IF(D28<=15,"L","A"))),IF(OR(B28="SE",B28="CE"),IF(E28>=4,IF(D28>=6,"H","A"),IF(E28>=2,IF(D28>=20,"H",IF(D28<=5,"L","A")),IF(D28<=19,"L","A"))),IF(OR(B28="ALI",B28="AIE"),IF(E28>=6,IF(D28>=20,"H","A"),IF(E28>=2,IF(D28>=51,"H",IF(D28<=19,"L","A")),IF(D28<=50,"L","A"))),"")))) -> L | J28: =CONCATENATE(B28,C28) -> AIEI | K28: =IF(OR(H28="",H28=0),L28,H28) -> 5 | L28: =IF(NOT(ISERROR(VLOOKUP(B28,Deflatores!G$42:H$64,2,FALSE))),VLOOKUP(B28,Deflatores!G$42:H$64,2,FALSE),IF(OR(ISBLANK(C28),ISBLANK(B28)),"",VLOOKUP(C28,Deflatores!G$4:H$38,2,FALSE)*H28+VLOOKUP(C28,Deflatores!G$4:I$38,3,FALSE))) -> 5
A29: Unidade | B29: AIE | C29: I | D29: 4 | E29: 1 | F29: =IF(ISBLANK(B29),"",IF(I29="L","Baixa",IF(I29="A","Média",IF(I29="","","Alta")))) -> Baixa | G29: =CONCATENATE(B29,I29) -> AIEL | H29: =IF(ISBLANK(B29),"",IF(B29="ALI",IF(I29="L",7,IF(I29="A",10,15)),IF(B29="AIE",IF(I29="L",5,IF(I29="A",7,10)),IF(B29="SE",IF(I29="L",4,IF(I29="A",5,7)),IF(OR(B29="EE",B29="CE"),IF(I29="L",3,IF(I29="A",4,6)),0))))) -> 5 | I29: =IF(OR(ISBLANK(D29),ISBLANK(E29)),IF(OR(B29="ALI",B29="AIE"),"L",IF(OR(B29="EE",B29="SE",B29="CE"),"A","")),IF(B29="EE",IF(E29>=3,IF(D29>=5,"H","A"),IF(E29>=2,IF(D29>=16,"H",IF(D29<=4,"L","A")),IF(D29<=15,"L","A"))),IF(OR(B29="SE",B29="CE"),IF(E29>=4,IF(D29>=6,"H","A"),IF(E29>=2,IF(D29>=20,"H",IF(D29<=5,"L","A")),IF(D29<=19,"L","A"))),IF(OR(B29="ALI",B29="AIE"),IF(E29>=6,IF(D29>=20,"H","A"),IF(E29>=2,IF(D29>=51,"H",IF(D29<=19,"L","A")),IF(D29<=50,"L","A"))),"")))) -> L | J29: =CONCATENATE(B29,C29) -> AIEI | K29: =IF(OR(H29="",H29=0),L29,H29) -> 5 | L29: =IF(NOT(ISERROR(VLOOKUP(B29,Deflatores!G$42:H$64,2,FALSE))),VLOOKUP(B29,Deflatores!G$42:H$64,2,FALSE),IF(OR(ISBLANK(C29),ISBLANK(B29)),"",VLOOKUP(C29,Deflatores!G$4:H$38,2,FALSE)*H29+VLOOKUP(C29,Deflatores!G$4:I$38,3,FALSE))) -> 5
A30: Identificação | B30: ALI | C30: I | D30: 61 | E30: 6 | F30: =IF(ISBLANK(B30),"",IF(I30="L","Baixa",IF(I30="A","Média",IF(I30="","","Alta")))) -> Alta | G30: =CONCATENATE(B30,I30) -> ALIH | H30: =IF(ISBLANK(B30),"",IF(B30="ALI",IF(I30="L",7,IF(I30="A",10,15)),IF(B30="AIE",IF(I30="L",5,IF(I30="A",7,10)),IF(B30="SE",IF(I30="L",4,IF(I30="A",5,7)),IF(OR(B30="EE",B30="CE"),IF(I30="L",3,IF(I30="A",4,6)),0))))) -> 15 | I30: =IF(OR(ISBLANK(D30),ISBLANK(E30)),IF(OR(B30="ALI",B30="AIE"),"L",IF(OR(B30="EE",B30="SE",B30="CE"),"A","")),IF(B30="EE",IF(E30>=3,IF(D30>=5,"H","A"),IF(E30>=2,IF(D30>=16,"H",IF(D30<=4,"L","A")),IF(D30<=15,"L","A"))),IF(OR(B30="SE",B30="CE"),IF(E30>=4,IF(D30>=6,"H","A"),IF(E30>=2,IF(D30>=20,"H",IF(D30<=5,"L","A")),IF(D30<=19,"L","A"))),IF(OR(B30="ALI",B30="AIE"),IF(E30>=6,IF(D30>=20,"H","A"),IF(E30>=2,IF(D30>=51,"H",IF(D30<=19,"L","A")),IF(D30<=50,"L","A"))),"")))) -> H | J30: =CONCATENATE(B30,C30) -> ALII | K30: =IF(OR(H30="",H30=0),L30,H30) -> 15 | L30: =IF(NOT(ISERROR(VLOOKUP(B30,Deflatores!G$42:H$64,2,FALSE))),VLOOKUP(B30,Deflatores!G$42:H$64,2,FALSE),IF(OR(ISBLANK(C30),ISBLANK(B30)),"",VLOOKUP(C30,Deflatores!G$4:H$38,2,FALSE)*H30+VLOOKUP(C30,Deflatores!G$4:I$38,3,FALSE))) -> 15
A31: Cadastrar Identificação do Imóvel | B31: EE | C31: I | D31: 19 | E31: 4 | F31: =IF(ISBLANK(B31),"",IF(I31="L","Baixa",IF(I31="A","Média",IF(I31="","","Alta")))) -> Alta | G31: =CONCATENATE(B31,I31) -> EEH | H31: =IF(ISBLANK(B31),"",IF(B31="ALI",IF(I31="L",7,IF(I31="A",10,15)),IF(B31="AIE",IF(I31="L",5,IF(I31="A",7,10)),IF(B31="SE",IF(I31="L",4,IF(I31="A",5,7)),IF(OR(B31="EE",B31="CE"),IF(I31="L",3,IF(I31="A",4,6)),0))))) -> 6 | I31: =IF(OR(ISBLANK(D31),ISBLANK(E31)),IF(OR(B31="ALI",B31="AIE"),"L",IF(OR(B31="EE",B31="SE",B31="CE"),"A","")),IF(B31="EE",IF(E31>=3,IF(D31>=5,"H","A"),IF(E31>=2,IF(D31>=16,"H",IF(D31<=4,"L","A")),IF(D31<=15,"L","A"))),IF(OR(B31="SE",B31="CE"),IF(E31>=4,IF(D31>=6,"H","A"),IF(E31>=2,IF(D31>=20,"H",IF(D31<=5,"L","A")),IF(D31<=19,"L","A"))),IF(OR(B31="ALI",B31="AIE"),IF(E31>=6,IF(D31>=20,"H","A"),IF(E31>=2,IF(D31>=51,"H",IF(D31<=19,"L","A")),IF(D31<=50,"L","A"))),"")))) -> H | J31: =CONCATENATE(B31,C31) -> EEI | K31: =IF(OR(H31="",H31=0),L31,H31) -> 6 | L31: =IF(NOT(ISERROR(VLOOKUP(B31,Deflatores!G$42:H$64,2,FALSE))),VLOOKUP(B31,Deflatores!G$42:H$64,2,FALSE),IF(OR(ISBLANK(C31),ISBLANK(B31)),"",VLOOKUP(C31,Deflatores!G$4:H$38,2,FALSE)*H31+VLOOKUP(C31,Deflatores!G$4:I$38,3,FALSE))) -> 6
A32: Combobox listar órgão | B32: CE | C32: E | D32: 4 | E32: 1 | F32: =IF(ISBLANK(B32),"",IF(I32="L","Baixa",IF(I32="A","Média",IF(I32="","","Alta")))) -> Baixa | G32: =CONCATENATE(B32,I32) -> CEL | H32: =IF(ISBLANK(B32),"",IF(B32="ALI",IF(I32="L",7,IF(I32="A",10,15)),IF(B32="AIE",IF(I32="L",5,IF(I32="A",7,10)),IF(B32="SE",IF(I32="L",4,IF(I32="A",5,7)),IF(OR(B32="EE",B32="CE"),IF(I32="L",3,IF(I32="A",4,6)),0))))) -> 3 | I32: =IF(OR(ISBLANK(D32),ISBLANK(E32)),IF(OR(B32="ALI",B32="AIE"),"L",IF(OR(B32="EE",B32="SE",B32="CE"),"A","")),IF(B32="EE",IF(E32>=3,IF(D32>=5,"H","A"),IF(E32>=2,IF(D32>=16,"H",IF(D32<=4,"L","A")),IF(D32<=15,"L","A"))),IF(OR(B32="SE",B32="CE"),IF(E32>=4,IF(D32>=6,"H","A"),IF(E32>=2,IF(D32>=20,"H",IF(D32<=5,"L","A")),IF(D32<=19,"L","A"))),IF(OR(B32="ALI",B32="AIE"),IF(E32>=6,IF(D32>=20,"H","A"),IF(E32>=2,IF(D32>=51,"H",IF(D32<=19,"L","A")),IF(D32<=50,"L","A"))),"")))) -> L | J32: =CONCATENATE(B32,C32) -> CEE | K32: =IF(OR(H32="",H32=0),L32,H32) -> 3 | L32: =IF(NOT(ISERROR(VLOOKUP(B32,Deflatores!G$42:H$64,2,FALSE))),VLOOKUP(B32,Deflatores!G$42:H$64,2,FALSE),IF(OR(ISBLANK(C32),ISBLANK(B32)),"",VLOOKUP(C32,Deflatores!G$4:H$38,2,FALSE)*H32+VLOOKUP(C32,Deflatores!G$4:I$38,3,FALSE))) -> 1.2
A33: Combobox listar pessoas | B33: CE | C33: E | D33: 5 | E33: 1 | F33: =IF(ISBLANK(B33),"",IF(I33="L","Baixa",IF(I33="A","Média",IF(I33="","","Alta")))) -> Baixa | G33: =CONCATENATE(B33,I33) -> CEL | H33: =IF(ISBLANK(B33),"",IF(B33="ALI",IF(I33="L",7,IF(I33="A",10,15)),IF(B33="AIE",IF(I33="L",5,IF(I33="A",7,10)),IF(B33="SE",IF(I33="L",4,IF(I33="A",5,7)),IF(OR(B33="EE",B33="CE"),IF(I33="L",3,IF(I33="A",4,6)),0))))) -> 3 | I33: =IF(OR(ISBLANK(D33),ISBLANK(E33)),IF(OR(B33="ALI",B33="AIE"),"L",IF(OR(B33="EE",B33="SE",B33="CE"),"A","")),IF(B33="EE",IF(E33>=3,IF(D33>=5,"H","A"),IF(E33>=2,IF(D33>=16,"H",IF(D33<=4,"L","A")),IF(D33<=15,"L","A"))),IF(OR(B33="SE",B33="CE"),IF(E33>=4,IF(D33>=6,"H","A"),IF(E33>=2,IF(D33>=20,"H",IF(D33<=5,"L","A")),IF(D33<=19,"L","A"))),IF(OR(B33="ALI",B33="AIE"),IF(E33>=6,IF(D33>=20,"H","A"),IF(E33>=2,IF(D33>=51,"H",IF(D33<=19,"L","A")),IF(D33<=50,"L","A"))),"")))) -> L | J33: =CONCATENATE(B33,C33) -> CEE | K33: =IF(OR(H33="",H33=0),L33,H33) -> 3 | L33: =IF(NOT(ISERROR(VLOOKUP(B33,Deflatores!G$42:H$64,2,FALSE))),VLOOKUP(B33,Deflatores!G$42:H$64,2,FALSE),IF(OR(ISBLANK(C33),ISBLANK(B33)),"",VLOOKUP(C33,Deflatores!G$4:H$38,2,FALSE)*H33+VLOOKUP(C33,Deflatores!G$4:I$38,3,FALSE))) -> 1.2
A34: Combobox listar pessoa física | B34: CE | C34: E | D34: 7 | E34: 3 | F34: =IF(ISBLANK(B34),"",IF(I34="L","Baixa",IF(I34="A","Média",IF(I34="","","Alta")))) -> Média | G34: =CONCATENATE(B34,I34) -> CEA | H34: =IF(ISBLANK(B34),"",IF(B34="ALI",IF(I34="L",7,IF(I34="A",10,15)),IF(B34="AIE",IF(I34="L",5,IF(I34="A",7,10)),IF(B34="SE",IF(I34="L",4,IF(I34="A",5,7)),IF(OR(B34="EE",B34="CE"),IF(I34="L",3,IF(I34="A",4,6)),0))))) -> 4 | I34: =IF(OR(ISBLANK(D34),ISBLANK(E34)),IF(OR(B34="ALI",B34="AIE"),"L",IF(OR(B34="EE",B34="SE",B34="CE"),"A","")),IF(B34="EE",IF(E34>=3,IF(D34>=5,"H","A"),IF(E34>=2,IF(D34>=16,"H",IF(D34<=4,"L","A")),IF(D34<=15,"L","A"))),IF(OR(B34="SE",B34="CE"),IF(E34>=4,IF(D34>=6,"H","A"),IF(E34>=2,IF(D34>=20,"H",IF(D34<=5,"L","A")),IF(D34<=19,"L","A"))),IF(OR(B34="ALI",B34="AIE"),IF(E34>=6,IF(D34>=20,"H","A"),IF(E34>=2,IF(D34>=51,"H",IF(D34<=19,"L","A")),IF(D34<=50,"L","A"))),"")))) -> A | J34: =CONCATENATE(B34,C34) -> CEE | K34: =IF(OR(H34="",H34=0),L34,H34) -> 4 | L34: =IF(NOT(ISERROR(VLOOKUP(B34,Deflatores!G$42:H$64,2,FALSE))),VLOOKUP(B34,Deflatores!G$42:H$64,2,FALSE),IF(OR(ISBLANK(C34),ISBLANK(B34)),"",VLOOKUP(C34,Deflatores!G$4:H$38,2,FALSE)*H34+VLOOKUP(C34,Deflatores!G$4:I$38,3,FALSE))) -> 1.6
A35: Combobox listar pessoa jurídica | B35: CE | C35: E | D35: 7 | E35: 3 | F35: =IF(ISBLANK(B35),"",IF(I35="L","Baixa",IF(I35="A","Média",IF(I35="","","Alta")))) -> Média | G35: =CONCATENATE(B35,I35) -> CEA | H35: =IF(ISBLANK(B35),"",IF(B35="ALI",IF(I35="L",7,IF(I35="A",10,15)),IF(B35="AIE",IF(I35="L",5,IF(I35="A",7,10)),IF(B35="SE",IF(I35="L",4,IF(I35="A",5,7)),IF(OR(B35="EE",B35="CE"),IF(I35="L",3,IF(I35="A",4,6)),0))))) -> 4 | I35: =IF(OR(ISBLANK(D35),ISBLANK(E35)),IF(OR(B35="ALI",B35="AIE"),"L",IF(OR(B35="EE",B35="SE",B35="CE"),"A","")),IF(B35="EE",IF(E35>=3,IF(D35>=5,"H","A"),IF(E35>=2,IF(D35>=16,"H",IF(D35<=4,"L","A")),IF(D35<=15,"L","A"))),IF(OR(B35="SE",B35="CE"),IF(E35>=4,IF(D35>=6,"H","A"),IF(E35>=2,IF(D35>=20,"H",IF(D35<=5,"L","A")),IF(D35<=19,"L","A"))),IF(OR(B35="ALI",B35="AIE"),IF(E35>=6,IF(D35>=20,"H","A"),IF(E35>=2,IF(D35>=51,"H",IF(D35<=19,"L","A")),IF(D35<=50,"L","A"))),"")))) -> A | J35: =CONCATENATE(B35,C35) -> CEE | K35: =IF(OR(H35="",H35=0),L35,H35) -> 4 | L35: =IF(NOT(ISERROR(VLOOKUP(B35,Deflatores!G$42:H$64,2,FALSE))),VLOOKUP(B35,Deflatores!G$42:H$64,2,FALSE),IF(OR(ISBLANK(C35),ISBLANK(B35)),"",VLOOKUP(C35,Deflatores!G$4:H$38,2,FALSE)*H35+VLOOKUP(C35,Deflatores!G$4:I$38,3,FALSE))) -> 1.6
A36: Combobox listar órgão/entidade | B36: CE | C36: I | D36: 6 | E36: 2 | F36: =IF(ISBLANK(B36),"",IF(I36="L","Baixa",IF(I36="A","Média",IF(I36="","","Alta")))) -> Média | G36: =CONCATENATE(B36,I36) -> CEA | H36: =IF(ISBLANK(B36),"",IF(B36="ALI",IF(I36="L",7,IF(I36="A",10,15)),IF(B36="AIE",IF(I36="L",5,IF(I36="A",7,10)),IF(B36="SE",IF(I36="L",4,IF(I36="A",5,7)),IF(OR(B36="EE",B36="CE"),IF(I36="L",3,IF(I36="A",4,6)),0))))) -> 4 | I36: =IF(OR(ISBLANK(D36),ISBLANK(E36)),IF(OR(B36="ALI",B36="AIE"),"L",IF(OR(B36="EE",B36="SE",B36="CE"),"A","")),IF(B36="EE",IF(E36>=3,IF(D36>=5,"H","A"),IF(E36>=2,IF(D36>=16,"H",IF(D36<=4,"L","A")),IF(D36<=15,"L","A"))),IF(OR(B36="SE",B36="CE"),IF(E36>=4,IF(D36>=6,"H","A"),IF(E36>=2,IF(D36>=20,"H",IF(D36<=5,"L","A")),IF(D36<=19,"L","A"))),IF(OR(B36="ALI",B36="AIE"),IF(E36>=6,IF(D36>=20,"H","A"),IF(E36>=2,IF(D36>=51,"H",IF(D36<=19,"L","A")),IF(D36<=50,"L","A"))),"")))) -> A | J36: =CONCATENATE(B36,C36) -> CEI | K36: =IF(OR(H36="",H36=0),L36,H36) -> 4 | L36: =IF(NOT(ISERROR(VLOOKUP(B36,Deflatores!G$42:H$64,2,FALSE))),VLOOKUP(B36,Deflatores!G$42:H$64,2,FALSE),IF(OR(ISBLANK(C36),ISBLANK(B36)),"",VLOOKUP(C36,Deflatores!G$4:H$38,2,FALSE)*H36+VLOOKUP(C36,Deflatores!G$4:I$38,3,FALSE))) -> 4
A37: Combobox listar unidade | B37: CE | C37: I | D37: 6 | E37: 1 | F37: =IF(ISBLANK(B37),"",IF(I37="L","Baixa",IF(I37="A","Média",IF(I37="","","Alta")))) -> Baixa | G37: =CONCATENATE(B37,I37) -> CEL | H37: =IF(ISBLANK(B37),"",IF(B37="ALI",IF(I37="L",7,IF(I37="A",10,15)),IF(B37="AIE",IF(I37="L",5,IF(I37="A",7,10)),IF(B37="SE",IF(I37="L",4,IF(I37="A",5,7)),IF(OR(B37="EE",B37="CE"),IF(I37="L",3,IF(I37="A",4,6)),0))))) -> 3 | I37: =IF(OR(ISBLANK(D37),ISBLANK(E37)),IF(OR(B37="ALI",B37="AIE"),"L",IF(OR(B37="EE",B37="SE",B37="CE"),"A","")),IF(B37="EE",IF(E37>=3,IF(D37>=5,"H","A"),IF(E37>=2,IF(D37>=16,"H",IF(D37<=4,"L","A")),IF(D37<=15,"L","A"))),IF(OR(B37="SE",B37="CE"),IF(E37>=4,IF(D37>=6,"H","A"),IF(E37>=2,IF(D37>=20,"H",IF(D37<=5,"L","A")),IF(D37<=19,"L","A"))),IF(OR(B37="ALI",B37="AIE"),IF(E37>=6,IF(D37>=20,"H","A"),IF(E37>=2,IF(D37>=51,"H",IF(D37<=19,"L","A")),IF(D37<=50,"L","A"))),"")))) -> L | J37: =CONCATENATE(B37,C37) -> CEI | K37: =IF(OR(H37="",H37=0),L37,H37) -> 3 | L37: =IF(NOT(ISERROR(VLOOKUP(B37,Deflatores!G$42:H$64,2,FALSE))),VLOOKUP(B37,Deflatores!G$42:H$64,2,FALSE),IF(OR(ISBLANK(C37),ISBLANK(B37)),"",VLOOKUP(C37,Deflatores!G$4:H$38,2,FALSE)*H37+VLOOKUP(C37,Deflatores!G$4:I$38,3,FALSE))) -> 3
A38: Combobox listar órgão/entidade e unidade | B38: CE | C38: I | D38: 9 | E38: 2 | F38: =IF(ISBLANK(B38),"",IF(I38="L","Baixa",IF(I38="A","Média",IF(I38="","","Alta")))) -> Média | G38: =CONCATENATE(B38,I38) -> CEA | H38: =IF(ISBLANK(B38),"",IF(B38="ALI",IF(I38="L",7,IF(I38="A",10,15)),IF(B38="AIE",IF(I38="L",5,IF(I38="A",7,10)),IF(B38="SE",IF(I38="L",4,IF(I38="A",5,7)),IF(OR(B38="EE",B38="CE"),IF(I38="L",3,IF(I38="A",4,6)),0))))) -> 4 | I38: =IF(OR(ISBLANK(D38),ISBLANK(E38)),IF(OR(B38="ALI",B38="AIE"),"L",IF(OR(B38="EE",B38="SE",B38="CE"),"A","")),IF(B38="EE",IF(E38>=3,IF(D38>=5,"H","A"),IF(E38>=2,IF(D38>=16,"H",IF(D38<=4,"L","A")),IF(D38<=15,"L","A"))),IF(OR(B38="SE",B38="CE"),IF(E38>=4,IF(D38>=6,"H","A"),IF(E38>=2,IF(D38>=20,"H",IF(D38<=5,"L","A")),IF(D38<=19,"L","A"))),IF(OR(B38="ALI",B38="AIE"),IF(E38>=6,IF(D38>=20,"H","A"),IF(E38>=2,IF(D38>=51,"H",IF(D38<=19,"L","A")),IF(D38<=50,"L","A"))),"")))) -> A | J38: =CONCATENATE(B38,C38) -> CEI | K38: =IF(OR(H38="",H38=0),L38,H38) -> 4 | L38: 4 | O38: AKST: Foi criada uma nova combo para juntar Entidade e Unidade e com o sufixo conforme orgem dos dados. Não foram excluidas ou editadas as combos existentes pois elas são usadas em outras funcionalidades
A39: Combo Sigla | B39: CE | C39: I | D39: 3 | E39: 2 | F39: =IF(ISBLANK(B39),"",IF(I39="L","Baixa",IF(I39="A","Média",IF(I39="","","Alta")))) -> Baixa | G39: =CONCATENATE(B39,I39) -> CEL | H39: =IF(ISBLANK(B39),"",IF(B39="ALI",IF(I39="L",7,IF(I39="A",10,15)),IF(B39="AIE",IF(I39="L",5,IF(I39="A",7,10)),IF(B39="SE",IF(I39="L",4,IF(I39="A",5,7)),IF(OR(B39="EE",B39="CE"),IF(I39="L",3,IF(I39="A",4,6)),0))))) -> 3 | I39: =IF(OR(ISBLANK(D39),ISBLANK(E39)),IF(OR(B39="ALI",B39="AIE"),"L",IF(OR(B39="EE",B39="SE",B39="CE"),"A","")),IF(B39="EE",IF(E39>=3,IF(D39>=5,"H","A"),IF(E39>=2,IF(D39>=16,"H",IF(D39<=4,"L","A")),IF(D39<=15,"L","A"))),IF(OR(B39="SE",B39="CE"),IF(E39>=4,IF(D39>=6,"H","A"),IF(E39>=2,IF(D39>=20,"H",IF(D39<=5,"L","A")),IF(D39<=19,"L","A"))),IF(OR(B39="ALI",B39="AIE"),IF(E39>=6,IF(D39>=20,"H","A"),IF(E39>=2,IF(D39>=51,"H",IF(D39<=19,"L","A")),IF(D39<=50,"L","A"))),"")))) -> L | J39: =CONCATENATE(B39,C39) -> CEI | K39: =IF(OR(H39="",H39=0),L39,H39) -> 3 | L39: =IF(NOT(ISERROR(VLOOKUP(B39,Deflatores!G$42:H$64,2,FALSE))),VLOOKUP(B39,Deflatores!G$42:H$64,2,FALSE),IF(OR(ISBLANK(C39),ISBLANK(B39)),"",VLOOKUP(C39,Deflatores!G$4:H$38,2,FALSE)*H39+VLOOKUP(C39,Deflatores!G$4:I$38,3,FALSE))) -> 3
A40: Editar Identificação do Imóvel | B40: EE | C40: I | D40: 27 | E40: 6 | F40: =IF(ISBLANK(B40),"",IF(I40="L","Baixa",IF(I40="A","Média",IF(I40="","","Alta")))) -> Alta | G40: =CONCATENATE(B40,I40) -> EEH | H40: =IF(ISBLANK(B40),"",IF(B40="ALI",IF(I40="L",7,IF(I40="A",10,15)),IF(B40="AIE",IF(I40="L",5,IF(I40="A",7,10)),IF(B40="SE",IF(I40="L",4,IF(I40="A",5,7)),IF(OR(B40="EE",B40="CE"),IF(I40="L",3,IF(I40="A",4,6)),0))))) -> 6 | I40: =IF(OR(ISBLANK(D40),ISBLANK(E40)),IF(OR(B40="ALI",B40="AIE"),"L",IF(OR(B40="EE",B40="SE",B40="CE"),"A","")),IF(B40="EE",IF(E40>=3,IF(D40>=5,"H","A"),IF(E40>=2,IF(D40>=16,"H",IF(D40<=4,"L","A")),IF(D40<=15,"L","A"))),IF(OR(B40="SE",B40="CE"),IF(E40>=4,IF(D40>=6,"H","A"),IF(E40>=2,IF(D40>=20,"H",IF(D40<=5,"L","A")),IF(D40<=19,"L","A"))),IF(OR(B40="ALI",B40="AIE"),IF(E40>=6,IF(D40>=20,"H","A"),IF(E40>=2,IF(D40>=51,"H",IF(D40<=19,"L","A")),IF(D40<=50,"L","A"))),"")))) -> H | J40: =CONCATENATE(B40,C40) -> EEI | K40: =IF(OR(H40="",H40=0),L40,H40) -> 6 | L40: =IF(NOT(ISERROR(VLOOKUP(B40,Deflatores!G$42:H$64,2,FALSE))),VLOOKUP(B40,Deflatores!G$42:H$64,2,FALSE),IF(OR(ISBLANK(C40),ISBLANK(B40)),"",VLOOKUP(C40,Deflatores!G$4:H$38,2,FALSE)*H40+VLOOKUP(C40,Deflatores!G$4:I$38,3,FALSE))) -> 6
A41: Consulta Implícita | B41: CE | C41: I | D41: 20 | E41: 6 | F41: =IF(ISBLANK(B41),"",IF(I41="L","Baixa",IF(I41="A","Média",IF(I41="","","Alta")))) -> Alta | G41: =CONCATENATE(B41,I41) -> CEH | H41: =IF(ISBLANK(B41),"",IF(B41="ALI",IF(I41="L",7,IF(I41="A",10,15)),IF(B41="AIE",IF(I41="L",5,IF(I41="A",7,10)),IF(B41="SE",IF(I41="L",4,IF(I41="A",5,7)),IF(OR(B41="EE",B41="CE"),IF(I41="L",3,IF(I41="A",4,6)),0))))) -> 6 | I41: =IF(OR(ISBLANK(D41),ISBLANK(E41)),IF(OR(B41="ALI",B41="AIE"),"L",IF(OR(B41="EE",B41="SE",B41="CE"),"A","")),IF(B41="EE",IF(E41>=3,IF(D41>=5,"H","A"),IF(E41>=2,IF(D41>=16,"H",IF(D41<=4,"L","A")),IF(D41<=15,"L","A"))),IF(OR(B41="SE",B41="CE"),IF(E41>=4,IF(D41>=6,"H","A"),IF(E41>=2,IF(D41>=20,"H",IF(D41<=5,"L","A")),IF(D41<=19,"L","A"))),IF(OR(B41="ALI",B41="AIE"),IF(E41>=6,IF(D41>=20,"H","A"),IF(E41>=2,IF(D41>=51,"H",IF(D41<=19,"L","A")),IF(D41<=50,"L","A"))),"")))) -> H | J41: =CONCATENATE(B41,C41) -> CEI | K41: =IF(OR(H41="",H41=0),L41,H41) -> 6 | L41: =IF(NOT(ISERROR(VLOOKUP(B41,Deflatores!G$42:H$64,2,FALSE))),VLOOKUP(B41,Deflatores!G$42:H$64,2,FALSE),IF(OR(ISBLANK(C41),ISBLANK(B41)),"",VLOOKUP(C41,Deflatores!G$4:H$38,2,FALSE)*H41+VLOOKUP(C41,Deflatores!G$4:I$38,3,FALSE))) -> 6
A42: Cadastrar Ocupantes | B42: EE | C42: I | D42: 12 | E42: 6 | F42: =IF(ISBLANK(B42),"",IF(I42="L","Baixa",IF(I42="A","Média",IF(I42="","","Alta")))) -> Alta | G42: =CONCATENATE(B42,I42) -> EEH | H42: =IF(ISBLANK(B42),"",IF(B42="ALI",IF(I42="L",7,IF(I42="A",10,15)),IF(B42="AIE",IF(I42="L",5,IF(I42="A",7,10)),IF(B42="SE",IF(I42="L",4,IF(I42="A",5,7)),IF(OR(B42="EE",B42="CE"),IF(I42="L",3,IF(I42="A",4,6)),0))))) -> 6 | I42: =IF(OR(ISBLANK(D42),ISBLANK(E42)),IF(OR(B42="ALI",B42="AIE"),"L",IF(OR(B42="EE",B42="SE",B42="CE"),"A","")),IF(B42="EE",IF(E42>=3,IF(D42>=5,"H","A"),IF(E42>=2,IF(D42>=16,"H",IF(D42<=4,"L","A")),IF(D42<=15,"L","A"))),IF(OR(B42="SE",B42="CE"),IF(E42>=4,IF(D42>=6,"H","A"),IF(E42>=2,IF(D42>=20,"H",IF(D42<=5,"L","A")),IF(D42<=19,"L","A"))),IF(OR(B42="ALI",B42="AIE"),IF(E42>=6,IF(D42>=20,"H","A"),IF(E42>=2,IF(D42>=51,"H",IF(D42<=19,"L","A")),IF(D42<=50,"L","A"))),"")))) -> H | J42: =CONCATENATE(B42,C42) -> EEI | K42: =IF(OR(H42="",H42=0),L42,H42) -> 6 | L42: =IF(NOT(ISERROR(VLOOKUP(B42,Deflatores!G$42:H$64,2,FALSE))),VLOOKUP(B42,Deflatores!G$42:H$64,2,FALSE),IF(OR(ISBLANK(C42),ISBLANK(B42)),"",VLOOKUP(C42,Deflatores!G$4:H$38,2,FALSE)*H42+VLOOKUP(C42,Deflatores!G$4:I$38,3,FALSE))) -> 6
A43: Combobox listar finalidade da ocupação | B43: CE | C43: I | D43: 2 | E43: 1 | F43: =IF(ISBLANK(B43),"",IF(I43="L","Baixa",IF(I43="A","Média",IF(I43="","","Alta")))) -> Baixa | G43: =CONCATENATE(B43,I43) -> CEL | H43: =IF(ISBLANK(B43),"",IF(B43="ALI",IF(I43="L",7,IF(I43="A",10,15)),IF(B43="AIE",IF(I43="L",5,IF(I43="A",7,10)),IF(B43="SE",IF(I43="L",4,IF(I43="A",5,7)),IF(OR(B43="EE",B43="CE"),IF(I43="L",3,IF(I43="A",4,6)),0))))) -> 3 | I43: =IF(OR(ISBLANK(D43),ISBLANK(E43)),IF(OR(B43="ALI",B43="AIE"),"L",IF(OR(B43="EE",B43="SE",B43="CE"),"A","")),IF(B43="EE",IF(E43>=3,IF(D43>=5,"H","A"),IF(E43>=2,IF(D43>=16,"H",IF(D43<=4,"L","A")),IF(D43<=15,"L","A"))),IF(OR(B43="SE",B43="CE"),IF(E43>=4,IF(D43>=6,"H","A"),IF(E43>=2,IF(D43>=20,"H",IF(D43<=5,"L","A")),IF(D43<=19,"L","A"))),IF(OR(B43="ALI",B43="AIE"),IF(E43>=6,IF(D43>=20,"H","A"),IF(E43>=2,IF(D43>=51,"H",IF(D43<=19,"L","A")),IF(D43<=50,"L","A"))),"")))) -> L | J43: =CONCATENATE(B43,C43) -> CEI | K43: =IF(OR(H43="",H43=0),L43,H43) -> 3 | L43: =IF(NOT(ISERROR(VLOOKUP(B43,Deflatores!G$42:H$64,2,FALSE))),VLOOKUP(B43,Deflatores!G$42:H$64,2,FALSE),IF(OR(ISBLANK(C43),ISBLANK(B43)),"",VLOOKUP(C43,Deflatores!G$4:H$38,2,FALSE)*H43+VLOOKUP(C43,Deflatores!G$4:I$38,3,FALSE))) -> 3
A44: Combobox listar tipo de outorga | B44: CE | C44: I | D44: 2 | E44: 1 | F44: =IF(ISBLANK(B44),"",IF(I44="L","Baixa",IF(I44="A","Média",IF(I44="","","Alta")))) -> Baixa | G44: =CONCATENATE(B44,I44) -> CEL | H44: =IF(ISBLANK(B44),"",IF(B44="ALI",IF(I44="L",7,IF(I44="A",10,15)),IF(B44="AIE",IF(I44="L",5,IF(I44="A",7,10)),IF(B44="SE",IF(I44="L",4,IF(I44="A",5,7)),IF(OR(B44="EE",B44="CE"),IF(I44="L",3,IF(I44="A",4,6)),0))))) -> 3 | I44: =IF(OR(ISBLANK(D44),ISBLANK(E44)),IF(OR(B44="ALI",B44="AIE"),"L",IF(OR(B44="EE",B44="SE",B44="CE"),"A","")),IF(B44="EE",IF(E44>=3,IF(D44>=5,"H","A"),IF(E44>=2,IF(D44>=16,"H",IF(D44<=4,"L","A")),IF(D44<=15,"L","A"))),IF(OR(B44="SE",B44="CE"),IF(E44>=4,IF(D44>=6,"H","A"),IF(E44>=2,IF(D44>=20,"H",IF(D44<=5,"L","A")),IF(D44<=19,"L","A"))),IF(OR(B44="ALI",B44="AIE"),IF(E44>=6,IF(D44>=20,"H","A"),IF(E44>=2,IF(D44>=51,"H",IF(D44<=19,"L","A")),IF(D44<=50,"L","A"))),"")))) -> L | J44: =CONCATENATE(B44,C44) -> CEI | K44: =IF(OR(H44="",H44=0),L44,H44) -> 3 | L44: =IF(NOT(ISERROR(VLOOKUP(B44,Deflatores!G$42:H$64,2,FALSE))),VLOOKUP(B44,Deflatores!G$42:H$64,2,FALSE),IF(OR(ISBLANK(C44),ISBLANK(B44)),"",VLOOKUP(C44,Deflatores!G$4:H$38,2,FALSE)*H44+VLOOKUP(C44,Deflatores!G$4:I$38,3,FALSE))) -> 3
A45: Editar Ocupantes | B45: EE | C45: I | D45: 18 | E45: 6 | F45: =IF(ISBLANK(B45),"",IF(I45="L","Baixa",IF(I45="A","Média",IF(I45="","","Alta")))) -> Alta | G45: =CONCATENATE(B45,I45) -> EEH | H45: =IF(ISBLANK(B45),"",IF(B45="ALI",IF(I45="L",7,IF(I45="A",10,15)),IF(B45="AIE",IF(I45="L",5,IF(I45="A",7,10)),IF(B45="SE",IF(I45="L",4,IF(I45="A",5,7)),IF(OR(B45="EE",B45="CE"),IF(I45="L",3,IF(I45="A",4,6)),0))))) -> 6 | I45: =IF(OR(ISBLANK(D45),ISBLANK(E45)),IF(OR(B45="ALI",B45="AIE"),"L",IF(OR(B45="EE",B45="SE",B45="CE"),"A","")),IF(B45="EE",IF(E45>=3,IF(D45>=5,"H","A"),IF(E45>=2,IF(D45>=16,"H",IF(D45<=4,"L","A")),IF(D45<=15,"L","A"))),IF(OR(B45="SE",B45="CE"),IF(E45>=4,IF(D45>=6,"H","A"),IF(E45>=2,IF(D45>=20,"H",IF(D45<=5,"L","A")),IF(D45<=19,"L","A"))),IF(OR(B45="ALI",B45="AIE"),IF(E45>=6,IF(D45>=20,"H","A"),IF(E45>=2,IF(D45>=51,"H",IF(D45<=19,"L","A")),IF(D45<=50,"L","A"))),"")))) -> H | J45: =CONCATENATE(B45,C45) -> EEI | K45: =IF(OR(H45="",H45=0),L45,H45) -> 6 | L45: =IF(NOT(ISERROR(VLOOKUP(B45,Deflatores!G$42:H$64,2,FALSE))),VLOOKUP(B45,Deflatores!G$42:H$64,2,FALSE),IF(OR(ISBLANK(C45),ISBLANK(B45)),"",VLOOKUP(C45,Deflatores!G$4:H$38,2,FALSE)*H45+VLOOKUP(C45,Deflatores!G$4:I$38,3,FALSE))) -> 6
A46: Consulta Implícia | B46: CE | C46: I | D46: 14 | E46: 5 | F46: =IF(ISBLANK(B46),"",IF(I46="L","Baixa",IF(I46="A","Média",IF(I46="","","Alta")))) -> Alta | G46: =CONCATENATE(B46,I46) -> CEH | H46: =IF(ISBLANK(B46),"",IF(B46="ALI",IF(I46="L",7,IF(I46="A",10,15)),IF(B46="AIE",IF(I46="L",5,IF(I46="A",7,10)),IF(B46="SE",IF(I46="L",4,IF(I46="A",5,7)),IF(OR(B46="EE",B46="CE"),IF(I46="L",3,IF(I46="A",4,6)),0))))) -> 6 | I46: =IF(OR(ISBLANK(D46),ISBLANK(E46)),IF(OR(B46="ALI",B46="AIE"),"L",IF(OR(B46="EE",B46="SE",B46="CE"),"A","")),IF(B46="EE",IF(E46>=3,IF(D46>=5,"H","A"),IF(E46>=2,IF(D46>=16,"H",IF(D46<=4,"L","A")),IF(D46<=15,"L","A"))),IF(OR(B46="SE",B46="CE"),IF(E46>=4,IF(D46>=6,"H","A"),IF(E46>=2,IF(D46>=20,"H",IF(D46<=5,"L","A")),IF(D46<=19,"L","A"))),IF(OR(B46="ALI",B46="AIE"),IF(E46>=6,IF(D46>=20,"H","A"),IF(E46>=2,IF(D46>=51,"H",IF(D46<=19,"L","A")),IF(D46<=50,"L","A"))),"")))) -> H | J46: =CONCATENATE(B46,C46) -> CEI | K46: =IF(OR(H46="",H46=0),L46,H46) -> 6 | L46: =IF(NOT(ISERROR(VLOOKUP(B46,Deflatores!G$42:H$64,2,FALSE))),VLOOKUP(B46,Deflatores!G$42:H$64,2,FALSE),IF(OR(ISBLANK(C46),ISBLANK(B46)),"",VLOOKUP(C46,Deflatores!G$4:H$38,2,FALSE)*H46+VLOOKUP(C46,Deflatores!G$4:I$38,3,FALSE))) -> 6
A47: Listar Ocupantes | B47: CE | C47: I | D47: 13 | E47: 3 | F47: =IF(ISBLANK(B47),"",IF(I47="L","Baixa",IF(I47="A","Média",IF(I47="","","Alta")))) -> Média | G47: =CONCATENATE(B47,I47) -> CEA | H47: =IF(ISBLANK(B47),"",IF(B47="ALI",IF(I47="L",7,IF(I47="A",10,15)),IF(B47="AIE",IF(I47="L",5,IF(I47="A",7,10)),IF(B47="SE",IF(I47="L",4,IF(I47="A",5,7)),IF(OR(B47="EE",B47="CE"),IF(I47="L",3,IF(I47="A",4,6)),0))))) -> 4 | I47: =IF(OR(ISBLANK(D47),ISBLANK(E47)),IF(OR(B47="ALI",B47="AIE"),"L",IF(OR(B47="EE",B47="SE",B47="CE"),"A","")),IF(B47="EE",IF(E47>=3,IF(D47>=5,"H","A"),IF(E47>=2,IF(D47>=16,"H",IF(D47<=4,"L","A")),IF(D47<=15,"L","A"))),IF(OR(B47="SE",B47="CE"),IF(E47>=4,IF(D47>=6,"H","A"),IF(E47>=2,IF(D47>=20,"H",IF(D47<=5,"L","A")),IF(D47<=19,"L","A"))),IF(OR(B47="ALI",B47="AIE"),IF(E47>=6,IF(D47>=20,"H","A"),IF(E47>=2,IF(D47>=51,"H",IF(D47<=19,"L","A")),IF(D47<=50,"L","A"))),"")))) -> A | J47: =CONCATENATE(B47,C47) -> CEI | K47: =IF(OR(H47="",H47=0),L47,H47) -> 4 | L47: =IF(NOT(ISERROR(VLOOKUP(B47,Deflatores!G$42:H$64,2,FALSE))),VLOOKUP(B47,Deflatores!G$42:H$64,2,FALSE),IF(OR(ISBLANK(C47),ISBLANK(B47)),"",VLOOKUP(C47,Deflatores!G$4:H$38,2,FALSE)*H47+VLOOKUP(C47,Deflatores!G$4:I$38,3,FALSE))) -> 4
A48: Excluir Ocupantes | B48: EE | C48: I | D48: 3 | E48: 1 | F48: =IF(ISBLANK(B48),"",IF(I48="L","Baixa",IF(I48="A","Média",IF(I48="","","Alta")))) -> Baixa | G48: =CONCATENATE(B48,I48) -> EEL | H48: =IF(ISBLANK(B48),"",IF(B48="ALI",IF(I48="L",7,IF(I48="A",10,15)),IF(B48="AIE",IF(I48="L",5,IF(I48="A",7,10)),IF(B48="SE",IF(I48="L",4,IF(I48="A",5,7)),IF(OR(B48="EE",B48="CE"),IF(I48="L",3,IF(I48="A",4,6)),0))))) -> 3 | I48: =IF(OR(ISBLANK(D48),ISBLANK(E48)),IF(OR(B48="ALI",B48="AIE"),"L",IF(OR(B48="EE",B48="SE",B48="CE"),"A","")),IF(B48="EE",IF(E48>=3,IF(D48>=5,"H","A"),IF(E48>=2,IF(D48>=16,"H",IF(D48<=4,"L","A")),IF(D48<=15,"L","A"))),IF(OR(B48="SE",B48="CE"),IF(E48>=4,IF(D48>=6,"H","A"),IF(E48>=2,IF(D48>=20,"H",IF(D48<=5,"L","A")),IF(D48<=19,"L","A"))),IF(OR(B48="ALI",B48="AIE"),IF(E48>=6,IF(D48>=20,"H","A"),IF(E48>=2,IF(D48>=51,"H",IF(D48<=19,"L","A")),IF(D48<=50,"L","A"))),"")))) -> L | J48: =CONCATENATE(B48,C48) -> EEI | K48: =IF(OR(H48="",H48=0),L48,H48) -> 3 | L48: =IF(NOT(ISERROR(VLOOKUP(B48,Deflatores!G$42:H$64,2,FALSE))),VLOOKUP(B48,Deflatores!G$42:H$64,2,FALSE),IF(OR(ISBLANK(C48),ISBLANK(B48)),"",VLOOKUP(C48,Deflatores!G$4:H$38,2,FALSE)*H48+VLOOKUP(C48,Deflatores!G$4:I$38,3,FALSE))) -> 3
A49: Visualizar Identificação | B49: CE | C49: I | D49: 38 | E49: 5 | F49: =IF(ISBLANK(B49),"",IF(I49="L","Baixa",IF(I49="A","Média",IF(I49="","","Alta")))) -> Alta | G49: =CONCATENATE(B49,I49) -> CEH | H49: =IF(ISBLANK(B49),"",IF(B49="ALI",IF(I49="L",7,IF(I49="A",10,15)),IF(B49="AIE",IF(I49="L",5,IF(I49="A",7,10)),IF(B49="SE",IF(I49="L",4,IF(I49="A",5,7)),IF(OR(B49="EE",B49="CE"),IF(I49="L",3,IF(I49="A",4,6)),0))))) -> 6 | I49: =IF(OR(ISBLANK(D49),ISBLANK(E49)),IF(OR(B49="ALI",B49="AIE"),"L",IF(OR(B49="EE",B49="SE",B49="CE"),"A","")),IF(B49="EE",IF(E49>=3,IF(D49>=5,"H","A"),IF(E49>=2,IF(D49>=16,"H",IF(D49<=4,"L","A")),IF(D49<=15,"L","A"))),IF(OR(B49="SE",B49="CE"),IF(E49>=4,IF(D49>=6,"H","A"),IF(E49>=2,IF(D49>=20,"H",IF(D49<=5,"L","A")),IF(D49<=19,"L","A"))),IF(OR(B49="ALI",B49="AIE"),IF(E49>=6,IF(D49>=20,"H","A"),IF(E49>=2,IF(D49>=51,"H",IF(D49<=19,"L","A")),IF(D49<=50,"L","A"))),"")))) -> H | J49: =CONCATENATE(B49,C49) -> CEI | K49: =IF(OR(H49="",H49=0),L49,H49) -> 6 | L49: =IF(NOT(ISERROR(VLOOKUP(B49,Deflatores!G$42:H$64,2,FALSE))),VLOOKUP(B49,Deflatores!G$42:H$64,2,FALSE),IF(OR(ISBLANK(C49),ISBLANK(B49)),"",VLOOKUP(C49,Deflatores!G$4:H$38,2,FALSE)*H49+VLOOKUP(C49,Deflatores!G$4:I$38,3,FALSE))) -> 6
A50: Modal seleção PF ou PJ | B50: EE | C50: I | D50: 13 | E50: 2 | F50: Baixa | G50: 3 | H50: 3 | I50: 3 | K50: =IF(OR(H50="",H50=0),L50,H50) -> 3 | L50: =IF(NOT(ISERROR(VLOOKUP(B50,Deflatores!G$42:H$64,2,FALSE))),VLOOKUP(B50,Deflatores!G$42:H$64,2,FALSE),IF(OR(ISBLANK(C50),ISBLANK(B50)),"",VLOOKUP(C50,Deflatores!G$4:H$38,2,FALSE)*H50+VLOOKUP(C50,Deflatores!G$4:I$38,3,FALSE))) -> 3
A51: Modal Responsável Patrimonial | B51: CE | C51: I | D51: 10 | E51: 2 | F51: =IF(ISBLANK(B51),"",IF(I51="L","Baixa",IF(I51="A","Média",IF(I51="","","Alta")))) -> Média | G51: =CONCATENATE(B51,I51) -> CEA | H51: =IF(ISBLANK(B51),"",IF(B51="ALI",IF(I51="L",7,IF(I51="A",10,15)),IF(B51="AIE",IF(I51="L",5,IF(I51="A",7,10)),IF(B51="SE",IF(I51="L",4,IF(I51="A",5,7)),IF(OR(B51="EE",B51="CE"),IF(I51="L",3,IF(I51="A",4,6)),0))))) -> 4 | I51: =IF(OR(ISBLANK(D51),ISBLANK(E51)),IF(OR(B51="ALI",B51="AIE"),"L",IF(OR(B51="EE",B51="SE",B51="CE"),"A","")),IF(B51="EE",IF(E51>=3,IF(D51>=5,"H","A"),IF(E51>=2,IF(D51>=16,"H",IF(D51<=4,"L","A")),IF(D51<=15,"L","A"))),IF(OR(B51="SE",B51="CE"),IF(E51>=4,IF(D51>=6,"H","A"),IF(E51>=2,IF(D51>=20,"H",IF(D51<=5,"L","A")),IF(D51<=19,"L","A"))),IF(OR(B51="ALI",B51="AIE"),IF(E51>=6,IF(D51>=20,"H","A"),IF(E51>=2,IF(D51>=51,"H",IF(D51<=19,"L","A")),IF(D51<=50,"L","A"))),"")))) -> A | J51: =CONCATENATE(B51,C51) -> CEI | K51: =IF(OR(H51="",H51=0),L51,H51) -> 4 | L51: =IF(NOT(ISERROR(VLOOKUP(B51,Deflatores!G$42:H$64,2,FALSE))),VLOOKUP(B51,Deflatores!G$42:H$64,2,FALSE),IF(OR(ISBLANK(C51),ISBLANK(B51)),"",VLOOKUP(C51,Deflatores!G$4:H$38,2,FALSE)*H51+VLOOKUP(C51,Deflatores!G$4:I$38,3,FALSE))) -> 4
F52: =IF(ISBLANK(B52),"",IF(I52="L","Baixa",IF(I52="A","Média",IF(I52="","","Alta")))) | G52: =CONCATENATE(B52,I52) | H52: =IF(ISBLANK(B52),"",IF(B52="ALI",IF(I52="L",7,IF(I52="A",10,15)),IF(B52="AIE",IF(I52="L",5,IF(I52="A",7,10)),IF(B52="SE",IF(I52="L",4,IF(I52="A",5,7)),IF(OR(B52="EE",B52="CE"),IF(I52="L",3,IF(I52="A",4,6)),0))))) | I52: =IF(OR(ISBLANK(D52),ISBLANK(E52)),IF(OR(B52="ALI",B52="AIE"),"L",IF(OR(B52="EE",B52="SE",B52="CE"),"A","")),IF(B52="EE",IF(E52>=3,IF(D52>=5,"H","A"),IF(E52>=2,IF(D52>=16,"H",IF(D52<=4,"L","A")),IF(D52<=15,"L","A"))),IF(OR(B52="SE",B52="CE"),IF(E52>=4,IF(D52>=6,"H","A"),IF(E52>=2,IF(D52>=20,"H",IF(D52<=5,"L","A")),IF(D52<=19,"L","A"))),IF(OR(B52="ALI",B52="AIE"),IF(E52>=6,IF(D52>=20,"H","A"),IF(E52>=2,IF(D52>=51,"H",IF(D52<=19,"L","A")),IF(D52<=50,"L","A"))),"")))) | J52: =CONCATENATE(B52,C52) | K52: =IF(OR(H52="",H52=0),L52,H52) | L52: =IF(NOT(ISERROR(VLOOKUP(B52,Deflatores!G$42:H$64,2,FALSE))),VLOOKUP(B52,Deflatores!G$42:H$64,2,FALSE),IF(OR(ISBLANK(C52),ISBLANK(B52)),"",VLOOKUP(C52,Deflatores!G$4:H$38,2,FALSE)*H52+VLOOKUP(C52,Deflatores!G$4:I$38,3,FALSE)))
A53: US 3 – Localização - Localização | C53: I | F53: =IF(ISBLANK(B53),"",IF(I53="L","Baixa",IF(I53="A","Média",IF(I53="","","Alta")))) | G53: =CONCATENATE(B53,I53) | H53: =IF(ISBLANK(B53),"",IF(B53="ALI",IF(I53="L",7,IF(I53="A",10,15)),IF(B53="AIE",IF(I53="L",5,IF(I53="A",7,10)),IF(B53="SE",IF(I53="L",4,IF(I53="A",5,7)),IF(OR(B53="EE",B53="CE"),IF(I53="L",3,IF(I53="A",4,6)),0))))) | I53: =IF(OR(ISBLANK(D53),ISBLANK(E53)),IF(OR(B53="ALI",B53="AIE"),"L",IF(OR(B53="EE",B53="SE",B53="CE"),"A","")),IF(B53="EE",IF(E53>=3,IF(D53>=5,"H","A"),IF(E53>=2,IF(D53>=16,"H",IF(D53<=4,"L","A")),IF(D53<=15,"L","A"))),IF(OR(B53="SE",B53="CE"),IF(E53>=4,IF(D53>=6,"H","A"),IF(E53>=2,IF(D53>=20,"H",IF(D53<=5,"L","A")),IF(D53<=19,"L","A"))),IF(OR(B53="ALI",B53="AIE"),IF(E53>=6,IF(D53>=20,"H","A"),IF(E53>=2,IF(D53>=51,"H",IF(D53<=19,"L","A")),IF(D53<=50,"L","A"))),"")))) | J53: =CONCATENATE(B53,C53) -> I | K53: =IF(OR(H53="",H53=0),L53,H53) | L53: =IF(NOT(ISERROR(VLOOKUP(B53,Deflatores!G$42:H$64,2,FALSE))),VLOOKUP(B53,Deflatores!G$42:H$64,2,FALSE),IF(OR(ISBLANK(C53),ISBLANK(B53)),"",VLOOKUP(C53,Deflatores!G$4:H$38,2,FALSE)*H53+VLOOKUP(C53,Deflatores!G$4:I$38,3,FALSE)))
A54: Município | B54: AIE | C54: I | D54: 4 | E54: 1 | F54: =IF(ISBLANK(B54),"",IF(I54="L","Baixa",IF(I54="A","Média",IF(I54="","","Alta")))) -> Baixa | G54: =CONCATENATE(B54,I54) -> AIEL | H54: =IF(ISBLANK(B54),"",IF(B54="ALI",IF(I54="L",7,IF(I54="A",10,15)),IF(B54="AIE",IF(I54="L",5,IF(I54="A",7,10)),IF(B54="SE",IF(I54="L",4,IF(I54="A",5,7)),IF(OR(B54="EE",B54="CE"),IF(I54="L",3,IF(I54="A",4,6)),0))))) -> 5 | I54: =IF(OR(ISBLANK(D54),ISBLANK(E54)),IF(OR(B54="ALI",B54="AIE"),"L",IF(OR(B54="EE",B54="SE",B54="CE"),"A","")),IF(B54="EE",IF(E54>=3,IF(D54>=5,"H","A"),IF(E54>=2,IF(D54>=16,"H",IF(D54<=4,"L","A")),IF(D54<=15,"L","A"))),IF(OR(B54="SE",B54="CE"),IF(E54>=4,IF(D54>=6,"H","A"),IF(E54>=2,IF(D54>=20,"H",IF(D54<=5,"L","A")),IF(D54<=19,"L","A"))),IF(OR(B54="ALI",B54="AIE"),IF(E54>=6,IF(D54>=20,"H","A"),IF(E54>=2,IF(D54>=51,"H",IF(D54<=19,"L","A")),IF(D54<=50,"L","A"))),"")))) -> L | J54: =CONCATENATE(B54,C54) -> AIEI | K54: =IF(OR(H54="",H54=0),L54,H54) -> 5 | L54: =IF(NOT(ISERROR(VLOOKUP(B54,Deflatores!G$42:H$64,2,FALSE))),VLOOKUP(B54,Deflatores!G$42:H$64,2,FALSE),IF(OR(ISBLANK(C54),ISBLANK(B54)),"",VLOOKUP(C54,Deflatores!G$4:H$38,2,FALSE)*H54+VLOOKUP(C54,Deflatores!G$4:I$38,3,FALSE))) -> 5
A55: Cadastrar Localização | B55: EE | C55: I | D55: 18 | E55: 2 | F55: =IF(ISBLANK(B55),"",IF(I55="L","Baixa",IF(I55="A","Média",IF(I55="","","Alta")))) -> Alta | G55: =CONCATENATE(B55,I55) -> EEH | H55: =IF(ISBLANK(B55),"",IF(B55="ALI",IF(I55="L",7,IF(I55="A",10,15)),IF(B55="AIE",IF(I55="L",5,IF(I55="A",7,10)),IF(B55="SE",IF(I55="L",4,IF(I55="A",5,7)),IF(OR(B55="EE",B55="CE"),IF(I55="L",3,IF(I55="A",4,6)),0))))) -> 6 | I55: =IF(OR(ISBLANK(D55),ISBLANK(E55)),IF(OR(B55="ALI",B55="AIE"),"L",IF(OR(B55="EE",B55="SE",B55="CE"),"A","")),IF(B55="EE",IF(E55>=3,IF(D55>=5,"H","A"),IF(E55>=2,IF(D55>=16,"H",IF(D55<=4,"L","A")),IF(D55<=15,"L","A"))),IF(OR(B55="SE",B55="CE"),IF(E55>=4,IF(D55>=6,"H","A"),IF(E55>=2,IF(D55>=20,"H",IF(D55<=5,"L","A")),IF(D55<=19,"L","A"))),IF(OR(B55="ALI",B55="AIE"),IF(E55>=6,IF(D55>=20,"H","A"),IF(E55>=2,IF(D55>=51,"H",IF(D55<=19,"L","A")),IF(D55<=50,"L","A"))),"")))) -> H | J55: =CONCATENATE(B55,C55) -> EEI | K55: =IF(OR(H55="",H55=0),L55,H55) -> 6 | L55: =IF(NOT(ISERROR(VLOOKUP(B55,Deflatores!G$42:H$64,2,FALSE))),VLOOKUP(B55,Deflatores!G$42:H$64,2,FALSE),IF(OR(ISBLANK(C55),ISBLANK(B55)),"",VLOOKUP(C55,Deflatores!G$4:H$38,2,FALSE)*H55+VLOOKUP(C55,Deflatores!G$4:I$38,3,FALSE))) -> 6
A56: Combobox listar município | B56: CE | C56: I | D56: 4 | E56: 1 | F56: =IF(ISBLANK(B56),"",IF(I56="L","Baixa",IF(I56="A","Média",IF(I56="","","Alta")))) -> Baixa | G56: =CONCATENATE(B56,I56) -> CEL | H56: =IF(ISBLANK(B56),"",IF(B56="ALI",IF(I56="L",7,IF(I56="A",10,15)),IF(B56="AIE",IF(I56="L",5,IF(I56="A",7,10)),IF(B56="SE",IF(I56="L",4,IF(I56="A",5,7)),IF(OR(B56="EE",B56="CE"),IF(I56="L",3,IF(I56="A",4,6)),0))))) -> 3 | I56: =IF(OR(ISBLANK(D56),ISBLANK(E56)),IF(OR(B56="ALI",B56="AIE"),"L",IF(OR(B56="EE",B56="SE",B56="CE"),"A","")),IF(B56="EE",IF(E56>=3,IF(D56>=5,"H","A"),IF(E56>=2,IF(D56>=16,"H",IF(D56<=4,"L","A")),IF(D56<=15,"L","A"))),IF(OR(B56="SE",B56="CE"),IF(E56>=4,IF(D56>=6,"H","A"),IF(E56>=2,IF(D56>=20,"H",IF(D56<=5,"L","A")),IF(D56<=19,"L","A"))),IF(OR(B56="ALI",B56="AIE"),IF(E56>=6,IF(D56>=20,"H","A"),IF(E56>=2,IF(D56>=51,"H",IF(D56<=19,"L","A")),IF(D56<=50,"L","A"))),"")))) -> L | J56: =CONCATENATE(B56,C56) -> CEI | K56: =IF(OR(H56="",H56=0),L56,H56) -> 3 | L56: =IF(NOT(ISERROR(VLOOKUP(B56,Deflatores!G$42:H$64,2,FALSE))),VLOOKUP(B56,Deflatores!G$42:H$64,2,FALSE),IF(OR(ISBLANK(C56),ISBLANK(B56)),"",VLOOKUP(C56,Deflatores!G$4:H$38,2,FALSE)*H56+VLOOKUP(C56,Deflatores!G$4:I$38,3,FALSE))) -> 3
A57: Combobox listar zoneamento | B57: CE | C57: I | D57: 2 | E57: 1 | F57: =IF(ISBLANK(B57),"",IF(I57="L","Baixa",IF(I57="A","Média",IF(I57="","","Alta")))) -> Baixa | G57: =CONCATENATE(B57,I57) -> CEL | H57: =IF(ISBLANK(B57),"",IF(B57="ALI",IF(I57="L",7,IF(I57="A",10,15)),IF(B57="AIE",IF(I57="L",5,IF(I57="A",7,10)),IF(B57="SE",IF(I57="L",4,IF(I57="A",5,7)),IF(OR(B57="EE",B57="CE"),IF(I57="L",3,IF(I57="A",4,6)),0))))) -> 3 | I57: =IF(OR(ISBLANK(D57),ISBLANK(E57)),IF(OR(B57="ALI",B57="AIE"),"L",IF(OR(B57="EE",B57="SE",B57="CE"),"A","")),IF(B57="EE",IF(E57>=3,IF(D57>=5,"H","A"),IF(E57>=2,IF(D57>=16,"H",IF(D57<=4,"L","A")),IF(D57<=15,"L","A"))),IF(OR(B57="SE",B57="CE"),IF(E57>=4,IF(D57>=6,"H","A"),IF(E57>=2,IF(D57>=20,"H",IF(D57<=5,"L","A")),IF(D57<=19,"L","A"))),IF(OR(B57="ALI",B57="AIE"),IF(E57>=6,IF(D57>=20,"H","A"),IF(E57>=2,IF(D57>=51,"H",IF(D57<=19,"L","A")),IF(D57<=50,"L","A"))),"")))) -> L | J57: =CONCATENATE(B57,C57) -> CEI | K57: =IF(OR(H57="",H57=0),L57,H57) -> 3 | L57: =IF(NOT(ISERROR(VLOOKUP(B57,Deflatores!G$42:H$64,2,FALSE))),VLOOKUP(B57,Deflatores!G$42:H$64,2,FALSE),IF(OR(ISBLANK(C57),ISBLANK(B57)),"",VLOOKUP(C57,Deflatores!G$4:H$38,2,FALSE)*H57+VLOOKUP(C57,Deflatores!G$4:I$38,3,FALSE))) -> 3
A58: Combobox listar unidade de medida | B58: CE | C58: I | D58: 2 | E58: 1 | F58: =IF(ISBLANK(B58),"",IF(I58="L","Baixa",IF(I58="A","Média",IF(I58="","","Alta")))) -> Baixa | G58: =CONCATENATE(B58,I58) -> CEL | H58: =IF(ISBLANK(B58),"",IF(B58="ALI",IF(I58="L",7,IF(I58="A",10,15)),IF(B58="AIE",IF(I58="L",5,IF(I58="A",7,10)),IF(B58="SE",IF(I58="L",4,IF(I58="A",5,7)),IF(OR(B58="EE",B58="CE"),IF(I58="L",3,IF(I58="A",4,6)),0))))) -> 3 | I58: =IF(OR(ISBLANK(D58),ISBLANK(E58)),IF(OR(B58="ALI",B58="AIE"),"L",IF(OR(B58="EE",B58="SE",B58="CE"),"A","")),IF(B58="EE",IF(E58>=3,IF(D58>=5,"H","A"),IF(E58>=2,IF(D58>=16,"H",IF(D58<=4,"L","A")),IF(D58<=15,"L","A"))),IF(OR(B58="SE",B58="CE"),IF(E58>=4,IF(D58>=6,"H","A"),IF(E58>=2,IF(D58>=20,"H",IF(D58<=5,"L","A")),IF(D58<=19,"L","A"))),IF(OR(B58="ALI",B58="AIE"),IF(E58>=6,IF(D58>=20,"H","A"),IF(E58>=2,IF(D58>=51,"H",IF(D58<=19,"L","A")),IF(D58<=50,"L","A"))),"")))) -> L | J58: =CONCATENATE(B58,C58) -> CEI | K58: =IF(OR(H58="",H58=0),L58,H58) -> 3 | L58: =IF(NOT(ISERROR(VLOOKUP(B58,Deflatores!G$42:H$64,2,FALSE))),VLOOKUP(B58,Deflatores!G$42:H$64,2,FALSE),IF(OR(ISBLANK(C58),ISBLANK(B58)),"",VLOOKUP(C58,Deflatores!G$4:H$38,2,FALSE)*H58+VLOOKUP(C58,Deflatores!G$4:I$38,3,FALSE))) -> 3
A59: Editar Localização | B59: EE | C59: I | D59: 19 | E59: 2 | F59: =IF(ISBLANK(B59),"",IF(I59="L","Baixa",IF(I59="A","Média",IF(I59="","","Alta")))) -> Alta | G59: =CONCATENATE(B59,I59) -> EEH | H59: =IF(ISBLANK(B59),"",IF(B59="ALI",IF(I59="L",7,IF(I59="A",10,15)),IF(B59="AIE",IF(I59="L",5,IF(I59="A",7,10)),IF(B59="SE",IF(I59="L",4,IF(I59="A",5,7)),IF(OR(B59="EE",B59="CE"),IF(I59="L",3,IF(I59="A",4,6)),0))))) -> 6 | I59: =IF(OR(ISBLANK(D59),ISBLANK(E59)),IF(OR(B59="ALI",B59="AIE"),"L",IF(OR(B59="EE",B59="SE",B59="CE"),"A","")),IF(B59="EE",IF(E59>=3,IF(D59>=5,"H","A"),IF(E59>=2,IF(D59>=16,"H",IF(D59<=4,"L","A")),IF(D59<=15,"L","A"))),IF(OR(B59="SE",B59="CE"),IF(E59>=4,IF(D59>=6,"H","A"),IF(E59>=2,IF(D59>=20,"H",IF(D59<=5,"L","A")),IF(D59<=19,"L","A"))),IF(OR(B59="ALI",B59="AIE"),IF(E59>=6,IF(D59>=20,"H","A"),IF(E59>=2,IF(D59>=51,"H",IF(D59<=19,"L","A")),IF(D59<=50,"L","A"))),"")))) -> H | J59: =CONCATENATE(B59,C59) -> EEI | K59: =IF(OR(H59="",H59=0),L59,H59) -> 6 | L59: =IF(NOT(ISERROR(VLOOKUP(B59,Deflatores!G$42:H$64,2,FALSE))),VLOOKUP(B59,Deflatores!G$42:H$64,2,FALSE),IF(OR(ISBLANK(C59),ISBLANK(B59)),"",VLOOKUP(C59,Deflatores!G$4:H$38,2,FALSE)*H59+VLOOKUP(C59,Deflatores!G$4:I$38,3,FALSE))) -> 6
A60: Consulta Implícia | B60: CE | C60: I | D60: 14 | E60: 1 | F60: =IF(ISBLANK(B60),"",IF(I60="L","Baixa",IF(I60="A","Média",IF(I60="","","Alta")))) -> Baixa | G60: =CONCATENATE(B60,I60) -> CEL | H60: =IF(ISBLANK(B60),"",IF(B60="ALI",IF(I60="L",7,IF(I60="A",10,15)),IF(B60="AIE",IF(I60="L",5,IF(I60="A",7,10)),IF(B60="SE",IF(I60="L",4,IF(I60="A",5,7)),IF(OR(B60="EE",B60="CE"),IF(I60="L",3,IF(I60="A",4,6)),0))))) -> 3 | I60: =IF(OR(ISBLANK(D60),ISBLANK(E60)),IF(OR(B60="ALI",B60="AIE"),"L",IF(OR(B60="EE",B60="SE",B60="CE"),"A","")),IF(B60="EE",IF(E60>=3,IF(D60>=5,"H","A"),IF(E60>=2,IF(D60>=16,"H",IF(D60<=4,"L","A")),IF(D60<=15,"L","A"))),IF(OR(B60="SE",B60="CE"),IF(E60>=4,IF(D60>=6,"H","A"),IF(E60>=2,IF(D60>=20,"H",IF(D60<=5,"L","A")),IF(D60<=19,"L","A"))),IF(OR(B60="ALI",B60="AIE"),IF(E60>=6,IF(D60>=20,"H","A"),IF(E60>=2,IF(D60>=51,"H",IF(D60<=19,"L","A")),IF(D60<=50,"L","A"))),"")))) -> L | J60: =CONCATENATE(B60,C60) -> CEI | K60: =IF(OR(H60="",H60=0),L60,H60) -> 3 | L60: =IF(NOT(ISERROR(VLOOKUP(B60,Deflatores!G$42:H$64,2,FALSE))),VLOOKUP(B60,Deflatores!G$42:H$64,2,FALSE),IF(OR(ISBLANK(C60),ISBLANK(B60)),"",VLOOKUP(C60,Deflatores!G$4:H$38,2,FALSE)*H60+VLOOKUP(C60,Deflatores!G$4:I$38,3,FALSE))) -> 3
A61: Visualizar Localização | B61: CE | C61: I | D61: 19 | E61: 2 | F61: =IF(ISBLANK(B61),"",IF(I61="L","Baixa",IF(I61="A","Média",IF(I61="","","Alta")))) -> Média | G61: =CONCATENATE(B61,I61) -> CEA | H61: =IF(ISBLANK(B61),"",IF(B61="ALI",IF(I61="L",7,IF(I61="A",10,15)),IF(B61="AIE",IF(I61="L",5,IF(I61="A",7,10)),IF(B61="SE",IF(I61="L",4,IF(I61="A",5,7)),IF(OR(B61="EE",B61="CE"),IF(I61="L",3,IF(I61="A",4,6)),0))))) -> 4 | I61: =IF(OR(ISBLANK(D61),ISBLANK(E61)),IF(OR(B61="ALI",B61="AIE"),"L",IF(OR(B61="EE",B61="SE",B61="CE"),"A","")),IF(B61="EE",IF(E61>=3,IF(D61>=5,"H","A"),IF(E61>=2,IF(D61>=16,"H",IF(D61<=4,"L","A")),IF(D61<=15,"L","A"))),IF(OR(B61="SE",B61="CE"),IF(E61>=4,IF(D61>=6,"H","A"),IF(E61>=2,IF(D61>=20,"H",IF(D61<=5,"L","A")),IF(D61<=19,"L","A"))),IF(OR(B61="ALI",B61="AIE"),IF(E61>=6,IF(D61>=20,"H","A"),IF(E61>=2,IF(D61>=51,"H",IF(D61<=19,"L","A")),IF(D61<=50,"L","A"))),"")))) -> A | J61: =CONCATENATE(B61,C61) -> CEI | K61: =IF(OR(H61="",H61=0),L61,H61) -> 4 | L61: =IF(NOT(ISERROR(VLOOKUP(B61,Deflatores!G$42:H$64,2,FALSE))),VLOOKUP(B61,Deflatores!G$42:H$64,2,FALSE),IF(OR(ISBLANK(C61),ISBLANK(B61)),"",VLOOKUP(C61,Deflatores!G$4:H$38,2,FALSE)*H61+VLOOKUP(C61,Deflatores!G$4:I$38,3,FALSE))) -> 4
A62: Modal compor matrícula | B62: EE | C62: E | D62: 8 | E62: 1 | F62: =IF(ISBLANK(B62),"",IF(I62="L","Baixa",IF(I62="A","Média",IF(I62="","","Alta")))) -> Baixa | G62: =CONCATENATE(B62,I62) -> EEL | H62: =IF(ISBLANK(B62),"",IF(B62="ALI",IF(I62="L",7,IF(I62="A",10,15)),IF(B62="AIE",IF(I62="L",5,IF(I62="A",7,10)),IF(B62="SE",IF(I62="L",4,IF(I62="A",5,7)),IF(OR(B62="EE",B62="CE"),IF(I62="L",3,IF(I62="A",4,6)),0))))) -> 3 | I62: =IF(OR(ISBLANK(D62),ISBLANK(E62)),IF(OR(B62="ALI",B62="AIE"),"L",IF(OR(B62="EE",B62="SE",B62="CE"),"A","")),IF(B62="EE",IF(E62>=3,IF(D62>=5,"H","A"),IF(E62>=2,IF(D62>=16,"H",IF(D62<=4,"L","A")),IF(D62<=15,"L","A"))),IF(OR(B62="SE",B62="CE"),IF(E62>=4,IF(D62>=6,"H","A"),IF(E62>=2,IF(D62>=20,"H",IF(D62<=5,"L","A")),IF(D62<=19,"L","A"))),IF(OR(B62="ALI",B62="AIE"),IF(E62>=6,IF(D62>=20,"H","A"),IF(E62>=2,IF(D62>=51,"H",IF(D62<=19,"L","A")),IF(D62<=50,"L","A"))),"")))) -> L | J62: =CONCATENATE(B62,C62) -> EEE | K62: =IF(OR(H62="",H62=0),L62,H62) -> 3 | L62: =IF(NOT(ISERROR(VLOOKUP(B62,Deflatores!G$42:H$64,2,FALSE))),VLOOKUP(B62,Deflatores!G$42:H$64,2,FALSE),IF(OR(ISBLANK(C62),ISBLANK(B62)),"",VLOOKUP(C62,Deflatores!G$4:H$38,2,FALSE)*H62+VLOOKUP(C62,Deflatores!G$4:I$38,3,FALSE))) -> 1.2 | O62: Itens excluídos da aba de Localização
A63: Listar matriculas | B63: CE | C63: E | D63: 8 | E63: 1 | F63: =IF(ISBLANK(B63),"",IF(I63="L","Baixa",IF(I63="A","Média",IF(I63="","","Alta")))) -> Baixa | G63: =CONCATENATE(B63,I63) -> CEL | H63: =IF(ISBLANK(B63),"",IF(B63="ALI",IF(I63="L",7,IF(I63="A",10,15)),IF(B63="AIE",IF(I63="L",5,IF(I63="A",7,10)),IF(B63="SE",IF(I63="L",4,IF(I63="A",5,7)),IF(OR(B63="EE",B63="CE"),IF(I63="L",3,IF(I63="A",4,6)),0))))) -> 3 | I63: =IF(OR(ISBLANK(D63),ISBLANK(E63)),IF(OR(B63="ALI",B63="AIE"),"L",IF(OR(B63="EE",B63="SE",B63="CE"),"A","")),IF(B63="EE",IF(E63>=3,IF(D63>=5,"H","A"),IF(E63>=2,IF(D63>=16,"H",IF(D63<=4,"L","A")),IF(D63<=15,"L","A"))),IF(OR(B63="SE",B63="CE"),IF(E63>=4,IF(D63>=6,"H","A"),IF(E63>=2,IF(D63>=20,"H",IF(D63<=5,"L","A")),IF(D63<=19,"L","A"))),IF(OR(B63="ALI",B63="AIE"),IF(E63>=6,IF(D63>=20,"H","A"),IF(E63>=2,IF(D63>=51,"H",IF(D63<=19,"L","A")),IF(D63<=50,"L","A"))),"")))) -> L | J63: =CONCATENATE(B63,C63) -> CEE | K63: =IF(OR(H63="",H63=0),L63,H63) -> 3 | L63: =IF(NOT(ISERROR(VLOOKUP(B63,Deflatores!G$42:H$64,2,FALSE))),VLOOKUP(B63,Deflatores!G$42:H$64,2,FALSE),IF(OR(ISBLANK(C63),ISBLANK(B63)),"",VLOOKUP(C63,Deflatores!G$4:H$38,2,FALSE)*H63+VLOOKUP(C63,Deflatores!G$4:I$38,3,FALSE))) -> 1.2 | O63: Itens excluídos da aba de Localização
A64: Excluir matriculas | B64: EE | C64: E | D64: 3 | E64: 1 | F64: =IF(ISBLANK(B64),"",IF(I64="L","Baixa",IF(I64="A","Média",IF(I64="","","Alta")))) -> Baixa | G64: =CONCATENATE(B64,I64) -> EEL | H64: =IF(ISBLANK(B64),"",IF(B64="ALI",IF(I64="L",7,IF(I64="A",10,15)),IF(B64="AIE",IF(I64="L",5,IF(I64="A",7,10)),IF(B64="SE",IF(I64="L",4,IF(I64="A",5,7)),IF(OR(B64="EE",B64="CE"),IF(I64="L",3,IF(I64="A",4,6)),0))))) -> 3 | I64: =IF(OR(ISBLANK(D64),ISBLANK(E64)),IF(OR(B64="ALI",B64="AIE"),"L",IF(OR(B64="EE",B64="SE",B64="CE"),"A","")),IF(B64="EE",IF(E64>=3,IF(D64>=5,"H","A"),IF(E64>=2,IF(D64>=16,"H",IF(D64<=4,"L","A")),IF(D64<=15,"L","A"))),IF(OR(B64="SE",B64="CE"),IF(E64>=4,IF(D64>=6,"H","A"),IF(E64>=2,IF(D64>=20,"H",IF(D64<=5,"L","A")),IF(D64<=19,"L","A"))),IF(OR(B64="ALI",B64="AIE"),IF(E64>=6,IF(D64>=20,"H","A"),IF(E64>=2,IF(D64>=51,"H",IF(D64<=19,"L","A")),IF(D64<=50,"L","A"))),"")))) -> L | J64: =CONCATENATE(B64,C64) -> EEE | K64: =IF(OR(H64="",H64=0),L64,H64) -> 3 | L64: =IF(NOT(ISERROR(VLOOKUP(B64,Deflatores!G$42:H$64,2,FALSE))),VLOOKUP(B64,Deflatores!G$42:H$64,2,FALSE),IF(OR(ISBLANK(C64),ISBLANK(B64)),"",VLOOKUP(C64,Deflatores!G$4:H$38,2,FALSE)*H64+VLOOKUP(C64,Deflatores!G$4:I$38,3,FALSE))) -> 1.2 | O64: Itens excluídos da aba de Localização
A65: ArcGIS - Endereço | B65: AIE | C65: I | D65: 5 | E65: 1 | F65: =IF(ISBLANK(B65),"",IF(I65="L","Baixa",IF(I65="A","Média",IF(I65="","","Alta")))) -> Baixa | G65: =CONCATENATE(B65,I65) -> AIEL | H65: =IF(ISBLANK(B65),"",IF(B65="ALI",IF(I65="L",7,IF(I65="A",10,15)),IF(B65="AIE",IF(I65="L",5,IF(I65="A",7,10)),IF(B65="SE",IF(I65="L",4,IF(I65="A",5,7)),IF(OR(B65="EE",B65="CE"),IF(I65="L",3,IF(I65="A",4,6)),0))))) -> 5 | I65: =IF(OR(ISBLANK(D65),ISBLANK(E65)),IF(OR(B65="ALI",B65="AIE"),"L",IF(OR(B65="EE",B65="SE",B65="CE"),"A","")),IF(B65="EE",IF(E65>=3,IF(D65>=5,"H","A"),IF(E65>=2,IF(D65>=16,"H",IF(D65<=4,"L","A")),IF(D65<=15,"L","A"))),IF(OR(B65="SE",B65="CE"),IF(E65>=4,IF(D65>=6,"H","A"),IF(E65>=2,IF(D65>=20,"H",IF(D65<=5,"L","A")),IF(D65<=19,"L","A"))),IF(OR(B65="ALI",B65="AIE"),IF(E65>=6,IF(D65>=20,"H","A"),IF(E65>=2,IF(D65>=51,"H",IF(D65<=19,"L","A")),IF(D65<=50,"L","A"))),"")))) -> L | J65: =CONCATENATE(B65,C65) -> AIEI | K65: =IF(OR(H65="",H65=0),L65,H65) -> 5 | L65: =IF(NOT(ISERROR(VLOOKUP(B65,Deflatores!G$42:H$64,2,FALSE))),VLOOKUP(B65,Deflatores!G$42:H$64,2,FALSE),IF(OR(ISBLANK(C65),ISBLANK(B65)),"",VLOOKUP(C65,Deflatores!G$4:H$38,2,FALSE)*H65+VLOOKUP(C65,Deflatores!G$4:I$38,3,FALSE))) -> 5
A66: Consultar Endereço ArcGIS - Endereço | B66: CE | C66: I | D66: 6 | E66: 1 | F66: =IF(ISBLANK(B66),"",IF(I66="L","Baixa",IF(I66="A","Média",IF(I66="","","Alta")))) -> Baixa | G66: =CONCATENATE(B66,I66) -> CEL | H66: =IF(ISBLANK(B66),"",IF(B66="ALI",IF(I66="L",7,IF(I66="A",10,15)),IF(B66="AIE",IF(I66="L",5,IF(I66="A",7,10)),IF(B66="SE",IF(I66="L",4,IF(I66="A",5,7)),IF(OR(B66="EE",B66="CE"),IF(I66="L",3,IF(I66="A",4,6)),0))))) -> 3 | I66: =IF(OR(ISBLANK(D66),ISBLANK(E66)),IF(OR(B66="ALI",B66="AIE"),"L",IF(OR(B66="EE",B66="SE",B66="CE"),"A","")),IF(B66="EE",IF(E66>=3,IF(D66>=5,"H","A"),IF(E66>=2,IF(D66>=16,"H",IF(D66<=4,"L","A")),IF(D66<=15,"L","A"))),IF(OR(B66="SE",B66="CE"),IF(E66>=4,IF(D66>=6,"H","A"),IF(E66>=2,IF(D66>=20,"H",IF(D66<=5,"L","A")),IF(D66<=19,"L","A"))),IF(OR(B66="ALI",B66="AIE"),IF(E66>=6,IF(D66>=20,"H","A"),IF(E66>=2,IF(D66>=51,"H",IF(D66<=19,"L","A")),IF(D66<=50,"L","A"))),"")))) -> L | J66: =CONCATENATE(B66,C66) -> CEI | K66: =IF(OR(H66="",H66=0),L66,H66) -> 3 | L66: =IF(NOT(ISERROR(VLOOKUP(B66,Deflatores!G$42:H$64,2,FALSE))),VLOOKUP(B66,Deflatores!G$42:H$64,2,FALSE),IF(OR(ISBLANK(C66),ISBLANK(B66)),"",VLOOKUP(C66,Deflatores!G$4:H$38,2,FALSE)*H66+VLOOKUP(C66,Deflatores!G$4:I$38,3,FALSE))) -> 3
F67: =IF(ISBLANK(B67),"",IF(I67="L","Baixa",IF(I67="A","Média",IF(I67="","","Alta")))) | G67: =CONCATENATE(B67,I67) | H67: =IF(ISBLANK(B67),"",IF(B67="ALI",IF(I67="L",7,IF(I67="A",10,15)),IF(B67="AIE",IF(I67="L",5,IF(I67="A",7,10)),IF(B67="SE",IF(I67="L",4,IF(I67="A",5,7)),IF(OR(B67="EE",B67="CE"),IF(I67="L",3,IF(I67="A",4,6)),0))))) | I67: =IF(OR(ISBLANK(D67),ISBLANK(E67)),IF(OR(B67="ALI",B67="AIE"),"L",IF(OR(B67="EE",B67="SE",B67="CE"),"A","")),IF(B67="EE",IF(E67>=3,IF(D67>=5,"H","A"),IF(E67>=2,IF(D67>=16,"H",IF(D67<=4,"L","A")),IF(D67<=15,"L","A"))),IF(OR(B67="SE",B67="CE"),IF(E67>=4,IF(D67>=6,"H","A"),IF(E67>=2,IF(D67>=20,"H",IF(D67<=5,"L","A")),IF(D67<=19,"L","A"))),IF(OR(B67="ALI",B67="AIE"),IF(E67>=6,IF(D67>=20,"H","A"),IF(E67>=2,IF(D67>=51,"H",IF(D67<=19,"L","A")),IF(D67<=50,"L","A"))),"")))) | J67: =CONCATENATE(B67,C67) | K67: =IF(OR(H67="",H67=0),L67,H67) | L67: =IF(NOT(ISERROR(VLOOKUP(B67,Deflatores!G$42:H$64,2,FALSE))),VLOOKUP(B67,Deflatores!G$42:H$64,2,FALSE),IF(OR(ISBLANK(C67),ISBLANK(B67)),"",VLOOKUP(C67,Deflatores!G$4:H$38,2,FALSE)*H67+VLOOKUP(C67,Deflatores!G$4:I$38,3,FALSE)))
A68: US 4 – Buscas - Filtros de Buscas | C68: I | F68: =IF(ISBLANK(B68),"",IF(I68="L","Baixa",IF(I68="A","Média",IF(I68="","","Alta")))) | G68: =CONCATENATE(B68,I68) | H68: =IF(ISBLANK(B68),"",IF(B68="ALI",IF(I68="L",7,IF(I68="A",10,15)),IF(B68="AIE",IF(I68="L",5,IF(I68="A",7,10)),IF(B68="SE",IF(I68="L",4,IF(I68="A",5,7)),IF(OR(B68="EE",B68="CE"),IF(I68="L",3,IF(I68="A",4,6)),0))))) | I68: =IF(OR(ISBLANK(D68),ISBLANK(E68)),IF(OR(B68="ALI",B68="AIE"),"L",IF(OR(B68="EE",B68="SE",B68="CE"),"A","")),IF(B68="EE",IF(E68>=3,IF(D68>=5,"H","A"),IF(E68>=2,IF(D68>=16,"H",IF(D68<=4,"L","A")),IF(D68<=15,"L","A"))),IF(OR(B68="SE",B68="CE"),IF(E68>=4,IF(D68>=6,"H","A"),IF(E68>=2,IF(D68>=20,"H",IF(D68<=5,"L","A")),IF(D68<=19,"L","A"))),IF(OR(B68="ALI",B68="AIE"),IF(E68>=6,IF(D68>=20,"H","A"),IF(E68>=2,IF(D68>=51,"H",IF(D68<=19,"L","A")),IF(D68<=50,"L","A"))),"")))) | J68: =CONCATENATE(B68,C68) -> I | K68: =IF(OR(H68="",H68=0),L68,H68) | L68: =IF(NOT(ISERROR(VLOOKUP(B68,Deflatores!G$42:H$64,2,FALSE))),VLOOKUP(B68,Deflatores!G$42:H$64,2,FALSE),IF(OR(ISBLANK(C68),ISBLANK(B68)),"",VLOOKUP(C68,Deflatores!G$4:H$38,2,FALSE)*H68+VLOOKUP(C68,Deflatores!G$4:I$38,3,FALSE)))
F69: =IF(ISBLANK(B69),"",IF(I69="L","Baixa",IF(I69="A","Média",IF(I69="","","Alta")))) | G69: =CONCATENATE(B69,I69) | H69: =IF(ISBLANK(B69),"",IF(B69="ALI",IF(I69="L",7,IF(I69="A",10,15)),IF(B69="AIE",IF(I69="L",5,IF(I69="A",7,10)),IF(B69="SE",IF(I69="L",4,IF(I69="A",5,7)),IF(OR(B69="EE",B69="CE"),IF(I69="L",3,IF(I69="A",4,6)),0))))) | I69: =IF(OR(ISBLANK(D69),ISBLANK(E69)),IF(OR(B69="ALI",B69="AIE"),"L",IF(OR(B69="EE",B69="SE",B69="CE"),"A","")),IF(B69="EE",IF(E69>=3,IF(D69>=5,"H","A"),IF(E69>=2,IF(D69>=16,"H",IF(D69<=4,"L","A")),IF(D69<=15,"L","A"))),IF(OR(B69="SE",B69="CE"),IF(E69>=4,IF(D69>=6,"H","A"),IF(E69>=2,IF(D69>=20,"H",IF(D69<=5,"L","A")),IF(D69<=19,"L","A"))),IF(OR(B69="ALI",B69="AIE"),IF(E69>=6,IF(D69>=20,"H","A"),IF(E69>=2,IF(D69>=51,"H",IF(D69<=19,"L","A")),IF(D69<=50,"L","A"))),"")))) | J69: =CONCATENATE(B69,C69) | K69: =IF(OR(H69="",H69=0),L69,H69) | L69: =IF(NOT(ISERROR(VLOOKUP(B69,Deflatores!G$42:H$64,2,FALSE))),VLOOKUP(B69,Deflatores!G$42:H$64,2,FALSE),IF(OR(ISBLANK(C69),ISBLANK(B69)),"",VLOOKUP(C69,Deflatores!G$4:H$38,2,FALSE)*H69+VLOOKUP(C69,Deflatores!G$4:I$38,3,FALSE)))
A70: US 5 – Buscar por Matrícula | F70: =IF(ISBLANK(B70),"",IF(I70="L","Baixa",IF(I70="A","Média",IF(I70="","","Alta")))) | G70: =CONCATENATE(B70,I70) | H70: =IF(ISBLANK(B70),"",IF(B70="ALI",IF(I70="L",7,IF(I70="A",10,15)),IF(B70="AIE",IF(I70="L",5,IF(I70="A",7,10)),IF(B70="SE",IF(I70="L",4,IF(I70="A",5,7)),IF(OR(B70="EE",B70="CE"),IF(I70="L",3,IF(I70="A",4,6)),0))))) | I70: =IF(OR(ISBLANK(D70),ISBLANK(E70)),IF(OR(B70="ALI",B70="AIE"),"L",IF(OR(B70="EE",B70="SE",B70="CE"),"A","")),IF(B70="EE",IF(E70>=3,IF(D70>=5,"H","A"),IF(E70>=2,IF(D70>=16,"H",IF(D70<=4,"L","A")),IF(D70<=15,"L","A"))),IF(OR(B70="SE",B70="CE"),IF(E70>=4,IF(D70>=6,"H","A"),IF(E70>=2,IF(D70>=20,"H",IF(D70<=5,"L","A")),IF(D70<=19,"L","A"))),IF(OR(B70="ALI",B70="AIE"),IF(E70>=6,IF(D70>=20,"H","A"),IF(E70>=2,IF(D70>=51,"H",IF(D70<=19,"L","A")),IF(D70<=50,"L","A"))),"")))) | J70: =CONCATENATE(B70,C70) | K70: =IF(OR(H70="",H70=0),L70,H70) | L70: =IF(NOT(ISERROR(VLOOKUP(B70,Deflatores!G$42:H$64,2,FALSE))),VLOOKUP(B70,Deflatores!G$42:H$64,2,FALSE),IF(OR(ISBLANK(C70),ISBLANK(B70)),"",VLOOKUP(C70,Deflatores!G$4:H$38,2,FALSE)*H70+VLOOKUP(C70,Deflatores!G$4:I$38,3,FALSE)))
A71: Buscar imóvel por matrícula | B71: CE | C71: I | D71: 5 | E71: 1 | F71: =IF(ISBLANK(B71),"",IF(I71="L","Baixa",IF(I71="A","Média",IF(I71="","","Alta")))) -> Baixa | G71: =CONCATENATE(B71,I71) -> CEL | H71: =IF(ISBLANK(B71),"",IF(B71="ALI",IF(I71="L",7,IF(I71="A",10,15)),IF(B71="AIE",IF(I71="L",5,IF(I71="A",7,10)),IF(B71="SE",IF(I71="L",4,IF(I71="A",5,7)),IF(OR(B71="EE",B71="CE"),IF(I71="L",3,IF(I71="A",4,6)),0))))) -> 3 | I71: =IF(OR(ISBLANK(D71),ISBLANK(E71)),IF(OR(B71="ALI",B71="AIE"),"L",IF(OR(B71="EE",B71="SE",B71="CE"),"A","")),IF(B71="EE",IF(E71>=3,IF(D71>=5,"H","A"),IF(E71>=2,IF(D71>=16,"H",IF(D71<=4,"L","A")),IF(D71<=15,"L","A"))),IF(OR(B71="SE",B71="CE"),IF(E71>=4,IF(D71>=6,"H","A"),IF(E71>=2,IF(D71>=20,"H",IF(D71<=5,"L","A")),IF(D71<=19,"L","A"))),IF(OR(B71="ALI",B71="AIE"),IF(E71>=6,IF(D71>=20,"H","A"),IF(E71>=2,IF(D71>=51,"H",IF(D71<=19,"L","A")),IF(D71<=50,"L","A"))),"")))) -> L | J71: =CONCATENATE(B71,C71) -> CEI | K71: =IF(OR(H71="",H71=0),L71,H71) -> 3 | L71: =IF(NOT(ISERROR(VLOOKUP(B71,Deflatores!G$42:H$64,2,FALSE))),VLOOKUP(B71,Deflatores!G$42:H$64,2,FALSE),IF(OR(ISBLANK(C71),ISBLANK(B71)),"",VLOOKUP(C71,Deflatores!G$4:H$38,2,FALSE)*H71+VLOOKUP(C71,Deflatores!G$4:I$38,3,FALSE))) -> 3
F72: =IF(ISBLANK(B72),"",IF(I72="L","Baixa",IF(I72="A","Média",IF(I72="","","Alta")))) | G72: =CONCATENATE(B72,I72) | H72: =IF(ISBLANK(B72),"",IF(B72="ALI",IF(I72="L",7,IF(I72="A",10,15)),IF(B72="AIE",IF(I72="L",5,IF(I72="A",7,10)),IF(B72="SE",IF(I72="L",4,IF(I72="A",5,7)),IF(OR(B72="EE",B72="CE"),IF(I72="L",3,IF(I72="A",4,6)),0))))) | I72: =IF(OR(ISBLANK(D72),ISBLANK(E72)),IF(OR(B72="ALI",B72="AIE"),"L",IF(OR(B72="EE",B72="SE",B72="CE"),"A","")),IF(B72="EE",IF(E72>=3,IF(D72>=5,"H","A"),IF(E72>=2,IF(D72>=16,"H",IF(D72<=4,"L","A")),IF(D72<=15,"L","A"))),IF(OR(B72="SE",B72="CE"),IF(E72>=4,IF(D72>=6,"H","A"),IF(E72>=2,IF(D72>=20,"H",IF(D72<=5,"L","A")),IF(D72<=19,"L","A"))),IF(OR(B72="ALI",B72="AIE"),IF(E72>=6,IF(D72>=20,"H","A"),IF(E72>=2,IF(D72>=51,"H",IF(D72<=19,"L","A")),IF(D72<=50,"L","A"))),"")))) | J72: =CONCATENATE(B72,C72) | K72: =IF(OR(H72="",H72=0),L72,H72) | L72: =IF(NOT(ISERROR(VLOOKUP(B72,Deflatores!G$42:H$64,2,FALSE))),VLOOKUP(B72,Deflatores!G$42:H$64,2,FALSE),IF(OR(ISBLANK(C72),ISBLANK(B72)),"",VLOOKUP(C72,Deflatores!G$4:H$38,2,FALSE)*H72+VLOOKUP(C72,Deflatores!G$4:I$38,3,FALSE)))
A73: US 6 – Vínculos - Vínculos do Imóvel | F73: =IF(ISBLANK(B73),"",IF(I73="L","Baixa",IF(I73="A","Média",IF(I73="","","Alta")))) | G73: =CONCATENATE(B73,I73) | H73: =IF(ISBLANK(B73),"",IF(B73="ALI",IF(I73="L",7,IF(I73="A",10,15)),IF(B73="AIE",IF(I73="L",5,IF(I73="A",7,10)),IF(B73="SE",IF(I73="L",4,IF(I73="A",5,7)),IF(OR(B73="EE",B73="CE"),IF(I73="L",3,IF(I73="A",4,6)),0))))) | I73: =IF(OR(ISBLANK(D73),ISBLANK(E73)),IF(OR(B73="ALI",B73="AIE"),"L",IF(OR(B73="EE",B73="SE",B73="CE"),"A","")),IF(B73="EE",IF(E73>=3,IF(D73>=5,"H","A"),IF(E73>=2,IF(D73>=16,"H",IF(D73<=4,"L","A")),IF(D73<=15,"L","A"))),IF(OR(B73="SE",B73="CE"),IF(E73>=4,IF(D73>=6,"H","A"),IF(E73>=2,IF(D73>=20,"H",IF(D73<=5,"L","A")),IF(D73<=19,"L","A"))),IF(OR(B73="ALI",B73="AIE"),IF(E73>=6,IF(D73>=20,"H","A"),IF(E73>=2,IF(D73>=51,"H",IF(D73<=19,"L","A")),IF(D73<=50,"L","A"))),"")))) | J73: =CONCATENATE(B73,C73) | K73: =IF(OR(H73="",H73=0),L73,H73) | L73: =IF(NOT(ISERROR(VLOOKUP(B73,Deflatores!G$42:H$64,2,FALSE))),VLOOKUP(B73,Deflatores!G$42:H$64,2,FALSE),IF(OR(ISBLANK(C73),ISBLANK(B73)),"",VLOOKUP(C73,Deflatores!G$4:H$38,2,FALSE)*H73+VLOOKUP(C73,Deflatores!G$4:I$38,3,FALSE)))
A74: Vínculo Imóvel | B74: ALI | C74: I | D74: 25 | E74: 2 | F74: =IF(ISBLANK(B74),"",IF(I74="L","Baixa",IF(I74="A","Média",IF(I74="","","Alta")))) -> Média | G74: =CONCATENATE(B74,I74) -> ALIA | H74: =IF(ISBLANK(B74),"",IF(B74="ALI",IF(I74="L",7,IF(I74="A",10,15)),IF(B74="AIE",IF(I74="L",5,IF(I74="A",7,10)),IF(B74="SE",IF(I74="L",4,IF(I74="A",5,7)),IF(OR(B74="EE",B74="CE"),IF(I74="L",3,IF(I74="A",4,6)),0))))) -> 10 | I74: =IF(OR(ISBLANK(D74),ISBLANK(E74)),IF(OR(B74="ALI",B74="AIE"),"L",IF(OR(B74="EE",B74="SE",B74="CE"),"A","")),IF(B74="EE",IF(E74>=3,IF(D74>=5,"H","A"),IF(E74>=2,IF(D74>=16,"H",IF(D74<=4,"L","A")),IF(D74<=15,"L","A"))),IF(OR(B74="SE",B74="CE"),IF(E74>=4,IF(D74>=6,"H","A"),IF(E74>=2,IF(D74>=20,"H",IF(D74<=5,"L","A")),IF(D74<=19,"L","A"))),IF(OR(B74="ALI",B74="AIE"),IF(E74>=6,IF(D74>=20,"H","A"),IF(E74>=2,IF(D74>=51,"H",IF(D74<=19,"L","A")),IF(D74<=50,"L","A"))),"")))) -> A | J74: =CONCATENATE(B74,C74) -> ALII | K74: =IF(OR(H74="",H74=0),L74,H74) -> 10 | L74: =IF(NOT(ISERROR(VLOOKUP(B74,Deflatores!G$42:H$64,2,FALSE))),VLOOKUP(B74,Deflatores!G$42:H$64,2,FALSE),IF(OR(ISBLANK(C74),ISBLANK(B74)),"",VLOOKUP(C74,Deflatores!G$4:H$38,2,FALSE)*H74+VLOOKUP(C74,Deflatores!G$4:I$38,3,FALSE))) -> 10
A75: Vincular Imóvel Pai | B75: EE | C75: I | D75: 28 | E75: 4 | F75: =IF(ISBLANK(B75),"",IF(I75="L","Baixa",IF(I75="A","Média",IF(I75="","","Alta")))) -> Alta | G75: =CONCATENATE(B75,I75) -> EEH | H75: =IF(ISBLANK(B75),"",IF(B75="ALI",IF(I75="L",7,IF(I75="A",10,15)),IF(B75="AIE",IF(I75="L",5,IF(I75="A",7,10)),IF(B75="SE",IF(I75="L",4,IF(I75="A",5,7)),IF(OR(B75="EE",B75="CE"),IF(I75="L",3,IF(I75="A",4,6)),0))))) -> 6 | I75: =IF(OR(ISBLANK(D75),ISBLANK(E75)),IF(OR(B75="ALI",B75="AIE"),"L",IF(OR(B75="EE",B75="SE",B75="CE"),"A","")),IF(B75="EE",IF(E75>=3,IF(D75>=5,"H","A"),IF(E75>=2,IF(D75>=16,"H",IF(D75<=4,"L","A")),IF(D75<=15,"L","A"))),IF(OR(B75="SE",B75="CE"),IF(E75>=4,IF(D75>=6,"H","A"),IF(E75>=2,IF(D75>=20,"H",IF(D75<=5,"L","A")),IF(D75<=19,"L","A"))),IF(OR(B75="ALI",B75="AIE"),IF(E75>=6,IF(D75>=20,"H","A"),IF(E75>=2,IF(D75>=51,"H",IF(D75<=19,"L","A")),IF(D75<=50,"L","A"))),"")))) -> H | J75: =CONCATENATE(B75,C75) -> EEI | K75: =IF(OR(H75="",H75=0),L75,H75) -> 6 | L75: =IF(NOT(ISERROR(VLOOKUP(B75,Deflatores!G$42:H$64,2,FALSE))),VLOOKUP(B75,Deflatores!G$42:H$64,2,FALSE),IF(OR(ISBLANK(C75),ISBLANK(B75)),"",VLOOKUP(C75,Deflatores!G$4:H$38,2,FALSE)*H75+VLOOKUP(C75,Deflatores!G$4:I$38,3,FALSE))) -> 6
A76: Desvincular Imóvel Pai | B76: EE | C76: I | D76: 11 | E76: 3 | F76: =IF(ISBLANK(B76),"",IF(I76="L","Baixa",IF(I76="A","Média",IF(I76="","","Alta")))) -> Alta | G76: =CONCATENATE(B76,I76) -> EEH | H76: =IF(ISBLANK(B76),"",IF(B76="ALI",IF(I76="L",7,IF(I76="A",10,15)),IF(B76="AIE",IF(I76="L",5,IF(I76="A",7,10)),IF(B76="SE",IF(I76="L",4,IF(I76="A",5,7)),IF(OR(B76="EE",B76="CE"),IF(I76="L",3,IF(I76="A",4,6)),0))))) -> 6 | I76: =IF(OR(ISBLANK(D76),ISBLANK(E76)),IF(OR(B76="ALI",B76="AIE"),"L",IF(OR(B76="EE",B76="SE",B76="CE"),"A","")),IF(B76="EE",IF(E76>=3,IF(D76>=5,"H","A"),IF(E76>=2,IF(D76>=16,"H",IF(D76<=4,"L","A")),IF(D76<=15,"L","A"))),IF(OR(B76="SE",B76="CE"),IF(E76>=4,IF(D76>=6,"H","A"),IF(E76>=2,IF(D76>=20,"H",IF(D76<=5,"L","A")),IF(D76<=19,"L","A"))),IF(OR(B76="ALI",B76="AIE"),IF(E76>=6,IF(D76>=20,"H","A"),IF(E76>=2,IF(D76>=51,"H",IF(D76<=19,"L","A")),IF(D76<=50,"L","A"))),"")))) -> H | J76: =CONCATENATE(B76,C76) -> EEI | K76: =IF(OR(H76="",H76=0),L76,H76) -> 6 | L76: =IF(NOT(ISERROR(VLOOKUP(B76,Deflatores!G$42:H$64,2,FALSE))),VLOOKUP(B76,Deflatores!G$42:H$64,2,FALSE),IF(OR(ISBLANK(C76),ISBLANK(B76)),"",VLOOKUP(C76,Deflatores!G$4:H$38,2,FALSE)*H76+VLOOKUP(C76,Deflatores!G$4:I$38,3,FALSE))) -> 6
A77: Listar Imóveis Filhos | B77: SE | C77: E | D77: 18 | E77: 5 | F77: =IF(ISBLANK(B77),"",IF(I77="L","Baixa",IF(I77="A","Média",IF(I77="","","Alta")))) -> Alta | G77: =CONCATENATE(B77,I77) -> SEH | H77: =IF(ISBLANK(B77),"",IF(B77="ALI",IF(I77="L",7,IF(I77="A",10,15)),IF(B77="AIE",IF(I77="L",5,IF(I77="A",7,10)),IF(B77="SE",IF(I77="L",4,IF(I77="A",5,7)),IF(OR(B77="EE",B77="CE"),IF(I77="L",3,IF(I77="A",4,6)),0))))) -> 7 | I77: =IF(OR(ISBLANK(D77),ISBLANK(E77)),IF(OR(B77="ALI",B77="AIE"),"L",IF(OR(B77="EE",B77="SE",B77="CE"),"A","")),IF(B77="EE",IF(E77>=3,IF(D77>=5,"H","A"),IF(E77>=2,IF(D77>=16,"H",IF(D77<=4,"L","A")),IF(D77<=15,"L","A"))),IF(OR(B77="SE",B77="CE"),IF(E77>=4,IF(D77>=6,"H","A"),IF(E77>=2,IF(D77>=20,"H",IF(D77<=5,"L","A")),IF(D77<=19,"L","A"))),IF(OR(B77="ALI",B77="AIE"),IF(E77>=6,IF(D77>=20,"H","A"),IF(E77>=2,IF(D77>=51,"H",IF(D77<=19,"L","A")),IF(D77<=50,"L","A"))),"")))) -> H | J77: =CONCATENATE(B77,C77) -> SEE | K77: =IF(OR(H77="",H77=0),L77,H77) -> 7 | L77: =IF(NOT(ISERROR(VLOOKUP(B77,Deflatores!G$42:H$64,2,FALSE))),VLOOKUP(B77,Deflatores!G$42:H$64,2,FALSE),IF(OR(ISBLANK(C77),ISBLANK(B77)),"",VLOOKUP(C77,Deflatores!G$4:H$38,2,FALSE)*H77+VLOOKUP(C77,Deflatores!G$4:I$38,3,FALSE))) -> 2.8
A78: Listar Imóvel Pai | B78: SE | C78: I | D78: 12 | E78: 4 | F78: =IF(ISBLANK(B78),"",IF(I78="L","Baixa",IF(I78="A","Média",IF(I78="","","Alta")))) -> Alta | G78: =CONCATENATE(B78,I78) -> SEH | H78: =IF(ISBLANK(B78),"",IF(B78="ALI",IF(I78="L",7,IF(I78="A",10,15)),IF(B78="AIE",IF(I78="L",5,IF(I78="A",7,10)),IF(B78="SE",IF(I78="L",4,IF(I78="A",5,7)),IF(OR(B78="EE",B78="CE"),IF(I78="L",3,IF(I78="A",4,6)),0))))) -> 7 | I78: =IF(OR(ISBLANK(D78),ISBLANK(E78)),IF(OR(B78="ALI",B78="AIE"),"L",IF(OR(B78="EE",B78="SE",B78="CE"),"A","")),IF(B78="EE",IF(E78>=3,IF(D78>=5,"H","A"),IF(E78>=2,IF(D78>=16,"H",IF(D78<=4,"L","A")),IF(D78<=15,"L","A"))),IF(OR(B78="SE",B78="CE"),IF(E78>=4,IF(D78>=6,"H","A"),IF(E78>=2,IF(D78>=20,"H",IF(D78<=5,"L","A")),IF(D78<=19,"L","A"))),IF(OR(B78="ALI",B78="AIE"),IF(E78>=6,IF(D78>=20,"H","A"),IF(E78>=2,IF(D78>=51,"H",IF(D78<=19,"L","A")),IF(D78<=50,"L","A"))),"")))) -> H | J78: =CONCATENATE(B78,C78) -> SEI | K78: =IF(OR(H78="",H78=0),L78,H78) -> 7 | L78: =IF(NOT(ISERROR(VLOOKUP(B78,Deflatores!G$42:H$64,2,FALSE))),VLOOKUP(B78,Deflatores!G$42:H$64,2,FALSE),IF(OR(ISBLANK(C78),ISBLANK(B78)),"",VLOOKUP(C78,Deflatores!G$4:H$38,2,FALSE)*H78+VLOOKUP(C78,Deflatores!G$4:I$38,3,FALSE))) -> 7
F79: =IF(ISBLANK(B79),"",IF(I79="L","Baixa",IF(I79="A","Média",IF(I79="","","Alta")))) | G79: =CONCATENATE(B79,I79) | H79: =IF(ISBLANK(B79),"",IF(B79="ALI",IF(I79="L",7,IF(I79="A",10,15)),IF(B79="AIE",IF(I79="L",5,IF(I79="A",7,10)),IF(B79="SE",IF(I79="L",4,IF(I79="A",5,7)),IF(OR(B79="EE",B79="CE"),IF(I79="L",3,IF(I79="A",4,6)),0))))) | I79: =IF(OR(ISBLANK(D79),ISBLANK(E79)),IF(OR(B79="ALI",B79="AIE"),"L",IF(OR(B79="EE",B79="SE",B79="CE"),"A","")),IF(B79="EE",IF(E79>=3,IF(D79>=5,"H","A"),IF(E79>=2,IF(D79>=16,"H",IF(D79<=4,"L","A")),IF(D79<=15,"L","A"))),IF(OR(B79="SE",B79="CE"),IF(E79>=4,IF(D79>=6,"H","A"),IF(E79>=2,IF(D79>=20,"H",IF(D79<=5,"L","A")),IF(D79<=19,"L","A"))),IF(OR(B79="ALI",B79="AIE"),IF(E79>=6,IF(D79>=20,"H","A"),IF(E79>=2,IF(D79>=51,"H",IF(D79<=19,"L","A")),IF(D79<=50,"L","A"))),"")))) | J79: =CONCATENATE(B79,C79) | K79: =IF(OR(H79="",H79=0),L79,H79) | L79: =IF(NOT(ISERROR(VLOOKUP(B79,Deflatores!G$42:H$64,2,FALSE))),VLOOKUP(B79,Deflatores!G$42:H$64,2,FALSE),IF(OR(ISBLANK(C79),ISBLANK(B79)),"",VLOOKUP(C79,Deflatores!G$4:H$38,2,FALSE)*H79+VLOOKUP(C79,Deflatores!G$4:I$38,3,FALSE)))
A80: US 7 – Vistorias - Vistorias do Imóvel (Edificado) | C80: I | F80: =IF(ISBLANK(B80),"",IF(I80="L","Baixa",IF(I80="A","Média",IF(I80="","","Alta")))) | G80: =CONCATENATE(B80,I80) | H80: =IF(ISBLANK(B80),"",IF(B80="ALI",IF(I80="L",7,IF(I80="A",10,15)),IF(B80="AIE",IF(I80="L",5,IF(I80="A",7,10)),IF(B80="SE",IF(I80="L",4,IF(I80="A",5,7)),IF(OR(B80="EE",B80="CE"),IF(I80="L",3,IF(I80="A",4,6)),0))))) | I80: =IF(OR(ISBLANK(D80),ISBLANK(E80)),IF(OR(B80="ALI",B80="AIE"),"L",IF(OR(B80="EE",B80="SE",B80="CE"),"A","")),IF(B80="EE",IF(E80>=3,IF(D80>=5,"H","A"),IF(E80>=2,IF(D80>=16,"H",IF(D80<=4,"L","A")),IF(D80<=15,"L","A"))),IF(OR(B80="SE",B80="CE"),IF(E80>=4,IF(D80>=6,"H","A"),IF(E80>=2,IF(D80>=20,"H",IF(D80<=5,"L","A")),IF(D80<=19,"L","A"))),IF(OR(B80="ALI",B80="AIE"),IF(E80>=6,IF(D80>=20,"H","A"),IF(E80>=2,IF(D80>=51,"H",IF(D80<=19,"L","A")),IF(D80<=50,"L","A"))),"")))) | J80: =CONCATENATE(B80,C80) -> I | K80: =IF(OR(H80="",H80=0),L80,H80) | L80: =IF(NOT(ISERROR(VLOOKUP(B80,Deflatores!G$42:H$64,2,FALSE))),VLOOKUP(B80,Deflatores!G$42:H$64,2,FALSE),IF(OR(ISBLANK(C80),ISBLANK(B80)),"",VLOOKUP(C80,Deflatores!G$4:H$38,2,FALSE)*H80+VLOOKUP(C80,Deflatores!G$4:I$38,3,FALSE)))
A81: Vistorias do Imóvel | B81: ALI | C81: I | D81: 68 | E81: 6 | F81: =IF(ISBLANK(B81),"",IF(I81="L","Baixa",IF(I81="A","Média",IF(I81="","","Alta")))) -> Alta | G81: =CONCATENATE(B81,I81) -> ALIH | H81: =IF(ISBLANK(B81),"",IF(B81="ALI",IF(I81="L",7,IF(I81="A",10,15)),IF(B81="AIE",IF(I81="L",5,IF(I81="A",7,10)),IF(B81="SE",IF(I81="L",4,IF(I81="A",5,7)),IF(OR(B81="EE",B81="CE"),IF(I81="L",3,IF(I81="A",4,6)),0))))) -> 15 | I81: =IF(OR(ISBLANK(D81),ISBLANK(E81)),IF(OR(B81="ALI",B81="AIE"),"L",IF(OR(B81="EE",B81="SE",B81="CE"),"A","")),IF(B81="EE",IF(E81>=3,IF(D81>=5,"H","A"),IF(E81>=2,IF(D81>=16,"H",IF(D81<=4,"L","A")),IF(D81<=15,"L","A"))),IF(OR(B81="SE",B81="CE"),IF(E81>=4,IF(D81>=6,"H","A"),IF(E81>=2,IF(D81>=20,"H",IF(D81<=5,"L","A")),IF(D81<=19,"L","A"))),IF(OR(B81="ALI",B81="AIE"),IF(E81>=6,IF(D81>=20,"H","A"),IF(E81>=2,IF(D81>=51,"H",IF(D81<=19,"L","A")),IF(D81<=50,"L","A"))),"")))) -> H | J81: =CONCATENATE(B81,C81) -> ALII | K81: =IF(OR(H81="",H81=0),L81,H81) -> 15 | L81: =IF(NOT(ISERROR(VLOOKUP(B81,Deflatores!G$42:H$64,2,FALSE))),VLOOKUP(B81,Deflatores!G$42:H$64,2,FALSE),IF(OR(ISBLANK(C81),ISBLANK(B81)),"",VLOOKUP(C81,Deflatores!G$4:H$38,2,FALSE)*H81+VLOOKUP(C81,Deflatores!G$4:I$38,3,FALSE))) -> 15 | O81: Incluído o campo registro profissional do avaliador e número da vistoria
A82: Cadastrar Vistoria do Imóvel Edificado | B82: EE | C82: I | D82: 17 | E82: 3 | F82: =IF(ISBLANK(B82),"",IF(I82="L","Baixa",IF(I82="A","Média",IF(I82="","","Alta")))) -> Alta | G82: =CONCATENATE(B82,I82) -> EEH | H82: =IF(ISBLANK(B82),"",IF(B82="ALI",IF(I82="L",7,IF(I82="A",10,15)),IF(B82="AIE",IF(I82="L",5,IF(I82="A",7,10)),IF(B82="SE",IF(I82="L",4,IF(I82="A",5,7)),IF(OR(B82="EE",B82="CE"),IF(I82="L",3,IF(I82="A",4,6)),0))))) -> 6 | I82: =IF(OR(ISBLANK(D82),ISBLANK(E82)),IF(OR(B82="ALI",B82="AIE"),"L",IF(OR(B82="EE",B82="SE",B82="CE"),"A","")),IF(B82="EE",IF(E82>=3,IF(D82>=5,"H","A"),IF(E82>=2,IF(D82>=16,"H",IF(D82<=4,"L","A")),IF(D82<=15,"L","A"))),IF(OR(B82="SE",B82="CE"),IF(E82>=4,IF(D82>=6,"H","A"),IF(E82>=2,IF(D82>=20,"H",IF(D82<=5,"L","A")),IF(D82<=19,"L","A"))),IF(OR(B82="ALI",B82="AIE"),IF(E82>=6,IF(D82>=20,"H","A"),IF(E82>=2,IF(D82>=51,"H",IF(D82<=19,"L","A")),IF(D82<=50,"L","A"))),"")))) -> H | J82: =CONCATENATE(B82,C82) -> EEI | K82: =IF(OR(H82="",H82=0),L82,H82) -> 6 | L82: =IF(NOT(ISERROR(VLOOKUP(B82,Deflatores!G$42:H$64,2,FALSE))),VLOOKUP(B82,Deflatores!G$42:H$64,2,FALSE),IF(OR(ISBLANK(C82),ISBLANK(B82)),"",VLOOKUP(C82,Deflatores!G$4:H$38,2,FALSE)*H82+VLOOKUP(C82,Deflatores!G$4:I$38,3,FALSE))) -> 6
A83: Combobox listar tipo de estado de conservação | B83: CE | C83: I | D83: 2 | E83: 1 | F83: =IF(ISBLANK(B83),"",IF(I83="L","Baixa",IF(I83="A","Média",IF(I83="","","Alta")))) -> Baixa | G83: =CONCATENATE(B83,I83) -> CEL | H83: =IF(ISBLANK(B83),"",IF(B83="ALI",IF(I83="L",7,IF(I83="A",10,15)),IF(B83="AIE",IF(I83="L",5,IF(I83="A",7,10)),IF(B83="SE",IF(I83="L",4,IF(I83="A",5,7)),IF(OR(B83="EE",B83="CE"),IF(I83="L",3,IF(I83="A",4,6)),0))))) -> 3 | I83: =IF(OR(ISBLANK(D83),ISBLANK(E83)),IF(OR(B83="ALI",B83="AIE"),"L",IF(OR(B83="EE",B83="SE",B83="CE"),"A","")),IF(B83="EE",IF(E83>=3,IF(D83>=5,"H","A"),IF(E83>=2,IF(D83>=16,"H",IF(D83<=4,"L","A")),IF(D83<=15,"L","A"))),IF(OR(B83="SE",B83="CE"),IF(E83>=4,IF(D83>=6,"H","A"),IF(E83>=2,IF(D83>=20,"H",IF(D83<=5,"L","A")),IF(D83<=19,"L","A"))),IF(OR(B83="ALI",B83="AIE"),IF(E83>=6,IF(D83>=20,"H","A"),IF(E83>=2,IF(D83>=51,"H",IF(D83<=19,"L","A")),IF(D83<=50,"L","A"))),"")))) -> L | J83: =CONCATENATE(B83,C83) -> CEI | K83: =IF(OR(H83="",H83=0),L83,H83) -> 3 | L83: =IF(NOT(ISERROR(VLOOKUP(B83,Deflatores!G$42:H$64,2,FALSE))),VLOOKUP(B83,Deflatores!G$42:H$64,2,FALSE),IF(OR(ISBLANK(C83),ISBLANK(B83)),"",VLOOKUP(C83,Deflatores!G$4:H$38,2,FALSE)*H83+VLOOKUP(C83,Deflatores!G$4:I$38,3,FALSE))) -> 3
A84: Editar Vistoria do Imóvel Edificado | C84: I | D84: 17 | E84: 3 | F84: =IF(ISBLANK(B84),"",IF(I84="L","Baixa",IF(I84="A","Média",IF(I84="","","Alta")))) | G84: =CONCATENATE(B84,I84) | H84: =IF(ISBLANK(B84),"",IF(B84="ALI",IF(I84="L",7,IF(I84="A",10,15)),IF(B84="AIE",IF(I84="L",5,IF(I84="A",7,10)),IF(B84="SE",IF(I84="L",4,IF(I84="A",5,7)),IF(OR(B84="EE",B84="CE"),IF(I84="L",3,IF(I84="A",4,6)),0))))) | I84: =IF(OR(ISBLANK(D84),ISBLANK(E84)),IF(OR(B84="ALI",B84="AIE"),"L",IF(OR(B84="EE",B84="SE",B84="CE"),"A","")),IF(B84="EE",IF(E84>=3,IF(D84>=5,"H","A"),IF(E84>=2,IF(D84>=16,"H",IF(D84<=4,"L","A")),IF(D84<=15,"L","A"))),IF(OR(B84="SE",B84="CE"),IF(E84>=4,IF(D84>=6,"H","A"),IF(E84>=2,IF(D84>=20,"H",IF(D84<=5,"L","A")),IF(D84<=19,"L","A"))),IF(OR(B84="ALI",B84="AIE"),IF(E84>=6,IF(D84>=20,"H","A"),IF(E84>=2,IF(D84>=51,"H",IF(D84<=19,"L","A")),IF(D84<=50,"L","A"))),"")))) | J84: =CONCATENATE(B84,C84) -> I | K84: =IF(OR(H84="",H84=0),L84,H84) | L84: =IF(NOT(ISERROR(VLOOKUP(B84,Deflatores!G$42:H$64,2,FALSE))),VLOOKUP(B84,Deflatores!G$42:H$64,2,FALSE),IF(OR(ISBLANK(C84),ISBLANK(B84)),"",VLOOKUP(C84,Deflatores!G$4:H$38,2,FALSE)*H84+VLOOKUP(C84,Deflatores!G$4:I$38,3,FALSE)))
A85: Consulta Implícia | B85: CE | C85: I | D85: 10 | E85: 2 | F85: =IF(ISBLANK(B85),"",IF(I85="L","Baixa",IF(I85="A","Média",IF(I85="","","Alta")))) -> Média | G85: =CONCATENATE(B85,I85) -> CEA | H85: =IF(ISBLANK(B85),"",IF(B85="ALI",IF(I85="L",7,IF(I85="A",10,15)),IF(B85="AIE",IF(I85="L",5,IF(I85="A",7,10)),IF(B85="SE",IF(I85="L",4,IF(I85="A",5,7)),IF(OR(B85="EE",B85="CE"),IF(I85="L",3,IF(I85="A",4,6)),0))))) -> 4 | I85: =IF(OR(ISBLANK(D85),ISBLANK(E85)),IF(OR(B85="ALI",B85="AIE"),"L",IF(OR(B85="EE",B85="SE",B85="CE"),"A","")),IF(B85="EE",IF(E85>=3,IF(D85>=5,"H","A"),IF(E85>=2,IF(D85>=16,"H",IF(D85<=4,"L","A")),IF(D85<=15,"L","A"))),IF(OR(B85="SE",B85="CE"),IF(E85>=4,IF(D85>=6,"H","A"),IF(E85>=2,IF(D85>=20,"H",IF(D85<=5,"L","A")),IF(D85<=19,"L","A"))),IF(OR(B85="ALI",B85="AIE"),IF(E85>=6,IF(D85>=20,"H","A"),IF(E85>=2,IF(D85>=51,"H",IF(D85<=19,"L","A")),IF(D85<=50,"L","A"))),"")))) -> A | J85: =CONCATENATE(B85,C85) -> CEI | K85: =IF(OR(H85="",H85=0),L85,H85) -> 4 | L85: =IF(NOT(ISERROR(VLOOKUP(B85,Deflatores!G$42:H$64,2,FALSE))),VLOOKUP(B85,Deflatores!G$42:H$64,2,FALSE),IF(OR(ISBLANK(C85),ISBLANK(B85)),"",VLOOKUP(C85,Deflatores!G$4:H$38,2,FALSE)*H85+VLOOKUP(C85,Deflatores!G$4:I$38,3,FALSE))) -> 4
A86: Incluir Documento | B86: EE | C86: I | D86: 11 | E86: 1 | F86: =IF(ISBLANK(B86),"",IF(I86="L","Baixa",IF(I86="A","Média",IF(I86="","","Alta")))) -> Baixa | G86: =CONCATENATE(B86,I86) -> EEL | H86: =IF(ISBLANK(B86),"",IF(B86="ALI",IF(I86="L",7,IF(I86="A",10,15)),IF(B86="AIE",IF(I86="L",5,IF(I86="A",7,10)),IF(B86="SE",IF(I86="L",4,IF(I86="A",5,7)),IF(OR(B86="EE",B86="CE"),IF(I86="L",3,IF(I86="A",4,6)),0))))) -> 3 | I86: =IF(OR(ISBLANK(D86),ISBLANK(E86)),IF(OR(B86="ALI",B86="AIE"),"L",IF(OR(B86="EE",B86="SE",B86="CE"),"A","")),IF(B86="EE",IF(E86>=3,IF(D86>=5,"H","A"),IF(E86>=2,IF(D86>=16,"H",IF(D86<=4,"L","A")),IF(D86<=15,"L","A"))),IF(OR(B86="SE",B86="CE"),IF(E86>=4,IF(D86>=6,"H","A"),IF(E86>=2,IF(D86>=20,"H",IF(D86<=5,"L","A")),IF(D86<=19,"L","A"))),IF(OR(B86="ALI",B86="AIE"),IF(E86>=6,IF(D86>=20,"H","A"),IF(E86>=2,IF(D86>=51,"H",IF(D86<=19,"L","A")),IF(D86<=50,"L","A"))),"")))) -> L | J86: =CONCATENATE(B86,C86) -> EEI | K86: =IF(OR(H86="",H86=0),L86,H86) -> 3 | L86: =IF(NOT(ISERROR(VLOOKUP(B86,Deflatores!G$42:H$64,2,FALSE))),VLOOKUP(B86,Deflatores!G$42:H$64,2,FALSE),IF(OR(ISBLANK(C86),ISBLANK(B86)),"",VLOOKUP(C86,Deflatores!G$4:H$38,2,FALSE)*H86+VLOOKUP(C86,Deflatores!G$4:I$38,3,FALSE))) -> 3
A87: Combobox listar tipo de documento vistoria | B87: CE | C87: I | D87: 2 | E87: 1 | F87: =IF(ISBLANK(B87),"",IF(I87="L","Baixa",IF(I87="A","Média",IF(I87="","","Alta")))) -> Baixa | G87: =CONCATENATE(B87,I87) -> CEL | H87: =IF(ISBLANK(B87),"",IF(B87="ALI",IF(I87="L",7,IF(I87="A",10,15)),IF(B87="AIE",IF(I87="L",5,IF(I87="A",7,10)),IF(B87="SE",IF(I87="L",4,IF(I87="A",5,7)),IF(OR(B87="EE",B87="CE"),IF(I87="L",3,IF(I87="A",4,6)),0))))) -> 3 | I87: =IF(OR(ISBLANK(D87),ISBLANK(E87)),IF(OR(B87="ALI",B87="AIE"),"L",IF(OR(B87="EE",B87="SE",B87="CE"),"A","")),IF(B87="EE",IF(E87>=3,IF(D87>=5,"H","A"),IF(E87>=2,IF(D87>=16,"H",IF(D87<=4,"L","A")),IF(D87<=15,"L","A"))),IF(OR(B87="SE",B87="CE"),IF(E87>=4,IF(D87>=6,"H","A"),IF(E87>=2,IF(D87>=20,"H",IF(D87<=5,"L","A")),IF(D87<=19,"L","A"))),IF(OR(B87="ALI",B87="AIE"),IF(E87>=6,IF(D87>=20,"H","A"),IF(E87>=2,IF(D87>=51,"H",IF(D87<=19,"L","A")),IF(D87<=50,"L","A"))),"")))) -> L | J87: =CONCATENATE(B87,C87) -> CEI | K87: =IF(OR(H87="",H87=0),L87,H87) -> 3 | L87: =IF(NOT(ISERROR(VLOOKUP(B87,Deflatores!G$42:H$64,2,FALSE))),VLOOKUP(B87,Deflatores!G$42:H$64,2,FALSE),IF(OR(ISBLANK(C87),ISBLANK(B87)),"",VLOOKUP(C87,Deflatores!G$4:H$38,2,FALSE)*H87+VLOOKUP(C87,Deflatores!G$4:I$38,3,FALSE))) -> 3
A88: Excluir Documento da Vistoria | B88: EE | C88: I | D88: 3 | E88: 1 | F88: =IF(ISBLANK(B88),"",IF(I88="L","Baixa",IF(I88="A","Média",IF(I88="","","Alta")))) -> Baixa | G88: =CONCATENATE(B88,I88) -> EEL | H88: =IF(ISBLANK(B88),"",IF(B88="ALI",IF(I88="L",7,IF(I88="A",10,15)),IF(B88="AIE",IF(I88="L",5,IF(I88="A",7,10)),IF(B88="SE",IF(I88="L",4,IF(I88="A",5,7)),IF(OR(B88="EE",B88="CE"),IF(I88="L",3,IF(I88="A",4,6)),0))))) -> 3 | I88: =IF(OR(ISBLANK(D88),ISBLANK(E88)),IF(OR(B88="ALI",B88="AIE"),"L",IF(OR(B88="EE",B88="SE",B88="CE"),"A","")),IF(B88="EE",IF(E88>=3,IF(D88>=5,"H","A"),IF(E88>=2,IF(D88>=16,"H",IF(D88<=4,"L","A")),IF(D88<=15,"L","A"))),IF(OR(B88="SE",B88="CE"),IF(E88>=4,IF(D88>=6,"H","A"),IF(E88>=2,IF(D88>=20,"H",IF(D88<=5,"L","A")),IF(D88<=19,"L","A"))),IF(OR(B88="ALI",B88="AIE"),IF(E88>=6,IF(D88>=20,"H","A"),IF(E88>=2,IF(D88>=51,"H",IF(D88<=19,"L","A")),IF(D88<=50,"L","A"))),"")))) -> L | J88: =CONCATENATE(B88,C88) -> EEI | K88: =IF(OR(H88="",H88=0),L88,H88) -> 3 | L88: =IF(NOT(ISERROR(VLOOKUP(B88,Deflatores!G$42:H$64,2,FALSE))),VLOOKUP(B88,Deflatores!G$42:H$64,2,FALSE),IF(OR(ISBLANK(C88),ISBLANK(B88)),"",VLOOKUP(C88,Deflatores!G$4:H$38,2,FALSE)*H88+VLOOKUP(C88,Deflatores!G$4:I$38,3,FALSE))) -> 3
A89: Listar Documentos da Vistoria | B89: CE | C89: I | D89: 6 | E89: 1 | F89: =IF(ISBLANK(B89),"",IF(I89="L","Baixa",IF(I89="A","Média",IF(I89="","","Alta")))) -> Baixa | G89: =CONCATENATE(B89,I89) -> CEL | H89: =IF(ISBLANK(B89),"",IF(B89="ALI",IF(I89="L",7,IF(I89="A",10,15)),IF(B89="AIE",IF(I89="L",5,IF(I89="A",7,10)),IF(B89="SE",IF(I89="L",4,IF(I89="A",5,7)),IF(OR(B89="EE",B89="CE"),IF(I89="L",3,IF(I89="A",4,6)),0))))) -> 3 | I89: =IF(OR(ISBLANK(D89),ISBLANK(E89)),IF(OR(B89="ALI",B89="AIE"),"L",IF(OR(B89="EE",B89="SE",B89="CE"),"A","")),IF(B89="EE",IF(E89>=3,IF(D89>=5,"H","A"),IF(E89>=2,IF(D89>=16,"H",IF(D89<=4,"L","A")),IF(D89<=15,"L","A"))),IF(OR(B89="SE",B89="CE"),IF(E89>=4,IF(D89>=6,"H","A"),IF(E89>=2,IF(D89>=20,"H",IF(D89<=5,"L","A")),IF(D89<=19,"L","A"))),IF(OR(B89="ALI",B89="AIE"),IF(E89>=6,IF(D89>=20,"H","A"),IF(E89>=2,IF(D89>=51,"H",IF(D89<=19,"L","A")),IF(D89<=50,"L","A"))),"")))) -> L | J89: =CONCATENATE(B89,C89) -> CEI | K89: =IF(OR(H89="",H89=0),L89,H89) -> 3 | L89: =IF(NOT(ISERROR(VLOOKUP(B89,Deflatores!G$42:H$64,2,FALSE))),VLOOKUP(B89,Deflatores!G$42:H$64,2,FALSE),IF(OR(ISBLANK(C89),ISBLANK(B89)),"",VLOOKUP(C89,Deflatores!G$4:H$38,2,FALSE)*H89+VLOOKUP(C89,Deflatores!G$4:I$38,3,FALSE))) -> 3
A90: Finalizar Vistoria Imóvel Edificado | B90: SE | C90: I | D90: 47 | E90: 3 | F90: =IF(ISBLANK(B90),"",IF(I90="L","Baixa",IF(I90="A","Média",IF(I90="","","Alta")))) -> Alta | G90: =CONCATENATE(B90,I90) -> SEH | H90: =IF(ISBLANK(B90),"",IF(B90="ALI",IF(I90="L",7,IF(I90="A",10,15)),IF(B90="AIE",IF(I90="L",5,IF(I90="A",7,10)),IF(B90="SE",IF(I90="L",4,IF(I90="A",5,7)),IF(OR(B90="EE",B90="CE"),IF(I90="L",3,IF(I90="A",4,6)),0))))) -> 7 | I90: =IF(OR(ISBLANK(D90),ISBLANK(E90)),IF(OR(B90="ALI",B90="AIE"),"L",IF(OR(B90="EE",B90="SE",B90="CE"),"A","")),IF(B90="EE",IF(E90>=3,IF(D90>=5,"H","A"),IF(E90>=2,IF(D90>=16,"H",IF(D90<=4,"L","A")),IF(D90<=15,"L","A"))),IF(OR(B90="SE",B90="CE"),IF(E90>=4,IF(D90>=6,"H","A"),IF(E90>=2,IF(D90>=20,"H",IF(D90<=5,"L","A")),IF(D90<=19,"L","A"))),IF(OR(B90="ALI",B90="AIE"),IF(E90>=6,IF(D90>=20,"H","A"),IF(E90>=2,IF(D90>=51,"H",IF(D90<=19,"L","A")),IF(D90<=50,"L","A"))),"")))) -> H | J90: =CONCATENATE(B90,C90) -> SEI | K90: =IF(OR(H90="",H90=0),L90,H90) -> 7 | L90: =IF(NOT(ISERROR(VLOOKUP(B90,Deflatores!G$42:H$64,2,FALSE))),VLOOKUP(B90,Deflatores!G$42:H$64,2,FALSE),IF(OR(ISBLANK(C90),ISBLANK(B90)),"",VLOOKUP(C90,Deflatores!G$4:H$38,2,FALSE)*H90+VLOOKUP(C90,Deflatores!G$4:I$38,3,FALSE))) -> 7
A91: Visualizar Vistoria | B91: CE | C91: I | D91: 23 | E91: 4 | F91: =IF(ISBLANK(B91),"",IF(I91="L","Baixa",IF(I91="A","Média",IF(I91="","","Alta")))) -> Alta | G91: =CONCATENATE(B91,I91) -> CEH | H91: =IF(ISBLANK(B91),"",IF(B91="ALI",IF(I91="L",7,IF(I91="A",10,15)),IF(B91="AIE",IF(I91="L",5,IF(I91="A",7,10)),IF(B91="SE",IF(I91="L",4,IF(I91="A",5,7)),IF(OR(B91="EE",B91="CE"),IF(I91="L",3,IF(I91="A",4,6)),0))))) -> 6 | I91: =IF(OR(ISBLANK(D91),ISBLANK(E91)),IF(OR(B91="ALI",B91="AIE"),"L",IF(OR(B91="EE",B91="SE",B91="CE"),"A","")),IF(B91="EE",IF(E91>=3,IF(D91>=5,"H","A"),IF(E91>=2,IF(D91>=16,"H",IF(D91<=4,"L","A")),IF(D91<=15,"L","A"))),IF(OR(B91="SE",B91="CE"),IF(E91>=4,IF(D91>=6,"H","A"),IF(E91>=2,IF(D91>=20,"H",IF(D91<=5,"L","A")),IF(D91<=19,"L","A"))),IF(OR(B91="ALI",B91="AIE"),IF(E91>=6,IF(D91>=20,"H","A"),IF(E91>=2,IF(D91>=51,"H",IF(D91<=19,"L","A")),IF(D91<=50,"L","A"))),"")))) -> H | J91: =CONCATENATE(B91,C91) -> CEI | K91: =IF(OR(H91="",H91=0),L91,H91) -> 6 | L91: =IF(NOT(ISERROR(VLOOKUP(B91,Deflatores!G$42:H$64,2,FALSE))),VLOOKUP(B91,Deflatores!G$42:H$64,2,FALSE),IF(OR(ISBLANK(C91),ISBLANK(B91)),"",VLOOKUP(C91,Deflatores!G$4:H$38,2,FALSE)*H91+VLOOKUP(C91,Deflatores!G$4:I$38,3,FALSE))) -> 6
A92: Visualizar Avaliação | B92: CE | C92: I | D92: 27 | E92: 4 | F92: =IF(ISBLANK(B92),"",IF(I92="L","Baixa",IF(I92="A","Média",IF(I92="","","Alta")))) -> Alta | G92: =CONCATENATE(B92,I92) -> CEH | H92: =IF(ISBLANK(B92),"",IF(B92="ALI",IF(I92="L",7,IF(I92="A",10,15)),IF(B92="AIE",IF(I92="L",5,IF(I92="A",7,10)),IF(B92="SE",IF(I92="L",4,IF(I92="A",5,7)),IF(OR(B92="EE",B92="CE"),IF(I92="L",3,IF(I92="A",4,6)),0))))) -> 6 | I92: =IF(OR(ISBLANK(D92),ISBLANK(E92)),IF(OR(B92="ALI",B92="AIE"),"L",IF(OR(B92="EE",B92="SE",B92="CE"),"A","")),IF(B92="EE",IF(E92>=3,IF(D92>=5,"H","A"),IF(E92>=2,IF(D92>=16,"H",IF(D92<=4,"L","A")),IF(D92<=15,"L","A"))),IF(OR(B92="SE",B92="CE"),IF(E92>=4,IF(D92>=6,"H","A"),IF(E92>=2,IF(D92>=20,"H",IF(D92<=5,"L","A")),IF(D92<=19,"L","A"))),IF(OR(B92="ALI",B92="AIE"),IF(E92>=6,IF(D92>=20,"H","A"),IF(E92>=2,IF(D92>=51,"H",IF(D92<=19,"L","A")),IF(D92<=50,"L","A"))),"")))) -> H | J92: =CONCATENATE(B92,C92) -> CEI | K92: =IF(OR(H92="",H92=0),L92,H92) -> 6 | L92: =IF(NOT(ISERROR(VLOOKUP(B92,Deflatores!G$42:H$64,2,FALSE))),VLOOKUP(B92,Deflatores!G$42:H$64,2,FALSE),IF(OR(ISBLANK(C92),ISBLANK(B92)),"",VLOOKUP(C92,Deflatores!G$4:H$38,2,FALSE)*H92+VLOOKUP(C92,Deflatores!G$4:I$38,3,FALSE))) -> 6
A93: Excluir Vistoria do Imóvel | B93: EE | C93: I | D93: 2 | E93: 1 | F93: =IF(ISBLANK(B93),"",IF(I93="L","Baixa",IF(I93="A","Média",IF(I93="","","Alta")))) -> Baixa | G93: =CONCATENATE(B93,I93) -> EEL | H93: =IF(ISBLANK(B93),"",IF(B93="ALI",IF(I93="L",7,IF(I93="A",10,15)),IF(B93="AIE",IF(I93="L",5,IF(I93="A",7,10)),IF(B93="SE",IF(I93="L",4,IF(I93="A",5,7)),IF(OR(B93="EE",B93="CE"),IF(I93="L",3,IF(I93="A",4,6)),0))))) -> 3 | I93: =IF(OR(ISBLANK(D93),ISBLANK(E93)),IF(OR(B93="ALI",B93="AIE"),"L",IF(OR(B93="EE",B93="SE",B93="CE"),"A","")),IF(B93="EE",IF(E93>=3,IF(D93>=5,"H","A"),IF(E93>=2,IF(D93>=16,"H",IF(D93<=4,"L","A")),IF(D93<=15,"L","A"))),IF(OR(B93="SE",B93="CE"),IF(E93>=4,IF(D93>=6,"H","A"),IF(E93>=2,IF(D93>=20,"H",IF(D93<=5,"L","A")),IF(D93<=19,"L","A"))),IF(OR(B93="ALI",B93="AIE"),IF(E93>=6,IF(D93>=20,"H","A"),IF(E93>=2,IF(D93>=51,"H",IF(D93<=19,"L","A")),IF(D93<=50,"L","A"))),"")))) -> L | J93: =CONCATENATE(B93,C93) -> EEI | K93: =IF(OR(H93="",H93=0),L93,H93) -> 3 | L93: =IF(NOT(ISERROR(VLOOKUP(B93,Deflatores!G$42:H$64,2,FALSE))),VLOOKUP(B93,Deflatores!G$42:H$64,2,FALSE),IF(OR(ISBLANK(C93),ISBLANK(B93)),"",VLOOKUP(C93,Deflatores!G$4:H$38,2,FALSE)*H93+VLOOKUP(C93,Deflatores!G$4:I$38,3,FALSE))) -> 3
F94: =IF(ISBLANK(B94),"",IF(I94="L","Baixa",IF(I94="A","Média",IF(I94="","","Alta")))) | G94: =CONCATENATE(B94,I94) | H94: =IF(ISBLANK(B94),"",IF(B94="ALI",IF(I94="L",7,IF(I94="A",10,15)),IF(B94="AIE",IF(I94="L",5,IF(I94="A",7,10)),IF(B94="SE",IF(I94="L",4,IF(I94="A",5,7)),IF(OR(B94="EE",B94="CE"),IF(I94="L",3,IF(I94="A",4,6)),0))))) | I94: =IF(OR(ISBLANK(D94),ISBLANK(E94)),IF(OR(B94="ALI",B94="AIE"),"L",IF(OR(B94="EE",B94="SE",B94="CE"),"A","")),IF(B94="EE",IF(E94>=3,IF(D94>=5,"H","A"),IF(E94>=2,IF(D94>=16,"H",IF(D94<=4,"L","A")),IF(D94<=15,"L","A"))),IF(OR(B94="SE",B94="CE"),IF(E94>=4,IF(D94>=6,"H","A"),IF(E94>=2,IF(D94>=20,"H",IF(D94<=5,"L","A")),IF(D94<=19,"L","A"))),IF(OR(B94="ALI",B94="AIE"),IF(E94>=6,IF(D94>=20,"H","A"),IF(E94>=2,IF(D94>=51,"H",IF(D94<=19,"L","A")),IF(D94<=50,"L","A"))),"")))) | J94: =CONCATENATE(B94,C94) | K94: =IF(OR(H94="",H94=0),L94,H94) | L94: =IF(NOT(ISERROR(VLOOKUP(B94,Deflatores!G$42:H$64,2,FALSE))),VLOOKUP(B94,Deflatores!G$42:H$64,2,FALSE),IF(OR(ISBLANK(C94),ISBLANK(B94)),"",VLOOKUP(C94,Deflatores!G$4:H$38,2,FALSE)*H94+VLOOKUP(C94,Deflatores!G$4:I$38,3,FALSE)))
A95: US 09 – Registro do Imóvel | C95: I | F95: =IF(ISBLANK(B95),"",IF(I95="L","Baixa",IF(I95="A","Média",IF(I95="","","Alta")))) | G95: =CONCATENATE(B95,I95) | H95: =IF(ISBLANK(B95),"",IF(B95="ALI",IF(I95="L",7,IF(I95="A",10,15)),IF(B95="AIE",IF(I95="L",5,IF(I95="A",7,10)),IF(B95="SE",IF(I95="L",4,IF(I95="A",5,7)),IF(OR(B95="EE",B95="CE"),IF(I95="L",3,IF(I95="A",4,6)),0))))) | I95: =IF(OR(ISBLANK(D95),ISBLANK(E95)),IF(OR(B95="ALI",B95="AIE"),"L",IF(OR(B95="EE",B95="SE",B95="CE"),"A","")),IF(B95="EE",IF(E95>=3,IF(D95>=5,"H","A"),IF(E95>=2,IF(D95>=16,"H",IF(D95<=4,"L","A")),IF(D95<=15,"L","A"))),IF(OR(B95="SE",B95="CE"),IF(E95>=4,IF(D95>=6,"H","A"),IF(E95>=2,IF(D95>=20,"H",IF(D95<=5,"L","A")),IF(D95<=19,"L","A"))),IF(OR(B95="ALI",B95="AIE"),IF(E95>=6,IF(D95>=20,"H","A"),IF(E95>=2,IF(D95>=51,"H",IF(D95<=19,"L","A")),IF(D95<=50,"L","A"))),"")))) | J95: =CONCATENATE(B95,C95) -> I | K95: =IF(OR(H95="",H95=0),L95,H95) | L95: =IF(NOT(ISERROR(VLOOKUP(B95,Deflatores!G$42:H$64,2,FALSE))),VLOOKUP(B95,Deflatores!G$42:H$64,2,FALSE),IF(OR(ISBLANK(C95),ISBLANK(B95)),"",VLOOKUP(C95,Deflatores!G$4:H$38,2,FALSE)*H95+VLOOKUP(C95,Deflatores!G$4:I$38,3,FALSE)))
A96: Cadastrar Registro do Imóvel | B96: EE | C96: I | D96: 11 | E96: 1 | F96: =IF(ISBLANK(B96),"",IF(I96="L","Baixa",IF(I96="A","Média",IF(I96="","","Alta")))) -> Baixa | G96: =CONCATENATE(B96,I96) -> EEL | H96: =IF(ISBLANK(B96),"",IF(B96="ALI",IF(I96="L",7,IF(I96="A",10,15)),IF(B96="AIE",IF(I96="L",5,IF(I96="A",7,10)),IF(B96="SE",IF(I96="L",4,IF(I96="A",5,7)),IF(OR(B96="EE",B96="CE"),IF(I96="L",3,IF(I96="A",4,6)),0))))) -> 3 | I96: =IF(OR(ISBLANK(D96),ISBLANK(E96)),IF(OR(B96="ALI",B96="AIE"),"L",IF(OR(B96="EE",B96="SE",B96="CE"),"A","")),IF(B96="EE",IF(E96>=3,IF(D96>=5,"H","A"),IF(E96>=2,IF(D96>=16,"H",IF(D96<=4,"L","A")),IF(D96<=15,"L","A"))),IF(OR(B96="SE",B96="CE"),IF(E96>=4,IF(D96>=6,"H","A"),IF(E96>=2,IF(D96>=20,"H",IF(D96<=5,"L","A")),IF(D96<=19,"L","A"))),IF(OR(B96="ALI",B96="AIE"),IF(E96>=6,IF(D96>=20,"H","A"),IF(E96>=2,IF(D96>=51,"H",IF(D96<=19,"L","A")),IF(D96<=50,"L","A"))),"")))) -> L | J96: =CONCATENATE(B96,C96) -> EEI | K96: =IF(OR(H96="",H96=0),L96,H96) -> 3 | L96: =IF(NOT(ISERROR(VLOOKUP(B96,Deflatores!G$42:H$64,2,FALSE))),VLOOKUP(B96,Deflatores!G$42:H$64,2,FALSE),IF(OR(ISBLANK(C96),ISBLANK(B96)),"",VLOOKUP(C96,Deflatores!G$4:H$38,2,FALSE)*H96+VLOOKUP(C96,Deflatores!G$4:I$38,3,FALSE))) -> 3
A97: Editar Registro do Imóvel | B97: EE | C97: I | D97: 11 | E97: 1 | F97: =IF(ISBLANK(B97),"",IF(I97="L","Baixa",IF(I97="A","Média",IF(I97="","","Alta")))) -> Baixa | G97: =CONCATENATE(B97,I97) -> EEL | H97: =IF(ISBLANK(B97),"",IF(B97="ALI",IF(I97="L",7,IF(I97="A",10,15)),IF(B97="AIE",IF(I97="L",5,IF(I97="A",7,10)),IF(B97="SE",IF(I97="L",4,IF(I97="A",5,7)),IF(OR(B97="EE",B97="CE"),IF(I97="L",3,IF(I97="A",4,6)),0))))) -> 3 | I97: =IF(OR(ISBLANK(D97),ISBLANK(E97)),IF(OR(B97="ALI",B97="AIE"),"L",IF(OR(B97="EE",B97="SE",B97="CE"),"A","")),IF(B97="EE",IF(E97>=3,IF(D97>=5,"H","A"),IF(E97>=2,IF(D97>=16,"H",IF(D97<=4,"L","A")),IF(D97<=15,"L","A"))),IF(OR(B97="SE",B97="CE"),IF(E97>=4,IF(D97>=6,"H","A"),IF(E97>=2,IF(D97>=20,"H",IF(D97<=5,"L","A")),IF(D97<=19,"L","A"))),IF(OR(B97="ALI",B97="AIE"),IF(E97>=6,IF(D97>=20,"H","A"),IF(E97>=2,IF(D97>=51,"H",IF(D97<=19,"L","A")),IF(D97<=50,"L","A"))),"")))) -> L | J97: =CONCATENATE(B97,C97) -> EEI | K97: =IF(OR(H97="",H97=0),L97,H97) -> 3 | L97: =IF(NOT(ISERROR(VLOOKUP(B97,Deflatores!G$42:H$64,2,FALSE))),VLOOKUP(B97,Deflatores!G$42:H$64,2,FALSE),IF(OR(ISBLANK(C97),ISBLANK(B97)),"",VLOOKUP(C97,Deflatores!G$4:H$38,2,FALSE)*H97+VLOOKUP(C97,Deflatores!G$4:I$38,3,FALSE))) -> 3
A98: Consulta Implícita | B98: CE | C98: I | D98: 9 | E98: 1 | F98: =IF(ISBLANK(B98),"",IF(I98="L","Baixa",IF(I98="A","Média",IF(I98="","","Alta")))) -> Baixa | G98: =CONCATENATE(B98,I98) -> CEL | H98: =IF(ISBLANK(B98),"",IF(B98="ALI",IF(I98="L",7,IF(I98="A",10,15)),IF(B98="AIE",IF(I98="L",5,IF(I98="A",7,10)),IF(B98="SE",IF(I98="L",4,IF(I98="A",5,7)),IF(OR(B98="EE",B98="CE"),IF(I98="L",3,IF(I98="A",4,6)),0))))) -> 3 | I98: =IF(OR(ISBLANK(D98),ISBLANK(E98)),IF(OR(B98="ALI",B98="AIE"),"L",IF(OR(B98="EE",B98="SE",B98="CE"),"A","")),IF(B98="EE",IF(E98>=3,IF(D98>=5,"H","A"),IF(E98>=2,IF(D98>=16,"H",IF(D98<=4,"L","A")),IF(D98<=15,"L","A"))),IF(OR(B98="SE",B98="CE"),IF(E98>=4,IF(D98>=6,"H","A"),IF(E98>=2,IF(D98>=20,"H",IF(D98<=5,"L","A")),IF(D98<=19,"L","A"))),IF(OR(B98="ALI",B98="AIE"),IF(E98>=6,IF(D98>=20,"H","A"),IF(E98>=2,IF(D98>=51,"H",IF(D98<=19,"L","A")),IF(D98<=50,"L","A"))),"")))) -> L | J98: =CONCATENATE(B98,C98) -> CEI | K98: =IF(OR(H98="",H98=0),L98,H98) -> 3 | L98: =IF(NOT(ISERROR(VLOOKUP(B98,Deflatores!G$42:H$64,2,FALSE))),VLOOKUP(B98,Deflatores!G$42:H$64,2,FALSE),IF(OR(ISBLANK(C98),ISBLANK(B98)),"",VLOOKUP(C98,Deflatores!G$4:H$38,2,FALSE)*H98+VLOOKUP(C98,Deflatores!G$4:I$38,3,FALSE))) -> 3
A99: Modal compor matrícula | B99: EE | C99: I | D99: 19 | E99: 3 | F99: Baixa | G99: 3 | H99: 3 | I99: 3 | K99: =IF(OR(H99="",H99=0),L99,H99) -> 3 | L99: =IF(NOT(ISERROR(VLOOKUP(B99,Deflatores!G$42:H$64,2,FALSE))),VLOOKUP(B99,Deflatores!G$42:H$64,2,FALSE),IF(OR(ISBLANK(C99),ISBLANK(B99)),"",VLOOKUP(C99,Deflatores!G$4:H$38,2,FALSE)*H99+VLOOKUP(C99,Deflatores!G$4:I$38,3,FALSE))) -> 3
A100: Listar Cartório | B100: CE | C100: I | D100: 7 | E100: 2 | F100: =IF(ISBLANK(B100),"",IF(I100="L","Baixa",IF(I100="A","Média",IF(I100="","","Alta")))) -> Média | G100: =CONCATENATE(B100,I100) -> CEA | H100: =IF(ISBLANK(B100),"",IF(B100="ALI",IF(I100="L",7,IF(I100="A",10,15)),IF(B100="AIE",IF(I100="L",5,IF(I100="A",7,10)),IF(B100="SE",IF(I100="L",4,IF(I100="A",5,7)),IF(OR(B100="EE",B100="CE"),IF(I100="L",3,IF(I100="A",4,6)),0))))) -> 4 | I100: =IF(OR(ISBLANK(D100),ISBLANK(E100)),IF(OR(B100="ALI",B100="AIE"),"L",IF(OR(B100="EE",B100="SE",B100="CE"),"A","")),IF(B100="EE",IF(E100>=3,IF(D100>=5,"H","A"),IF(E100>=2,IF(D100>=16,"H",IF(D100<=4,"L","A")),IF(D100<=15,"L","A"))),IF(OR(B100="SE",B100="CE"),IF(E100>=4,IF(D100>=6,"H","A"),IF(E100>=2,IF(D100>=20,"H",IF(D100<=5,"L","A")),IF(D100<=19,"L","A"))),IF(OR(B100="ALI",B100="AIE"),IF(E100>=6,IF(D100>=20,"H","A"),IF(E100>=2,IF(D100>=51,"H",IF(D100<=19,"L","A")),IF(D100<=50,"L","A"))),"")))) -> A | J100: =CONCATENATE(B100,C100) -> CEI | K100: =IF(OR(H100="",H100=0),L100,H100) -> 4 | L100: =IF(NOT(ISERROR(VLOOKUP(B100,Deflatores!G$42:H$64,2,FALSE))),VLOOKUP(B100,Deflatores!G$42:H$64,2,FALSE),IF(OR(ISBLANK(C100),ISBLANK(B100)),"",VLOOKUP(C100,Deflatores!G$4:H$38,2,FALSE)*H100+VLOOKUP(C100,Deflatores!G$4:I$38,3,FALSE))) -> 4
A101: Listar matriculas | B101: CE | C101: I | D101: 16 | E101: 3 | F101: Baixa | G101: 3 | H101: 3 | I101: 3 | K101: =IF(OR(H101="",H101=0),L101,H101) -> 3 | L101: =IF(NOT(ISERROR(VLOOKUP(B101,Deflatores!G$42:H$64,2,FALSE))),VLOOKUP(B101,Deflatores!G$42:H$64,2,FALSE),IF(OR(ISBLANK(C101),ISBLANK(B101)),"",VLOOKUP(C101,Deflatores!G$4:H$38,2,FALSE)*H101+VLOOKUP(C101,Deflatores!G$4:I$38,3,FALSE))) -> 3
A102: Excluir matriculas | B102: EE | C102: I | D102: 5 | E102: 1 | F102: Baixa | G102: 3 | H102: 3 | I102: 3 | K102: =IF(OR(H102="",H102=0),L102,H102) -> 3 | L102: =IF(NOT(ISERROR(VLOOKUP(B102,Deflatores!G$42:H$64,2,FALSE))),VLOOKUP(B102,Deflatores!G$42:H$64,2,FALSE),IF(OR(ISBLANK(C102),ISBLANK(B102)),"",VLOOKUP(C102,Deflatores!G$4:H$38,2,FALSE)*H102+VLOOKUP(C102,Deflatores!G$4:I$38,3,FALSE))) -> 3
A103: Download arquivo | B103: CE | C103: I | D103: 4 | E103: 1 | F103: Baixa | G103: 3 | H103: 3 | I103: 3 | K103: =IF(OR(H103="",H103=0),L103,H103) -> 3 | L103: =IF(NOT(ISERROR(VLOOKUP(B103,Deflatores!G$42:H$64,2,FALSE))),VLOOKUP(B103,Deflatores!G$42:H$64,2,FALSE),IF(OR(ISBLANK(C103),ISBLANK(B103)),"",VLOOKUP(C103,Deflatores!G$4:H$38,2,FALSE)*H103+VLOOKUP(C103,Deflatores!G$4:I$38,3,FALSE))) -> 3
A104: Visualizar matrícula | B104: CE | C104: I | D104: 19 | E104: 3 | F104: =IF(ISBLANK(B104),"",IF(I104="L","Baixa",IF(I104="A","Média",IF(I104="","","Alta")))) -> Média | G104: =CONCATENATE(B104,I104) -> CEA | H104: =IF(ISBLANK(B104),"",IF(B104="ALI",IF(I104="L",7,IF(I104="A",10,15)),IF(B104="AIE",IF(I104="L",5,IF(I104="A",7,10)),IF(B104="SE",IF(I104="L",4,IF(I104="A",5,7)),IF(OR(B104="EE",B104="CE"),IF(I104="L",3,IF(I104="A",4,6)),0))))) -> 4 | I104: =IF(OR(ISBLANK(D104),ISBLANK(E104)),IF(OR(B104="ALI",B104="AIE"),"L",IF(OR(B104="EE",B104="SE",B104="CE"),"A","")),IF(B104="EE",IF(E104>=3,IF(D104>=5,"H","A"),IF(E104>=2,IF(D104>=16,"H",IF(D104<=4,"L","A")),IF(D104<=15,"L","A"))),IF(OR(B104="SE",B104="CE"),IF(E104>=4,IF(D104>=6,"H","A"),IF(E104>=2,IF(D104>=20,"H",IF(D104<=5,"L","A")),IF(D104<=19,"L","A"))),IF(OR(B104="ALI",B104="AIE"),IF(E104>=6,IF(D104>=20,"H","A"),IF(E104>=2,IF(D104>=51,"H",IF(D104<=19,"L","A")),IF(D104<=50,"L","A"))),"")))) -> A | J104: =CONCATENATE(B104,C104) -> CEI | K104: =IF(OR(H104="",H104=0),L104,H104) -> 4 | L104: =IF(NOT(ISERROR(VLOOKUP(B104,Deflatores!G$42:H$64,2,FALSE))),VLOOKUP(B104,Deflatores!G$42:H$64,2,FALSE),IF(OR(ISBLANK(C104),ISBLANK(B104)),"",VLOOKUP(C104,Deflatores!G$4:H$38,2,FALSE)*H104+VLOOKUP(C104,Deflatores!G$4:I$38,3,FALSE))) -> 4
...

Sheet Deflatores
A1: Itens Não Mensuráveis
A2: Tipo de Manutenção na Função | G2: Sigla | H2: Contribuição em PF Local | J2: PF IFPUG | K2: PF Local FS
A3: Contrato | B3: Descrição | F3: Origem | H3: Percentual (%) | I3: Fixa (PF)
A4: Adicionada | B4: Inclusão | G4: I | H4: 1 | J4: =SUMIF(Funções!$C$86:$C$188,Deflatores!G4,Funções!$H$86:$H$188) -> 340 | K4: =IF(H4="",COUNTIF(Funções!C$86:C$188,G4)*I4,H4*J4) -> 340
A5: Alterada | B5: Alteração (sem conhecimento do Fator de Impacto) | F5: SISP – 4.2 Projeto de Melhoria | G5: A | H5: 0.5 | J5: =SUMIF(Funções!$C$86:$C$188,Deflatores!G5,Funções!$H$86:$H$188) -> 0 | K5: =IF(H5="",COUNTIF(Funções!C$86:C$188,G5)*I5,H5*J5) -> 0
A6: Excluída | B6: Exclusão | F6: SISP – 4.2 Projeto de Melhoria | G6: E | H6: 0.4 | J6: =SUMIF(Funções!$C$86:$C$188,Deflatores!G6,Funções!$H$86:$H$188) -> 6 | K6: =IF(H6="",COUNTIF(Funções!C$86:C$188,G6)*I6,H6*J6) -> 2.4
B7: Alteração (50%) de função desenvolvida ou já alterada pela empresa atual | F7: SISP – 4.2 Projeto de Melhoria | G7: A50 | H7: 0.5 | J7: =SUMIF(Funções!$C$86:$C$188,Deflatores!G7,Funções!$H$86:$H$188) -> 0 | K7: =IF(H7="",COUNTIF(Funções!C$86:C$188,G7)*I7,H7*J7) -> 0
B8: Alteração (75%) de função não desenv. e ainda não alterada pela empresa atual | F8: SISP – 4.2 Projeto de Melhoria | G8: A75 | H8: 0.75 | J8: =SUMIF(Funções!$C$86:$C$188,Deflatores!G8,Funções!$H$86:$H$188) -> 0 | K8: =IF(H8="",COUNTIF(Funções!C$86:C$188,G8)*I8,H8*J8) -> 0
B9: Alteração (75%+15%): o mesmo acima + redocumentar a função | F9: SISP – 4.2 Projeto de Melhoria | G9: A90 | H9: 0.9 | J9: =SUMIF(Funções!$C$86:$C$188,Deflatores!G9,Funções!$H$86:$H$188) -> 0 | K9: =IF(H9="",COUNTIF(Funções!C$86:C$188,G9)*I9,H9*J9) -> 0
B10: Migração de Dados | F10: SISP – 4.3 Projetos de Migração de Dados | G10: PMD | H10: 1 | J10: =SUMIF(Funções!$C$86:$C$188,Deflatores!G10,Funções!$H$86:$H$188) -> 0 | K10: =IF(H10="",COUNTIF(Funções!C$86:C$188,G10)*I10,H10*J10) -> 0
B11: Corretiva (sem conhecimento do Fator de Impacto) | F11: SISP – 4.4 Manutenção Corretiva | G11: COR | H11: 0.5 | J11: =SUMIF(Funções!$C$86:$C$188,Deflatores!G11,Funções!$H$86:$H$188) -> 0 | K11: =IF(H11="",COUNTIF(Funções!C$86:C$188,G11)*I11,H11*J11) -> 0
B12: Corretiva (50%) - Fora da garantia (mesma empresa) | F12: SISP – 4.4 Manutenção Corretiva | G12: COR50 | H12: 0.5 | J12: =SUMIF(Funções!$C$86:$C$188,Deflatores!G12,Funções!$H$86:$H$188) -> 0 | K12: =IF(H12="",COUNTIF(Funções!C$86:C$188,G12)*I12,H12*J12) -> 0
B13: Corretiva (75%) - Fora da garantia (outra empresa) | F13: SISP – 4.4 Manutenção Corretiva | G13: COR75 | H13: 0.75 | J13: =SUMIF(Funções!$C$86:$C$188,Deflatores!G13,Funções!$H$86:$H$188) -> 0 | K13: =IF(H13="",COUNTIF(Funções!C$86:C$188,G13)*I13,H13*J13) -> 0
B14: Corretiva (75%+15%) - Fora da garantia (outra empresa) + Redocumentação | F14: SISP – 4.4 Manutenção Corretiva | G14: COR90 | H14: 0.9 | J14: =SUMIF(Funções!$C$86:$C$188,Deflatores!G14,Funções!$H$86:$H$188) -> 0 | K14: =IF(H14="",COUNTIF(Funções!C$86:C$188,G14)*I14,H14*J14) -> 0
B15: Corretiva em Garantia | F15: SISP – 4.4 Manutenção Corretiva | G15: GAR | H15: 0 | J15: =SUMIF(Funções!$C$86:$C$188,Deflatores!G15,Funções!$H$86:$H$188) -> 0 | K15: =IF(H15="",COUNTIF(Funções!C$86:C$188,G15)*I15,H15*J15) -> 0
B16: Mudança de Plataforma - Linguagem de Programação | F16: SISP – 4.5.1 Mudança de Plataforma – Linguagem de Programação | G16: MLP | H16: 1 | J16: =SUMIF(Funções!$C$86:$C$188,Deflatores!G16,Funções!$H$86:$H$188) -> 0 | K16: =IF(H16="",COUNTIF(Funções!C$86:C$188,G16)*I16,H16*J16) -> 0
B17: Mudança de Plataforma - Banco de Dados (outro paradigma) | F17: SISP – 4.5.2 Mudança de Plataforma – Banco de Dados | G17: MBO | H17: 1 | J17: =SUMIF(Funções!$C$86:$C$188,Deflatores!G17,Funções!$H$86:$H$188) -> 0 | K17: =IF(H17="",COUNTIF(Funções!C$86:C$188,G17)*I17,H17*J17) -> 0
B18: Mudança de Plataforma - Banco de Dados (mesmo paradigma com alterações) | F18: SISP – 4.5.2 Mudança de Plataforma – Banco de Dados | G18: MBM | H18: 0.3 | J18: =SUMIF(Funções!$C$86:$C$188,Deflatores!G18,Funções!$H$86:$H$188) -> 0 | K18: =IF(H18="",COUNTIF(Funções!C$86:C$188,G18)*I18,H18*J18) -> 0
... B21: Atualização de Versão – Banco de Dados | F21: SISP – 4.6.3 Atualização de Versão – Banco de Dados | G21: ABD | H21: 0.3 | J21: =SUMIF(Funções!$C$86:$C$188,Deflatores!G21,Funções!$H$86:$H$188) -> 0 | K21: =IF(H21="",COUNTIF(Funções!C$86:C$188,G21)*I21,H21*J21) -> 0
B22: Manutenção Cosmética | F22: SISP – 4.7 Manutenção Cosmética | G22: COS | I22: 0.6 | J22: =SUMIF(Funções!$C$86:$C$188,Deflatores!G22,Funções!$H$86:$H$188) -> 0 | K22: =IF(H22="",COUNTIF(Funções!C$86:C$188,G22)*I22,H22*J22) -> 0
B23: Adaptação em Funcionalidades sem Alteração de Requisitos Funcionais (sem conhecimento do Fator de Impacto) | F23: SISP – 4.8 Adaptação em Funcionalidades sem Alteração de Requisitos Funcionais | G23: ARN | H23: 0.5 | J23: =SUMIF(Funções!$C$86:$C$188,Deflatores!G23,Funções!$H$86:$H$188) -> 0 | K23: =IF(H23="",COUNTIF(Funções!C$86:C$188,G23)*I23,H23*J23) -> 0
B24: Adaptação em Funcionalidades sem Alteração de Requisitos Funcionais (50%) (em função desenvolvida ou já alterada pela empresa atual) | F24: SISP – 4.8 Adaptação em Funcionalidades sem Alteração de Requisitos Funcionais | G24: ARN50 | H24: 0.5 | J24: =SUMIF(Funções!$C$86:$C$188,Deflatores!G24,Funções!$H$86:$H$188) -> 0 | K24: =IF(H24="",COUNTIF(Funções!C$86:C$188,G24)*I24,H24*J24) -> 0
B25: Adaptação em Funcionalidades sem Alteração de Requisitos Funcionais (75%) (em função não desenvolvida e ainda não alterada pela empresa atual) | F25: SISP – 4.8 Adaptação em Funcionalidades sem Alteração de Requisitos Funcionais | G25: ARN75 | H25: 0.75 | J25: =SUMIF(Funções!$C$86:$C$188,Deflatores!G25,Funções!$H$86:$H$188) -> 0 | K25: =IF(H25="",COUNTIF(Funções!C$86:C$188,G25)*I25,H25*J25) -> 0
B26: Atualização de Dados sem Consulta Prévia | F26: SISP – 4.9.1 Apuração Especial – Base de Dados | G26: ADS | H26: 1 | J26: =SUMIF(Funções!$C$86:$C$188,Deflatores!G26,Funções!$H$86:$H$188) -> 0 | K26: =IF(H26="",COUNTIF(Funções!C$86:C$188,G26)*I26,H26*J26) -> 0
B27: Consulta Prévia sem Atualização | F27: SISP – 4.9.1 Apuração Especial – Base de Dados | G27: CPA | H27: 1 | J27: =SUMIF(Funções!$C$86:$C$188,Deflatores!G27,Funções!$H$86:$H$188) -> 0 | K27: =IF(H27="",COUNTIF(Funções!C$86:C$188,G27)*I27,H27*J27) -> 0
B28: Atualização de Dados com Consulta Prévia | F28: SISP – 4.9.1 Apuração Especial – Base de Dados | G28: ADC | H28: 0.6 | J28: =SUMIF(Funções!$C$86:$C$188,Deflatores!G28,Funções!$H$86:$H$188) -> 0 | K28: =IF(H28="",COUNTIF(Funções!C$86:C$188,G28)*I28,H28*J28) -> 0
B29: Apuração Especial – Geração de Relatórios | F29: SISP – 4.9.2 Apuração Especial – Geração de Relatórios | G29: AGR | H29: 1 | J29: =SUMIF(Funções!$C$86:$C$188,Deflatores!G29,Funções!$H$86:$H$188) -> 0 | K29: =IF(H29="",COUNTIF(Funções!C$86:C$188,G29)*I29,H29*J29) -> 0
B30: Apuração Especial – Reexecução | F30: SISP – 4.9.3 Apuração Especial – Reexecução | G30: AER | H30: 0.1 | J30: =SUMIF(Funções!$C$86:$C$188,Deflatores!G30,Funções!$H$86:$H$188) -> 0 | K30: =IF(H30="",COUNTIF(Funções!C$86:C$188,G30)*I30,H30*J30) -> 0
B31: Atualização de Dados | F31: SISP – 4.10 Atualização de Dados | G31: ATD | H31: 0.1 | J31: =SUMIF(Funções!$C$86:$C$188,Deflatores!G31,Funções!$H$86:$H$188) -> 0 | K31: =IF(H31="",COUNTIF(Funções!C$86:C$188,G31)*I31,H31*J31) -> 0
B32: Manutenção de Documentação de Sistemas Legados | F32: SISP – 4.12 Manutenção de Documentação de Sistemas Legados | G32: MSL | H32: 0.25 | J32: =SUMIF(Funções!$C$86:$C$188,Deflatores!G32,Funções!$H$86:$H$188) -> 0 | K32: =IF(H32="",COUNTIF(Funções!C$86:C$188,G32)*I32,H32*J32) -> 0
B33: Verificação de Erros (Sem Documentação de Teste existente) | F33: SISP – 4.13 Verificação de Erros | G33: VES | H33: 0.2 | J33: =SUMIF(Funções!$C$86:$C$188,Deflatores!G33,Funções!$H$86:$H$188) -> 0 | K33: =IF(H33="",COUNTIF(Funções!C$86:C$188,G33)*I33,H33*J33) -> 0
B34: Verificação de Erros (Com Documentação de Teste existente) | F34: SISP – 4.13 Verificação de Erros | G34: VEC | H34: 0.15 | J34: =SUMIF(Funções!$C$86:$C$188,Deflatores!G34,Funções!$H$86:$H$188) -> 0 | K34: =IF(H34="",COUNTIF(Funções!C$86:C$188,G34)*I34,H34*J34) -> 0
... B36: Componente Interno Reusável | F36: SISP – 4.15 Componente Interno Reusável | G36: CIR | H36: 1 | J36: =SUMIF(Funções!$C$86:$C$188,Deflatores!G36,Funções!$H$86:$H$188) -> 0 | K36: =IF(H36="",COUNTIF(Funções!C$86:C$188,G36)*I36,H36*J36) -> 0
G37: . | J37: =SUMIF(Funções!$C$86:$C$188,Deflatores!G37,Funções!$H$86:$H$188) -> 0 | K37: =IF(H37="",COUNTIF(Funções!C$86:C$188,G37)*I37,H37*J37) -> 0 | L37: ALI
G38: . | J38: =SUMIF(Funções!$C$86:$C$188,Deflatores!G38,Funções!$H$86:$H$188) -> 0 | K38: =IF(H38="",COUNTIF(Funções!C$86:C$188,G38)*I38,H38*J38) -> 0 | L38: AIE
L39: EE
A40: Itens Não Mensuráveis | G40: Sigla | H40: Contribuição em PF Local | J40: Quantidade | K40: PF Local FS | L40: CE
A41: Contrato | B41: Descrição | F41: Origem | L41: SE
B42: Páginas Estáticas | F42: SISP – 4.11 Desenvolvimento, Manutenção e Publicação de Paginas Estáticas de Intranet, Internet ou Portal | G42: PAG | H42: 0.6 | J42: =COUNTIF(Funções!B$86:B$188,G42) -> 0 | K42: =SUMIF(Funções!B$86:B$188,$G42,Funções!K$86:K$188) -> 0 | L42: =""&G42 -> PAG
B43: Manutenção Cosmética (atrelada a algo não funcional) | F43: SISP – 4.7 Manutenção Cosmética | G43: COSNF | H43: 0.6 | J43: =COUNTIF(Funções!B$86:B$188,G43) -> 0 | K43: =SUMIF(Funções!B$86:B$188,$G43,Funções!K$86:K$188) -> 0 | L43: =""&G43 -> COSNF
B44: Dados de Código | G44: DC | H44: 0 | J44: =COUNTIF(Funções!B$86:B$188,G44) -> 0 | K44: =SUMIF(Funções!B$86:B$188,$G44,Funções!K$86:K$188) -> 0 | L44: =""&G44 -> DC
G45: . | J45: =COUNTIF(Funções!B$86:B$188,G45) -> 0 | K45: =SUMIF(Funções!B$86:B$188,$G45,Funções!K$86:K$188) -> 0 | L45: =""&G45 -> .
G46: . | J46: =COUNTIF(Funções!B$86:B$188,G46) -> 0 | K46: =SUMIF(Funções!B$86:B$188,$G46,Funções!K$86:K$188) -> 0 | L46: =""&G46 -> .
G47: . | J47: =COUNTIF(Funções!B$86:B$188,G47) -> 0 | K47: =SUMIF(Funções!B$86:B$188,$G47,Funções!K$86:K$188) -> 0 | L47: =""&G47 -> .
G48: . | J48: =COUNTIF(Funções!B$86:B$188,G48) -> 0 | K48: =SUMIF(Funções!B$86:B$188,$G48,Funções!K$86:K$188) -> 0 | L48: =""&G48 -> .
G49: . | J49: =COUNTIF(Funções!B$86:B$188,G49) -> 0 | K49: =SUMIF(Funções!B$86:B$188,$G49,Funções!K$86:K$188) -> 0 | L49: =""&G49 -> .
G50: . | J50: =COUNTIF(Funções!B$86:B$188,G50) -> 0 | K50: =SUMIF(Funções!B$86:B$188,$G50,Funções!K$86:K$188) -> 0 | L50: =""&G50 -> .
G51: . | J51: =COUNTIF(Funções!B$86:B$188,G51) -> 0 | K51: =SUMIF(Funções!B$86:B$188,$G51,Funções!K$86:K$188) -> 0 | L51: =""&G51 -> .
G52: . | J52: =COUNTIF(Funções!B$86:B$188,G52) -> 0 | K52: =SUMIF(Funções!B$86:B$188,$G52,Funções!K$86:K$188) -> 0 | L52: =""&G52 -> .
G53: . | J53: =COUNTIF(Funções!B$86:B$188,G53) -> 0 | K53: =SUMIF(Funções!B$86:B$188,$G53,Funções!K$86:K$188) -> 0 | L53: =""&G53 -> .
G54: . | J54: =COUNTIF(Funções!B$86:B$188,G54) -> 0 | K54: =SUMIF(Funções!B$86:B$188,$G54,Funções!K$86:K$188) -> 0 | L54: =""&G54 -> .
G55: . | J55: =COUNTIF(Funções!B$86:B$188,G55) -> 0 | K55: =SUMIF(Funções!B$86:B$188,$G55,Funções!K$86:K$188) -> 0 | L55: =""&G55 -> .
G56: . | J56: =COUNTIF(Funções!B$86:B$188,G56) -> 0 | K56: =SUMIF(Funções!B$86:B$188,$G56,Funções!K$86:K$188) -> 0 | L56: =""&G56 -> .
... G64: . | J64: =COUNTIF(Funções!B$86:B$188,G64) -> 0 | K64: =SUMIF(Funções!B$86:B$188,$G64,Funções!K$86:K$188) -> 0 | L64: =""&G64 -> .

Sheet Sumário 1
A1: Sumário da Contagem
A4: =Contagem!A5&" : "&Contagem!F5 -> Aplicação : | F4: =Contagem!A8&" : "&Contagem!F8 -> Projeto : SIABI - Sistema de Avaliação de Imóveis
A5: =Contagem!A9&" : "&Contagem!F9 -> Responsável : Luana Alves de Araujo Passos Aguiar | F5: =Contagem!A10&" : "&Contagem!F10 -> Revisor :
A6: =Contagem!A4&" : "&Contagem!F4 -> Empresa : Secretaria de Estado de Planejamento e Gestão de Mato Grosso | F6: ="Tipo de Contagem : "&Contagem!F6 -> Tipo de Contagem : Projeto de Desenvolvimento
A7: Tipo de Função | C7: Complexidade Funcional | G7: Total PF IFPUG por Complexidade | H7: % | J7: Total PF Local FS por tipo de manutenção básica | L7: %
B10: EE | C10: =COUNTIF(Funções!G86:G188,"EEL") -> 14 | E10: Baixa | F10: x 3 | G10: =C10*3 -> 42 | J10: =Deflatores!$G$4&"=" -> I= | K10: =SUMIF(Funções!$J$86:$J$188,"EE"&Deflatores!G4,Funções!$L$86:$L$188) -> 124
C11: =COUNTIF(Funções!G86:G188,"EEA") -> 4 | E11: Média | F11: x 4 | G11: =C11*4 -> 16 | J11: =Deflatores!$G$5&"=" -> A= | K11: =SUMIF(Funções!$J$86:$J$188,"EE"&Deflatores!G5,Funções!$L$86:$L$188) -> 0
C12: =COUNTIF(Funções!G86:G188,"EEH") -> 11 | E12: Alta | F12: x 6 | G12: =C12*6 -> 66 | J12: =Deflatores!$G$6&"=" -> E= | K12: =SUMIF(Funções!$J$86:$J$188,"EE"&Deflatores!G6,Funções!$L$86:$L$188) -> 0
B14: Qtd Total | C14: =SUM(C10:C12) -> 29 | F14: Total | G14: =SUM(G10:G12) -> 124 | H14: =IF($G$45<>0,G14/$G$45,"") -> 0.37125749 | K14: =SUM(K10:K13) -> 124 | L14: =IF('Sumário 2'!L11<>0,K14/'Sumário 2'!L11,"") -> 0.024367238
B17: SE | C17: =COUNTIF(Funções!G86:G188,"SEL") -> 0 | E17: Baixa | F17: x 4 | G17: =C17*4 -> 0 | J17: =Deflatores!$G$4&"=" -> I= | K17: =SUMIF(Funções!$J$86:$J$188,"SE"&Deflatores!$G$4,Funções!$L$86:$L$188) -> 21
C18: =COUNTIF(Funções!G86:G188,"SEA") -> 0 | E18: Média | F18: x 5 | G18: =C18*5 -> 0 | J18: =Deflatores!$G$5&"=" -> A= | K18: =SUMIF(Funções!$J$86:$J$188,"SE"&Deflatores!$G$5,Funções!$L$86:$L$188) -> 0
C19: =COUNTIF(Funções!G86:G188,"SEH") -> 3 | E19: Alta | F19: x 7 | G19: =C19*7 -> 21 | J19: =Deflatores!$G$6&"=" -> E= | K19: =SUMIF(Funções!$J$86:$J$188,"SE"&Deflatores!$G$6,Funções!$L$86:$L$188) -> 0
B21: Qtd Total | C21: =SUM(C17:C19) -> 3 | F21: Total | G21: =SUM(G17:G19) -> 21 | H21: =IF($G$45<>0,G21/$G$45,"") -> 0.062874251 | K21: =SUM(K17:K20) -> 21 | L21: =IF('Sumário 2'!L11<>0,K21/'Sumário 2'!L11,"") -> 0.0041267096
B24: CE | C24: =COUNTIF(Funções!G86:G188,"CEL") -> 23 | E24: Baixa | F24: x 3 | G24: =C24*3 -> 69 | J24: =Deflatores!$G$4&"=" -> I= | K24: =SUMIF(Funções!$J$86:$J$188,"CE"&Deflatores!$G$4,Funções!$L$86:$L$188) -> 119
C25: =COUNTIF(Funções!G86:G188,"CEA") -> 5 | E25: Média | F25: x 4 | G25: =C25*4 -> 20 | J25: =Deflatores!$G$5&"=" -> A= | K25: =SUMIF(Funções!$J$86:$J$188,"CE"&Deflatores!$G$5,Funções!$L$86:$L$188) -> 0
C26: =COUNTIF(Funções!G86:G188,"CEH") -> 6 | E26: Alta | F26: x 6 | G26: =C26*6 -> 36 | J26: =Deflatores!$G$6&"=" -> E= | K26: =SUMIF(Funções!$J$86:$J$188,"CE"&Deflatores!$G$6,Funções!$L$86:$L$188) -> 2.4
B28: Qtd Total | C28: =SUM(C24:C26) -> 34 | F28: Total | G28: =SUM(G24:G26) -> 125 | H28: =IF($G$45<>0,G28/$G$45,"") -> 0.3742515 | K28: =SUM(K24:K27) -> 121.4 | L28: =IF('Sumário 2'!L11<>0,K28/'Sumário 2'!L11,"") -> 0.023856312
B31: ALI | C31: =COUNTIF(Funções!G86:G188,"ALIL") -> 7 | E31: Baixa | F31: x 7 | G31: =C31*7 -> 49 | J31: =Deflatores!$G$4&"=" -> I= | K31: =SUMIF(Funções!$J$86:$J$188,"ALI"&Deflatores!$G$4,Funções!$L$86:$L$188) -> 59
C32: =COUNTIF(Funções!G86:G188,"ALIA") -> 1 | E32: Média | F32: x 10 | G32: =C32*10 -> 10 | J32: =Deflatores!$G$5&"=" -> A= | K32: =SUMIF(Funções!$J$86:$J$188,"ALI"&Deflatores!$G$5,Funções!$L$86:$L$188) -> 0
C33: =COUNTIF(Funções!G86:G188,"ALIH") -> 0 | E33: Alta | F33: x 15 | G33: =C33*15 -> 0 | J33: =Deflatores!$G$6&"=" -> E= | K33: =SUMIF(Funções!$J$86:$J$188,"ALI"&Deflatores!$G$6,Funções!$L$86:$L$188) -> 0
B35: Qtd Total | C35: =SUM(C31:C33) -> 8 | F35: Total | G35: =SUM(G31:G33) -> 59 | H35: =IF($G$45<>0,G35/$G$45,"") -> 0.17664671 | K35: =SUM(K31:K34) -> 59 | L35: =IF('Sumário 2'!L11<>0,K35/'Sumário 2'!L11,"") -> 0.011594089
B38: AIE | C38: =COUNTIF(Funções!G86:G188,"AIEL") -> 1 | E38: Baixa | F38: x 5 | G38: =C38*5 -> 5 | J38: =Deflatores!$G$4&"=" -> I= | K38: =SUMIF(Funções!$J$86:$J$188,"AIE"&Deflatores!$G$4,Funções!$L$86:$L$188) -> 5
C39: =COUNTIF(Funções!G86:G188,"AIEA") -> 0 | E39: Média | F39: x 7 | G39: =C39*7 -> 0 | J39: =Deflatores!$G$5&"=" -> A= | K39: =SUMIF(Funções!$J$86:$J$188,"AIE"&Deflatores!$G$5,Funções!$L$86:$L$188) -> 0
C40: =COUNTIF(Funções!G86:G188,"AIEH") -> 0 | E40: Alta | F40: x 10 | G40: =C40*10 -> 0 | J40: =Deflatores!$G$6&"=" -> E= | K40: =SUMIF(Funções!$J$86:$J$188,"AIE"&Deflatores!$G$6,Funções!$L$86:$L$188) -> 0
B42: Qtd Total | C42: =SUM(C38:C40) -> 1 | F42: Total | G42: =SUM(G38:G40) -> 5 | H42: =IF($G$45<>0,G42/$G$45,"") -> 0.01497006 | K42: =SUM(K38:K41) -> 5 | L42: =IF('Sumário 2'!L11<>0,K42/'Sumário 2'!L11,"") -> 0.00098254991
B45: Total PF não ajustados (contagem detalhada) | G45: =SUM(G14+G21+G28+G35+G42) -> 334
B46: Total PF não ajustados (contagem estimativa) | G46: =(C10+C11+C12)*4+(C17+C18+C19)*5+(C24+C25+C26)*4+(C31+C32+C33)*7+(C38+C39+C40)*5 -> 328
B47: Total PF não ajustados (contagem indicativa) | G47: =(C31+C32+C33)*35+(C38+C39+C40)*15 -> 295

Sheet Sumário 2
A1: Sumário por Deflatores e Itens não mensuráveis
A4: =Contagem!A5&" : "&Contagem!F5 -> Aplicação : | F4: =Contagem!A8&" : "&Contagem!F8 -> Projeto : SIABI - Sistema de Avaliação de Imóveis
A5: =Contagem!A9&" : "&Contagem!F9 -> Responsável : Luana Alves de Araujo Passos Aguiar | F5: =Contagem!A10&" : "&Contagem!F10 -> Revisor :
A6: =Contagem!A4&" : "&Contagem!F4 -> Empresa : Secretaria de Estado de Planejamento e Gestão de Mato Grosso | F6: ="Tipo de Contagem : "&Contagem!F6 -> Tipo de Contagem : Projeto de Desenvolvimento
B9: Deflatores aplicados a Itens Funcionais | E9: Quantidade | F9: PF IFPUG | G9: Deflator | H9: Contrib. Fixa | I9: PF Local da FS | J9: % LOCAL
B10: =""&Deflatores!B4 -> Inclusão | D10: =""&Deflatores!G4 -> I | E10: =IF(D10="","",COUNTIF(Funções!C$86:C$188,D10)) -> 83 | F10: =SUMIF(Funções!$C$86:$C$188,Deflatores!G4,Funções!$H$86:$H$188) -> 340 | G10: =IF(ISBLANK(Deflatores!H4),"",Deflatores!H4) -> 1 | H10: =IF(ISBLANK(Deflatores!I4),"",Deflatores!I4) | I10: =IF(F10=0,Deflatores!K4,F10*G10) -> 340 | J10: =IF($L$11<>0,I10/$L$11,"") -> 0.066813394 | L10: PF Local da FS
B11: =""&Deflatores!B5 -> Alteração (sem conhecimento do Fator de Impacto) | D11: =""&Deflatores!G5 -> A | E11: =IF(D11="","",COUNTIF(Funções!C$86:C$188,D11)) -> 0 | F11: =SUMIF(Funções!$C$86:$C$188,Deflatores!G5,Funções!$H$86:$H$188) -> 0 | G11: =IF(ISBLANK(Deflatores!H5),"",Deflatores!H5) -> 0.5 | H11: =IF(ISBLANK(Deflatores!I5),"",Deflatores!I5) | I11: =IF(F11=0,Deflatores!K5,F11*G11) -> 0 | J11: =IF($L$11<>0,I11/$L$11,"") -> 0 | L11: =Contagem!Q6 -> 5088.8
B12: =""&Deflatores!B6 -> Exclusão | D12: =""&Deflatores!G6 -> E | E12: =IF(D12="","",COUNTIF(Funções!C$86:C$188,D12)) -> 2 | F12: =SUMIF(Funções!$C$86:$C$188,Deflatores!G6,Funções!$H$86:$H$188) -> 6 | G12: =IF(ISBLANK(Deflatores!H6),"",Deflatores!H6) -> 0.4 | H12: =IF(ISBLANK(Deflatores!I6),"",Deflatores!I6) | I12: =IF(F12=0,Deflatores!K6,F12*G12) -> 2.4 | J12: =IF($L$11<>0,I12/$L$11,"") -> 0.00047162396
B13: =""&Deflatores!B7 -> Alteração (50%) de função desenvolvida ou já alterada pela empresa atual | D13: =""&Deflatores!G7 -> A50 | E13: =IF(D13="","",COUNTIF(Funções!C$86:C$188,D13)) -> 0 | F13: =SUMIF(Funções!$C$86:$C$188,Deflatores!G7,Funções!$H$86:$H$188) -> 0 | G13: =IF(ISBLANK(Deflatores!H7),"",Deflatores!H7) -> 0.5 | H13: =IF(ISBLANK(Deflatores!I7),"",Deflatores!I7) | I13: =Deflatores!K7 -> 0 | J13: =IF($L$11<>0,I13/$L$11,"") -> 0 | L13: Total IFPUG
B14: =""&Deflatores!B8 -> Alteração (75%) de função não desenv. e ainda não alterada pela empresa atual | D14: =""&Deflatores!G8 -> A75 | E14: =IF(D14="","",COUNTIF(Funções!C$86:C$188,D14)) -> 0 | F14: =SUMIF(Funções!$C$86:$C$188,Deflatores!G8,Funções!$H$86:$H$188) -> 0 | G14: =IF(ISBLANK(Deflatores!H8),"",Deflatores!H8) -> 0.75 | H14: =IF(ISBLANK(Deflatores!I8),"",Deflatores!I8) | I14: =Deflatores!K8 -> 0 | J14: =IF($L$11<>0,I14/$L$11,"") -> 0 | L14: =Contagem!Q4 -> 5222
B15: =""&Deflatores!B9 -> Alteração (75%+15%): o mesmo acima + redocumentar a função | D15: =""&Deflatores!G9 -> A90 | E15: =IF(D15="","",COUNTIF(Funções!C$86:C$188,D15)) -> 0 | F15: =SUMIF(Funções!$C$86:$C$188,Deflatores!G9,Funções!$H$86:$H$188) -> 0 | G15: =IF(ISBLANK(Deflatores!H9),"",Deflatores!H9) -> 0.9 | H15: =IF(ISBLANK(Deflatores!I9),"",Deflatores!I9) | I15: =Deflatores!K9 -> 0 | J15: =IF($L$11<>0,I15/$L$11,"") -> 0
B16: =""&Deflatores!B10 -> Migração de Dados | D16: =""&Deflatores!G10 -> PMD | E16: =IF(D16="","",COUNTIF(Funções!C$86:C$188,D16)) -> 0 | F16: =SUMIF(Funções!$C$86:$C$188,Deflatores!G10,Funções!$H$86:$H$188) -> 0 | G16: =IF(ISBLANK(Deflatores!H10),"",Deflatores!H10) -> 1 | H16: =IF(ISBLANK(Deflatores!I10),"",Deflatores!I10) | I16: =Deflatores!K10 -> 0 | J16: =IF($L$11<>0,I16/$L$11,"") -> 0
B17: =""&Deflatores!B11 -> Corretiva (sem conhecimento do Fator de Impacto) | D17: =""&Deflatores!G11 -> COR | E17: =IF(D17="","",COUNTIF(Funções!C$86:C$188,D17)) -> 0 | F17: =SUMIF(Funções!$C$86:$C$188,Deflatores!G11,Funções!$H$86:$H$188) -> 0 | G17: =IF(ISBLANK(Deflatores!H11),"",Deflatores!H11) -> 0.5 | H17: =IF(ISBLANK(Deflatores!I11),"",Deflatores!I11) | I17: =Deflatores!K11 -> 0 | J17: =IF($L$11<>0,I17/$L$11,"") -> 0
B18: =""&Deflatores!B12 -> Corretiva (50%) - Fora da garantia (mesma empresa) | D18: =""&Deflatores!G12 -> COR50 | E18: =IF(D18="","",COUNTIF(Funções!C$86:C$188,D18)) -> 0 | F18: =SUMIF(Funções!$C$86:$C$188,Deflatores!G12,Funções!$H$86:$H$188) -> 0 | G18: =IF(ISBLANK(Deflatores!H12),"",Deflatores!H12) -> 0.5 | H18: =IF(ISBLANK(Deflatores!I12),"",Deflatores!I12) | I18: =Deflatores!K12 -> 0 | J18: =IF($L$11<>0,I18/$L$11,"") -> 0
B19: =""&Deflatores!B13 -> Corretiva (75%) - Fora da garantia (outra empresa) | D19: =""&Deflatores!G13 -> COR75 | E19: =IF(D19="","",COUNTIF(Funções!C$86:C$188,D19)) -> 0 | F19: =SUMIF(Funções!$C$86:$C$188,Deflatores!G13,Funções!$H$86:$H$188) -> 0 | G19: =IF(ISBLANK(Deflatores!H13),"",Deflatores!H13) -> 0.75 | H19: =IF(ISBLANK(Deflatores!I13),"",Deflatores!I13) | I19: =Deflatores!K13 -> 0 | J19: =IF($L$11<>0,I19/$L$11,"") -> 0
B20: =""&Deflatores!B14 -> Corretiva (75%+15%) - Fora da garantia (outra empresa) + Redocumentação | D20: =""&Deflatores!G14 -> COR90 | E20: =IF(D20="","",COUNTIF(Funções!C$86:C$188,D20)) -> 0 | F20: =SUMIF(Funções!$C$86:$C$188,Deflatores!G14,Funções!$H$86:$H$188) -> 0 | G20: =IF(ISBLANK(Deflatores!H14),"",Deflatores!H14) -> 0.9 | H20: =IF(ISBLANK(Deflatores!I14),"",Deflatores!I14) | I20: =Deflatores!K14 -> 0 | J20: =IF($L$11<>0,I20/$L$11,"") -> 0
B21: =""&Deflatores!B15 -> Corretiva em Garantia | D21: =""&Deflatores!G15 -> GAR | E21: =IF(D21="","",COUNTIF(Funções!C$86:C$188,D21)) -> 0 | F21: =SUMIF(Funções!$C$86:$C$188,Deflatores!G15,Funções!$H$86:$H$188) -> 0 | G21: =IF(ISBLANK(Deflatores!H15),"",Deflatores!H15) -> 0 | H21: =IF(ISBLANK(Deflatores!I15),"",Deflatores!I15) | I21: =Deflatores!K15 -> 0 | J21: =IF($L$11<>0,I21/$L$11,"") -> 0
B22: =""&Deflatores!B16 -> Mudança de Plataforma - Linguagem de Programação | D22: =""&Deflatores!G16 -> MLP | E22: =IF(D22="","",COUNTIF(Funções!C$86:C$188,D22)) -> 0 | F22: =SUMIF(Funções!$C$86:$C$188,Deflatores!G16,Funções!$H$86:$H$188) -> 0 | G22: =IF(ISBLANK(Deflatores!H16),"",Deflatores!H16) -> 1 | H22: =IF(ISBLANK(Deflatores!I16),"",Deflatores!I16) | I22: =Deflatores!K16 -> 0 | J22: =IF($L$11<>0,I22/$L$11,"") -> 0
B23: =""&Deflatores!B17 -> Mudança de Plataforma - Banco de Dados (outro paradigma) | D23: =""&Deflatores!G17 -> MBO | E23: =IF(D23="","",COUNTIF(Funções!C$86:C$188,D23)) -> 0 | F23: =SUMIF(Funções!$C$86:$C$188,Deflatores!G17,Funções!$H$86:$H$188) -> 0 | G23: =IF(ISBLANK(Deflatores!H17),"",Deflatores!H17) -> 1 | H23: =IF(ISBLANK(Deflatores!I17),"",Deflatores!I17) | I23: =Deflatores!K17 -> 0 | J23: =IF($L$11<>0,I23/$L$11,"") -> 0
B24: =""&Deflatores!B18 -> Mudança de Plataforma - Banco de Dados (mesmo paradigma com alterações) | D24: =""&Deflatores!G18 -> MBM | E24: =IF(D24="","",COUNTIF(Funções!C$86:C$188,D24)) -> 0 | F24: =SUMIF(Funções!$C$86:$C$188,Deflatores!G18,Funções!$H$86:$H$188) -> 0 | G24: =IF(ISBLANK(Deflatores!H18),"",Deflatores!H18) -> 0.3 | H24: =IF(ISBLANK(Deflatores!I18),"",Deflatores!I18) | I24: =Deflatores!K18 -> 0 | J24: =IF($L$11<>0,I24/$L$11,"") -> 0
B25: =""&Deflatores!B19 -> Atualização de Versão – Linguagem de Programação | D25: =""&Deflatores!G19 -> ALP | E25: =IF(D25="","",COUNTIF(Funções!C$86:C$188,D25)) -> 0 | F25: =SUMIF(Funções!$C$86:$C$188,Deflatores!G19,Funções!$H$86:$H$188) -> 0 | G25: =IF(ISBLANK(Deflatores!H19),"",Deflatores!H19) -> 0.3 | H25: =IF(ISBLANK(Deflatores!I19),"",Deflatores!I19) | I25: =Deflatores!K19 -> 0 | J25: =IF($L$11<>0,I25/$L$11,"") -> 0
B26: =""&Deflatores!B20 -> Atualização de Versão – Browser | D26: =""&Deflatores!G20 -> AVB | E26: =IF(D26="","",COUNTIF(Funções!C$86:C$188,D26)) -> 0 | F26: =SUMIF(Funções!$C$86:$C$188,Deflatores!G20,Funções!$H$86:$H$188) -> 0 | G26: =IF(ISBLANK(Deflatores!H20),"",Deflatores!H20) -> 0.3 | H26: =IF(ISBLANK(Deflatores!I20),"",Deflatores!I20) | I26: =Deflatores!K20 -> 0 | J26: =IF($L$11<>0,I26/$L$11,"") -> 0
... B44: =""&Deflatores!B38 | D44: =""&Deflatores!G38 -> . | E44: =IF(D44="","",COUNTIF(Funções!C$86:C$188,D44)) -> 0 | F44: =SUMIF(Funções!$C$86:$C$188,Deflatores!G38,Funções!$H$86:$H$188) -> 0 | G44: =IF(ISBLANK(Deflatores!H38),"",Deflatores!H38) | H44: =IF(ISBLANK(Deflatores!I38),"",Deflatores!I38) | I44: =Deflatores!K38 -> 0 | J44: =IF($L$11<>0,I44/$L$11,"") -> 0
B46: Itens não Funcionais (Tipo de Função) | E46: Quantidade | H46: Contrib. Fixa | I46: PF Local da FS | J46: % LOCAL
B47: =""&Deflatores!B42 -> Páginas Estáticas | D47: =""&Deflatores!G42 -> PAG | E47: =Deflatores!J42 -> 0 | H47: =IF(ISBLANK(Deflatores!H42),"",Deflatores!H42) -> 0.6 | I47: =IF(ISNUMBER(H47),E47*H47,"") -> 0 | J47: =IF(ISNUMBER(I47),IF($L$11<>0,I47/$L$11,""),"") -> 0
B48: =""&Deflatores!B43 -> Manutenção Cosmética (atrelada a algo não funcional) | D48: =""&Deflatores!G43 -> COSNF | E48: =Deflatores!J43 -> 0 | H48: =IF(ISBLANK(Deflatores!H43),"",Deflatores!H43) -> 0.6 | I48: =IF(ISNUMBER(H48),E48*H48,"") -> 0 | J48: =IF(ISNUMBER(I48),IF($L$11<>0,I48/$L$11,""),"") -> 0
B49: =""&Deflatores!B44 -> Dados de Código | D49: =""&Deflatores!G44 -> DC | E49: =Deflatores!J44 -> 0 | H49: =IF(ISBLANK(Deflatores!H44),"",Deflatores!H44) -> 0 | I49: =IF(ISNUMBER(H49),E49*H49,"") -> 0 | J49: =IF(ISNUMBER(I49),IF($L$11<>0,I49/$L$11,""),"") -> 0
B50: =""&Deflatores!B45 | D50: =""&Deflatores!G45 -> . | E50: =Deflatores!J45 -> 0 | H50: =IF(ISBLANK(Deflatores!H45),"",Deflatores!H45) | I50: =IF(ISNUMBER(H50),E50*H50,"") | J50: =IF(ISNUMBER(I50),IF($L$11<>0,I50/$L$11,""),"")
B51: =""&Deflatores!B46 | D51: =""&Deflatores!G46 -> . | E51: =Deflatores!J46 -> 0 | H51: =IF(ISBLANK(Deflatores!H46),"",Deflatores!H46) | I51: =IF(ISNUMBER(H51),E51*H51,"") | J51: =IF(ISNUMBER(I51),IF($L$11<>0,I51/$L$11,""),"")
B52: =""&Deflatores!B47 | D52: =""&Deflatores!G47 -> . | E52: =Deflatores!J47 -> 0 | H52: =IF(ISBLANK(Deflatores!H47),"",Deflatores!H47) | I52: =IF(ISNUMBER(H52),E52*H52,"") | J52: =IF(ISNUMBER(I52),IF($L$11<>0,I52/$L$11,""),"")
B53: =""&Deflatores!B48 | D53: =""&Deflatores!G48 -> . | E53: =Deflatores!J48 -> 0 | H53: =IF(ISBLANK(Deflatores!H48),"",Deflatores!H48) | I53: =IF(ISNUMBER(H53),E53*H53,"") | J53: =IF(ISNUMBER(I53),IF($L$11<>0,I53/$L$11,""),"")
B54: =""&Deflatores!B49 | D54: =""&Deflatores!G49 -> . | E54: =Deflatores!J49 -> 0 | H54: =IF(ISBLANK(Deflatores!H49),"",Deflatores!H49) | I54: =IF(ISNUMBER(H54),E54*H54,"") | J54: =IF(ISNUMBER(I54),IF($L$11<>0,I54/$L$11,""),"")
B55: =""&Deflatores!B50 | D55: =""&Deflatores!G50 -> . | E55: =Deflatores!J50 -> 0 | H55: =IF(ISBLANK(Deflatores!H50),"",Deflatores!H50) | I55: =IF(ISNUMBER(H55),E55*H55,"") | J55: =IF(ISNUMBER(I55),IF($L$11<>0,I55/$L$11,""),"")
B56: =""&Deflatores!B51 | D56: =""&Deflatores!G51 -> . | E56: =Deflatores!J51 -> 0 | H56: =IF(ISBLANK(Deflatores!H51),"",Deflatores!H51) | I56: =IF(ISNUMBER(H56),E56*H56,"") | J56: =IF(ISNUMBER(I56),IF($L$11<>0,I56/$L$11,""),"")
B57: =""&Deflatores!B52 | D57: =""&Deflatores!G52 -> . | E57: =Deflatores!J52 -> 0 | H57: =IF(ISBLANK(Deflatores!H52),"",Deflatores!H52) | I57: =IF(ISNUMBER(H57),E57*H57,"") | J57: =IF(ISNUMBER(I57),IF($L$11<>0,I57/$L$11,""),"")
B58: =""&Deflatores!B53 | D58: =""&Deflatores!G53 -> . | E58: =Deflatores!J53 -> 0 | H58: =IF(ISBLANK(Deflatores!H53),"",Deflatores!H53) | I58: =IF(ISNUMBER(H58),E58*H58,"") | J58: =IF(ISNUMBER(I58),IF($L$11<>0,I58/$L$11,""),"")
... B69: =""&Deflatores!B64 | D69: =""&Deflatores!G64 -> . | E69: =Deflatores!J64 -> 0 | H69: =IF(ISBLANK(Deflatores!H64),"",Deflatores!H64) | I69: =IF(ISNUMBER(H69),E69*H69,"") | J69: =IF(ISNUMBER(I69),IF($L$11<>0,I69/$L$11,""),"")
